Workbook

Sheet Cover
B2: 5-YEAR REVENUE FORECAST MODEL
B3: RetailPro Group | Phoenix, AZ | Portfolio Sample (Illustrative)
B4: 12 Locations | 3 Scenarios | Monthly Seasonality | Sensitivity Analysis | Auto-Updating Actuals
B8: ='Revenue Forecast'!G12 -> 46916.121 | D8: ='Revenue Forecast'!C17 -> 0.33636364 | F8: 3 Scenarios
B9: FY2030 Base Revenue | D9: FY2026 Base Growth | F9: Conservative / Base / Aggressive
B13: PROJECT DETAILS
B14: CLIENT | E14: DURATION
B15: RetailPro Group — Phoenix, AZ (Illustrative Sample) | E15: 7 Days
B16: TOOLS USED | E16: ENGAGEMENT
B17: Excel, Forecast Functions, Scenario Manager | E17: Portfolio Sample
B18: DELIVERABLES | E18: STANDARDS
B19: 3 Scenarios - Sensitivity Tables - Monthly Dashboard - Auto-Updating Actuals | E19: US GAAP
B20: IMPACT | E20: PREPARER
B21: 34% more accurate than previous manual forecasts — used in board presentations | E21: Muhammad Zeenat Ullah | CA Finalist | Ex-KPMG | QBO ProAdvisor
B23: Prepared by: Muhammad Zeenat Ullah | CA Finalist (ICAP) | Ex-KPMG | QBO Pro Advisor | This is an illustrative sample model. Client and financial data are fictional.

Sheet Assumptions
A1: MODEL ASSUMPTIONS
A2: RetailPro Group | Phoenix, AZ | Portfolio Sample (Illustrative)
A3: BLUE = hardcoded inputs. Change any blue cell to update the full model.
A5: Prepared by: Muhammad Zeenat Ullah | CA Finalist (ICAP) | Ex-KPMG | QBO Pro Advisor | Excel Expert | zeenatullah.bookkeeper@gmail.com | +44 7577 845321 (WhatsApp Only)
A7: ASSUMPTION | B7: CONSERVATIVE | C7: BASE CASE | D7: AGGRESSIVE | E7: NOTES
A9: GENERAL ASSUMPTIONS
A10: Base Year Revenue — FY2025E ($000s) | B10: 19800 | C10: n/a | D10: n/a | E10: Same for all scenarios
A11: Starting Store Count (FY2025E) | B11: 12 | C11: n/a | D11: n/a | E11: 12 Phoenix metro locations as of Jan 2026
A13: SAME-STORE SALES GROWTH RATE — By Year
A14: YEAR | B14: CONSERVATIVE | C14: BASE CASE | D14: AGGRESSIVE | E14: COMMENTARY
A15: FY2026 | B15: 0.03 | C15: 0.1 | D15: 0.15 | E15: Base: new product lines + loyalty program launch
A16: FY2027 | B16: 0.03 | C16: 0.08 | D16: 0.13 | E16: Maturing stores; base normalises; agg sustains
A17: FY2028 | B17: 0.02 | C17: 0.07 | D17: 0.12 | E17: Con: macro headwinds; Base: steady; Agg: premium
A18: FY2029 | B18: 0.02 | C18: 0.06 | D18: 0.11 | E18: Late-cycle moderation across scenarios
A19: FY2030 | B19: 0.02 | C19: 0.05 | D19: 0.1 | E19: Terminal growth converging toward long-run retail avg
A22: YEAR | B22: CONSERVATIVE | C22: BASE CASE | D22: AGGRESSIVE | E22: LOCATION PIPELINE
A23: FY2026 | B23: 1 | C23: 4 | D23: 5 | E23: Base: Chandler, Tempe North, Ahwatukee, Scottsdale South
A24: FY2027 | B24: 1 | C24: 3 | D24: 5 | E24: Base: Mesa East, Queen Creek 2, North Scottsdale
A25: FY2028 | B25: 1 | C25: 3 | D25: 4 | E25: Conservative pace; Base targets suburban expansion
A26: FY2029 | B26: 0 | C26: 2 | D26: 3 | E26: Base: Sun Lakes, South Phoenix
A27: FY2030 | B27: 0 | C27: 2 | D27: 3 | E27: Base: Paradise Valley, Gilbert East
A29: NEW STORE ECONOMICS
A30: Average Revenue Per New Store — Full Year ($000s) | B30: 900 | C30: 1800 | D30: 2200 | E30: Tier: Con=suburban, Base=metro, Agg=flagship
A31: Year-1 Revenue Ramp Factor (% of avg, opening year) | B31: 0.5 | C31: 0.65 | D31: 0.75 | E31: Partial-year effect + soft opening; Year 2+ = full run-rate
A33: MONTHLY SEASONALITY INDICES (sum = 12.00)
A34: MONTH | B34: INDEX | C34: n/a | D34: n/a | E34: RATIONALE
A35: January | B35: 0.72 | C35: n/a | D35: n/a | E35: Post-holiday lull; winter clearance
A36: February | B36: 0.78 | C36: n/a | D36: n/a | E36: Valentine's Day lift; below avg
A37: March | B37: 0.9 | C37: n/a | D37: n/a | E37: Spring refresh; home goods uptick
A38: April | B38: 0.92 | C38: n/a | D38: n/a | E38: Tax refund spending; spring season
A39: May | B39: 0.95 | C39: n/a | D39: n/a | E39: Mother's Day + outdoor products
A40: June | B40: 0.92 | C40: n/a | D40: n/a | E40: Summer slowdown begins; AZ heat
A41: July | B41: 0.89 | C41: n/a | D41: n/a | E41: Lowest traffic; peak summer heat
A42: August | B42: 0.91 | C42: n/a | D42: n/a | E42: Back-to-school partial recovery
A43: September | B43: 0.95 | C43: n/a | D43: n/a | E43: Fall refresh; cooler weather
A44: October | B44: 1.08 | C44: n/a | D44: n/a | E44: Pre-holiday build; home decor
A45: November | B45: 1.38 | C45: n/a | D45: n/a | E45: Black Friday; peak season begins
A46: December | B46: 1.6 | C46: n/a | D46: n/a | E46: Peak holiday; gift cards + Christmas
A47: Sum Check — Must Equal 12.00 | B47: =SUM(B35:B46) -> 12
A49: HOW THE MODEL WORKS: Revenue = Prior Year Revenue × (1 + SSS Growth) + New Stores × Avg Store Revenue × Year-1 Ramp. Monthly Revenue = Annual × Seasonal Index / 12. All blue cells are inputs — change any to update the full model automatically.

Sheet Revenue Forecast
A1: 5-YEAR REVENUE FORECAST — THREE SCENARIOS
A2: RetailPro Group | Phoenix, AZ | Portfolio Sample (Illustrative)
A3: FY2025E–FY2030 | USD $000s | All figures linked to Assumptions | Change any input → all numbers update
A5: Muhammad Zeenat Ullah | CA Finalist (ICAP) | Ex-KPMG | QBO Pro Advisor | Excel Expert | zeenatullah.bookkeeper@gmail.com | +44 7577 845321 (WhatsApp Only)
B7: FY2025E | C7: FY2026 | D7: FY2027 | E7: FY2028 | F7: FY2029 | G7: FY2030 | H7: 5-YR CAGR
A9: SECTION 1 | TOTAL NET REVENUE ($000s)
A10: SCENARIO | B10: BASE YEAR | C10: FY2026 | D10: FY2027 | E10: FY2028 | F10: FY2029 | G10: FY2030 | H10: CAGR
A11: Conservative | B11: =Assumptions!B10 -> 19800 | C11: =Assumptions!B10*(1+Assumptions!B15)+Assumptions!B23*Assumptions!B30*Assumptions!B31 -> 20844 | D11: =C11*(1+Assumptions!B16)+Assumptions!B24*Assumptions!B30*Assumptions!B31 -> 21919.32 | E11: =D11*(1+Assumptions!B17)+Assumptions!B25*Assumptions!B30*Assumptions!B31 -> 22807.706 | F11: =E11*(1+Assumptions!B18)+Assumptions!B26*Assumptions!B30*Assumptions!B31 -> 23263.861 | G11: =F11*(1+Assumptions!B19)+Assumptions!B27*Assumptions!B30*Assumptions!B31 -> 23729.138 | H11: =(G11/Assumptions!B10)^(1/5)-1 -> 0.036867718
A12: Base Case | B12: =Assumptions!B10 -> 19800 | C12: =Assumptions!B10*(1+Assumptions!C15)+Assumptions!C23*Assumptions!C30*Assumptions!C31 -> 26460 | D12: =C12*(1+Assumptions!C16)+Assumptions!C24*Assumptions!C30*Assumptions!C31 -> 32086.8 | E12: =D12*(1+Assumptions!C17)+Assumptions!C25*Assumptions!C30*Assumptions!C31 -> 37842.876 | F12: =E12*(1+Assumptions!C18)+Assumptions!C26*Assumptions!C30*Assumptions!C31 -> 42453.449 | G12: =F12*(1+Assumptions!C19)+Assumptions!C27*Assumptions!C30*Assumptions!C31 -> 46916.121 | H12: =(G12/Assumptions!B10)^(1/5)-1 -> 0.18831446
A13: Aggressive | B13: =Assumptions!B10 -> 19800 | C13: =Assumptions!B10*(1+Assumptions!D15)+Assumptions!D23*Assumptions!D30*Assumptions!D31 -> 31020 | D13: =C13*(1+Assumptions!D16)+Assumptions!D24*Assumptions!D30*Assumptions!D31 -> 43302.6 | E13: =D13*(1+Assumptions!D17)+Assumptions!D25*Assumptions!D30*Assumptions!D31 -> 55098.912 | F13: =E13*(1+Assumptions!D18)+Assumptions!D26*Assumptions!D30*Assumptions!D31 -> 66109.792 | G13: =F13*(1+Assumptions!D19)+Assumptions!D27*Assumptions!D30*Assumptions!D31 -> 77670.772 | H13: =(G13/Assumptions!B10)^(1/5)-1 -> 0.31437257
A15: SECTION 2 | YEAR-OVER-YEAR GROWTH RATE
A16: Conservative | B16: n/a | C16: =C11/B11-1 -> 0.052727273 | D16: =D11/C11-1 -> 0.051588946 | E16: =E11/D11-1 -> 0.040529834 | F16: =F11/E11-1 -> 0.02 | G16: =G11/F11-1 -> 0.02 | H16: n/a
A17: Base Case | B17: n/a | C17: =C12/B12-1 -> 0.33636364 | D17: =D12/C12-1 -> 0.21265306 | E17: =E12/D12-1 -> 0.17939078 | F17: =F12/E12-1 -> 0.12183462 | G17: =G12/F12-1 -> 0.1051192 | H17: n/a
A18: Aggressive | B18: n/a | C18: =C13/B13-1 -> 0.56666667 | D18: =D13/C13-1 -> 0.39595745 | E18: =E13/D13-1 -> 0.27241579 | F18: =F13/E13-1 -> 0.19983843 | G18: =G13/F13-1 -> 0.17487544 | H18: n/a
A20: SECTION 3 | TOTAL STORE COUNT (YEAR-END)
A21: Conservative | B21: =Assumptions!B11 -> 12 | C21: =B21+Assumptions!B23 -> 13 | D21: =C21+Assumptions!B24 -> 14 | E21: =D21+Assumptions!B25 -> 15 | F21: =E21+Assumptions!B26 -> 15 | G21: =F21+Assumptions!B27 -> 15 | H21: =G21 -> 15
A22: Base Case | B22: =Assumptions!B11 -> 12 | C22: =B22+Assumptions!C23 -> 16 | D22: =C22+Assumptions!C24 -> 19 | E22: =D22+Assumptions!C25 -> 22 | F22: =E22+Assumptions!C26 -> 24 | G22: =F22+Assumptions!C27 -> 26 | H22: =G22 -> 26
A23: Aggressive | B23: =Assumptions!B11 -> 12 | C23: =B23+Assumptions!D23 -> 17 | D23: =C23+Assumptions!D24 -> 22 | E23: =D23+Assumptions!D25 -> 26 | F23: =E23+Assumptions!D26 -> 29 | G23: =F23+Assumptions!D27 -> 32 | H23: =G23 -> 32
A25: SECTION 4 | REVENUE DRIVER BREAKDOWN — BASE CASE ($000s)
A26: COMPONENT | B26: FY2025E | C26: FY2026 | D26: FY2027 | E26: FY2028 | F26: FY2029 | G26: FY2030
A27: Opening Revenue (Prior Year) | B27: n/a | C27: =Assumptions!B10 -> 19800 | D27: =C12 -> 26460 | E27: =D12 -> 32086.8 | F27: =E12 -> 37842.876 | G27: =F12 -> 42453.449 | H27: n/a
A28: Add: Same-Store Sales Growth ($) | B28: n/a | C28: =Assumptions!B10*Assumptions!C15 -> 1980 | D28: =C12*Assumptions!C16 -> 2116.8 | E28: =D12*Assumptions!C17 -> 2246.076 | F28: =E12*Assumptions!C18 -> 2270.5726 | G28: =F12*Assumptions!C19 -> 2122.6724 | H28: n/a
A29: Add: New Store Revenue (openings x avg x ramp) | B29: n/a | C29: =Assumptions!C23*Assumptions!C30*Assumptions!C31 -> 4680 | D29: =Assumptions!C24*Assumptions!C30*Assumptions!C31 -> 3510 | E29: =Assumptions!C25*Assumptions!C30*Assumptions!C31 -> 3510 | F29: =Assumptions!C26*Assumptions!C30*Assumptions!C31 -> 2340 | G29: =Assumptions!C27*Assumptions!C30*Assumptions!C31 -> 2340 | H29: n/a
A30: Total Revenue (Sum of Drivers Above) | B30: =Assumptions!B10 -> 19800 | C30: =C12 -> 26460 | D30: =D12 -> 32086.8 | E30: =E12 -> 37842.876 | F30: =F12 -> 42453.449 | G30: =G12 -> 46916.121 | H30: =(G12/Assumptions!B10)^(1/5)-1 -> 0.18831446
A32: SECTION 5 | REVENUE DRIVER BREAKDOWN — CONSERVATIVE ($000s)
A33: COMPONENT | B33: FY2025E | C33: FY2026 | D33: FY2027 | E33: FY2028 | F33: FY2029 | G33: FY2030
A34: Opening Revenue (Prior Year) | B34: n/a | C34: =Assumptions!B10 -> 19800 | D34: =C11 -> 20844 | E34: =D11 -> 21919.32 | F34: =E11 -> 22807.706 | G34: =F11 -> 23263.861 | H34: n/a
A35: Add: Same-Store Sales Growth ($) | B35: n/a | C35: =Assumptions!B10*Assumptions!B15 -> 594 | D35: =C11*Assumptions!B16 -> 625.32 | E35: =D11*Assumptions!B17 -> 438.3864 | F35: =E11*Assumptions!B18 -> 456.15413 | G35: =F11*Assumptions!B19 -> 465.27721 | H35: n/a
A36: Add: New Store Revenue (openings x avg x ramp) | B36: n/a | C36: =Assumptions!B23*Assumptions!B30*Assumptions!B31 -> 450 | D36: =Assumptions!B24*Assumptions!B30*Assumptions!B31 -> 450 | E36: =Assumptions!B25*Assumptions!B30*Assumptions!B31 -> 450 | F36: =Assumptions!B26*Assumptions!B30*Assumptions!B31 -> 0 | G36: =Assumptions!B27*Assumptions!B30*Assumptions!B31 -> 0 | H36: n/a
A37: Total Revenue (Sum of Drivers Above) | B37: =Assumptions!B10 -> 19800 | C37: =C11 -> 20844 | D37: =D11 -> 21919.32 | E37: =E11 -> 22807.706 | F37: =F11 -> 23263.861 | G37: =G11 -> 23729.138 | H37: =(G11/Assumptions!B10)^(1/5)-1 -> 0.036867718
A39: SECTION 6 | REVENUE DRIVER BREAKDOWN — AGGRESSIVE ($000s)
A40: COMPONENT | B40: FY2025E | C40: FY2026 | D40: FY2027 | E40: FY2028 | F40: FY2029 | G40: FY2030
A41: Opening Revenue (Prior Year) | B41: n/a | C41: =Assumptions!B10 -> 19800 | D41: =C13 -> 31020 | E41: =D13 -> 43302.6 | F41: =E13 -> 55098.912 | G41: =F13 -> 66109.792 | H41: n/a
A42: Add: Same-Store Sales Growth ($) | B42: n/a | C42: =Assumptions!B10*Assumptions!D15 -> 2970 | D42: =C13*Assumptions!D16 -> 4032.6 | E42: =D13*Assumptions!D17 -> 5196.312 | F42: =E13*Assumptions!D18 -> 6060.8803 | G42: =F13*Assumptions!D19 -> 6610.9792 | H42: n/a
A43: Add: New Store Revenue (openings x avg x ramp) | B43: n/a | C43: =Assumptions!D23*Assumptions!D30*Assumptions!D31 -> 8250 | D43: =Assumptions!D24*Assumptions!D30*Assumptions!D31 -> 8250 | E43: =Assumptions!D25*Assumptions!D30*Assumptions!D31 -> 6600 | F43: =Assumptions!D26*Assumptions!D30*Assumptions!D31 -> 4950 | G43: =Assumptions!D27*Assumptions!D30*Assumptions!D31 -> 4950 | H43: n/a
A44: Total Revenue (Sum of Drivers Above) | B44: =Assumptions!B10 -> 19800 | C44: =C13 -> 31020 | D44: =D13 -> 43302.6 | E44: =E13 -> 55098.912 | F44: =F13 -> 66109.792 | G44: =G13 -> 77670.772 | H44: =(G13/Assumptions!B10)^(1/5)-1 -> 0.31437257
A46: FORMULA: Total Revenue = Prior Year Revenue x (1 + SSS Growth Rate) + New Stores Opened x Average Store Revenue x Year-1 Ramp Factor. Sections 4-6 decompose each scenario into its drivers for auditability — the 'Total Revenue' row in each block always equals the totals shown in Section 1. CAGR = (FY2030 / FY2025E)^(1/5) - 1.

Sheet Monthly Dashboard
A1: MONTHLY REVENUE DASHBOARD — FY2026
A2: RetailPro Group | Phoenix, AZ | Portfolio Sample (Illustrative)
A3: Monthly forecast by scenario | Yellow cells = enter actuals as each month is realised | Variance auto-calculates
A5: Muhammad Zeenat Ullah | CA Finalist (ICAP) | Ex-KPMG | QBO Pro Advisor | Excel Expert | zeenatullah.bookkeeper@gmail.com | +44 7577 845321 (WhatsApp Only)
B7: Conservative Annual ($K) | D7: Base Case Annual ($K) | F7: Aggressive Annual ($K)
B8: ='Revenue Forecast'!C11 -> 20844 | D8: ='Revenue Forecast'!C12 -> 26460 | F8: ='Revenue Forecast'!C13 -> 31020 | H8: FY2026
A10: MONTH | B10: CONSERVATIVE ($K) | C10: BASE CASE ($K) | D10: AGGRESSIVE ($K) | E10: ACTUAL ($K) — TYPE HERE | F10: VARIANCE vs BASE ($K) | G10: VARIANCE % | H10: SEASONALITY
A11: January | B11: ='Revenue Forecast'!C11*Assumptions!B35/12 -> 1250.64 | C11: ='Revenue Forecast'!C12*Assumptions!B35/12 -> 1587.6 | D11: ='Revenue Forecast'!C13*Assumptions!B35/12 -> 1861.2 | E11: 1620 | F11: =IF(ISBLANK(E11),"—",E11-C11) -> 32.4 | G11: =IF(ISBLANK(E11),"—",IF(C11=0,"N/A",(E11-C11)/C11)) -> 0.020408163 | H11: 0.72x (Below Avg)
A12: February | B12: ='Revenue Forecast'!C11*Assumptions!B36/12 -> 1354.86 | C12: ='Revenue Forecast'!C12*Assumptions!B36/12 -> 1719.9 | D12: ='Revenue Forecast'!C13*Assumptions!B36/12 -> 2016.3 | E12: 1695 | F12: =IF(ISBLANK(E12),"—",E12-C12) -> -24.9 | G12: =IF(ISBLANK(E12),"—",IF(C12=0,"N/A",(E12-C12)/C12)) -> -0.014477586 | H12: 0.78x (Below Avg)
A13: March | B13: ='Revenue Forecast'!C11*Assumptions!B37/12 -> 1563.3 | C13: ='Revenue Forecast'!C12*Assumptions!B37/12 -> 1984.5 | D13: ='Revenue Forecast'!C13*Assumptions!B37/12 -> 2326.5 | E13: 2050 | F13: =IF(ISBLANK(E13),"—",E13-C13) -> 65.5 | G13: =IF(ISBLANK(E13),"—",IF(C13=0,"N/A",(E13-C13)/C13)) -> 0.033005795 | H13: 0.90x (Below Avg)
A14: April | B14: ='Revenue Forecast'!C11*Assumptions!B38/12 -> 1598.04 | C14: ='Revenue Forecast'!C12*Assumptions!B38/12 -> 2028.6 | D14: ='Revenue Forecast'!C13*Assumptions!B38/12 -> 2378.2 | E14: 2010 | F14: =IF(ISBLANK(E14),"—",E14-C14) -> -18.6 | G14: =IF(ISBLANK(E14),"—",IF(C14=0,"N/A",(E14-C14)/C14)) -> -0.0091688849 | H14: 0.92x (Avg)
A15: May | B15: ='Revenue Forecast'!C11*Assumptions!B39/12 -> 1650.15 | C15: ='Revenue Forecast'!C12*Assumptions!B39/12 -> 2094.75 | D15: ='Revenue Forecast'!C13*Assumptions!B39/12 -> 2455.75 | F15: =IF(ISBLANK(E15),"—",E15-C15) -> — | G15: =IF(ISBLANK(E15),"—",IF(C15=0,"N/A",(E15-C15)/C15)) -> — | H15: 0.95x (Avg)
A16: June | B16: ='Revenue Forecast'!C11*Assumptions!B40/12 -> 1598.04 | C16: ='Revenue Forecast'!C12*Assumptions!B40/12 -> 2028.6 | D16: ='Revenue Forecast'!C13*Assumptions!B40/12 -> 2378.2 | F16: =IF(ISBLANK(E16),"—",E16-C16) -> — | G16: =IF(ISBLANK(E16),"—",IF(C16=0,"N/A",(E16-C16)/C16)) -> — | H16: 0.92x (Avg)
A17: July | B17: ='Revenue Forecast'!C11*Assumptions!B41/12 -> 1545.93 | C17: ='Revenue Forecast'!C12*Assumptions!B41/12 -> 1962.45 | D17: ='Revenue Forecast'!C13*Assumptions!B41/12 -> 2300.65 | F17: =IF(ISBLANK(E17),"—",E17-C17) -> — | G17: =IF(ISBLANK(E17),"—",IF(C17=0,"N/A",(E17-C17)/C17)) -> — | H17: 0.89x (Below Avg)
A18: August | B18: ='Revenue Forecast'!C11*Assumptions!B42/12 -> 1580.67 | C18: ='Revenue Forecast'!C12*Assumptions!B42/12 -> 2006.55 | D18: ='Revenue Forecast'!C13*Assumptions!B42/12 -> 2352.35 | F18: =IF(ISBLANK(E18),"—",E18-C18) -> — | G18: =IF(ISBLANK(E18),"—",IF(C18=0,"N/A",(E18-C18)/C18)) -> — | H18: 0.91x (Below Avg)
A19: September | B19: ='Revenue Forecast'!C11*Assumptions!B43/12 -> 1650.15 | C19: ='Revenue Forecast'!C12*Assumptions!B43/12 -> 2094.75 | D19: ='Revenue Forecast'!C13*Assumptions!B43/12 -> 2455.75 | F19: =IF(ISBLANK(E19),"—",E19-C19) -> — | G19: =IF(ISBLANK(E19),"—",IF(C19=0,"N/A",(E19-C19)/C19)) -> — | H19: 0.95x (Avg)
A20: October | B20: ='Revenue Forecast'!C11*Assumptions!B44/12 -> 1875.96 | C20: ='Revenue Forecast'!C12*Assumptions!B44/12 -> 2381.4 | D20: ='Revenue Forecast'!C13*Assumptions!B44/12 -> 2791.8 | F20: =IF(ISBLANK(E20),"—",E20-C20) -> — | G20: =IF(ISBLANK(E20),"—",IF(C20=0,"N/A",(E20-C20)/C20)) -> — | H20: 1.08x (Above Avg)
A21: November | B21: ='Revenue Forecast'!C11*Assumptions!B45/12 -> 2397.06 | C21: ='Revenue Forecast'!C12*Assumptions!B45/12 -> 3042.9 | D21: ='Revenue Forecast'!C13*Assumptions!B45/12 -> 3567.3 | F21: =IF(ISBLANK(E21),"—",E21-C21) -> — | G21: =IF(ISBLANK(E21),"—",IF(C21=0,"N/A",(E21-C21)/C21)) -> — | H21: 1.38x (Peak)
A22: December | B22: ='Revenue Forecast'!C11*Assumptions!B46/12 -> 2779.2 | C22: ='Revenue Forecast'!C12*Assumptions!B46/12 -> 3528 | D22: ='Revenue Forecast'!C13*Assumptions!B46/12 -> 4136 | F22: =IF(ISBLANK(E22),"—",E22-C22) -> — | G22: =IF(ISBLANK(E22),"—",IF(C22=0,"N/A",(E22-C22)/C22)) -> — | H22: 1.60x (Peak)
A23: FY2026 ANNUAL TOTAL | B23: ='Revenue Forecast'!C11 -> 20844 | C23: ='Revenue Forecast'!C12 -> 26460 | D23: ='Revenue Forecast'!C13 -> 31020 | E23: =IF(COUNT(E11:E22)=0,"—",SUM(E11:E22)) -> 7375 | F23: =IF(COUNT(E11:E22)=0,"—",SUM(E11:E22)-SUMIF(E11:E22,"<>",C11:C22)) -> 54.4
A25: YEAR-TO-DATE TRACKING
A26: Metric | B26: Value | D26: Metric | E26: Value
A27: Months with Actuals Entered | B27: =COUNT(E11:E22) -> 4 | D27: YTD Base Case Forecast ($K) | E27: =IF(COUNT(E11:E22)=0,"—",SUMIF(E11:E22,"<>",C11:C22)) -> 7320.6
A28: YTD Actual Revenue ($K) | B28: =IF(COUNT(E11:E22)=0,"—",SUM(E11:E22)) -> 7375 | D28: YTD Variance vs Base ($K) | E28: =IF(COUNT(E11:E22)=0,"—",SUM(E11:E22)-SUMIF(E11:E22,"<>",C11:C22)) -> 54.4
A29: LIVE TRACKING DEMO: January–April show sample actual results already entered (proving the auto-variance calculation works). May–December are intentionally left blank — type a number into any yellow cell and Variance, Variance %, and YTD Tracking below will recalculate instantly. Blank months correctly show "—" rather than a misleading $0.

Sheet Sensitivity Analysis
A1: SENSITIVITY ANALYSIS — FY2030 BASE CASE REVENUE ($000s)
A2: RetailPro Group | Phoenix, AZ | Portfolio Sample (Illustrative)
A3: Two-Way Tables | FY2030 projected revenue under varying assumptions | Green = Base Case
A5: Muhammad Zeenat Ullah | CA Finalist (ICAP) | Ex-KPMG | QBO Pro Advisor | Excel Expert | zeenatullah.bookkeeper@gmail.com | +44 7577 845321 (WhatsApp Only)
A7: TABLE 1: FY2030 Revenue ($000s) — Same-Store Sales Growth x New Stores/Year
A8: FY2030 ($000s) | B8: Stores: 0 | C8: Stores: 1 | D8: Stores: 2 | E8: Stores: 3 | F8: Stores: 4 | G8: Stores: 5
A9: SSS = 3% | B9: 22950 | C9: 29170 | D9: 35380 | E9: 41590 | F9: 47800 | G9: 54010
A10: SSS = 5% | B10: 25270 | C10: 31740 | D10: 38200 | E10: 44670 | F10: 51130 | G10: 57600
A11: SSS = 8% | B11: 29090 | C11: 35960 | D11: 42820 | E11: 49680 | F11: 56550 | G11: 63410
A12: SSS = 10% | B12: 31890 | C12: 39030 | D12: 46170 | E12: 53320 | F12: 60460 | G12: 67600
A13: SSS = 12% | B13: 34890 | C13: 42330 | D13: 49760 | E13: 57190 | F13: 64630 | G13: 72060
A14: SSS = 15% | B14: 39820 | C14: 47710 | D14: 55600 | E14: 63490 | F14: 71380 | G14: 79270
A15: Green = Base Case | Blue row = base SSS (8%) | Avg new store $1,800K, Ramp 65%
A17: TABLE 2: FY2030 Revenue ($000s) — Avg New Store Revenue x New Stores/Year
A18: FY2030 ($000s) | B18: $600K | C18: $900K | D18: $1,200K | E18: $1,500K | F18: $1,800K | G18: $2,100K
A19: 1 New Store/Year | B19: 31380 | C19: 32520 | D19: 33670 | E19: 34810 | F19: 35960 | G19: 37100
A20: 2 New Stores/Year | B20: 33670 | C20: 35960 | D20: 38240 | E20: 40530 | F20: 42820 | G20: 45110
A21: 3 New Stores/Year | B21: 35960 | C21: 39390 | D21: 42820 | E21: 46250 | F21: 49680 | G21: 53120
A22: 4 New Stores/Year | B22: 38240 | C22: 42820 | D22: 47400 | E22: 51970 | F22: 56550 | G22: 61120
A23: 5 New Stores/Year | B23: 40530 | C23: 46250 | D23: 51970 | E23: 57690 | F23: 63410 | G23: 69130
A24: Green = Base Case ($1,800K avg, 2 stores/yr) | Blue row = 2 stores/yr
A26: Table 1: Holds avg new store revenue at $1,800K. Varies SSS (3%-15%) and store count (0-5/yr). Table 2: Holds SSS at 8%/yr constant. Varies avg new store revenue ($600K-$2,100K) and count.

Sheet Store Performance
A1: STORE PERFORMANCE — HISTORICAL DATA
A2: RetailPro Group | Phoenix, AZ | Portfolio Sample (Illustrative)
A3: 12 Active Locations | FY2022A-FY2025E | Basis for $19,800K base year revenue assumption
A5: Muhammad Zeenat Ullah | CA Finalist (ICAP) | Ex-KPMG | QBO Pro Advisor | Excel Expert | zeenatullah.bookkeeper@gmail.com | +44 7577 845321 (WhatsApp Only)
A7: STORE LOCATION | B7: TYPE | C7: FY2022A | D7: FY2023A | E7: FY2024A | F7: FY2025E | G7: 3-YR CAGR
A9: Phoenix Downtown | B9: Flagship | C9: 1380 | D9: 1680 | E9: 2100 | F9: 2310 | G9: =(F9/C9)^(1/3)-1 -> 0.18734692
A10: Scottsdale Fashion Sq | B10: Flagship | C10: 1560 | D10: 1890 | E10: 2400 | F10: 2640 | G10: =(F10/C10)^(1/3)-1 -> 0.19168034
A11: Tempe Marketplace | B11: Standard | C11: 1140 | D11: 1440 | E11: 1920 | F11: 2100 | G11: =(F11/C11)^(1/3)-1 -> 0.2258523
A12: Chandler Fashion Ctr | B12: Standard | C12: 1080 | D12: 1350 | E12: 1800 | F12: 2010 | G12: =(F12/C12)^(1/3)-1 -> 0.23005378
A13: Mesa Riverview | B13: Standard | C13: 960 | D13: 1200 | E13: 1620 | F13: 1800 | G13: =(F13/C13)^(1/3)-1 -> 0.23310604
A14: Glendale Westgate | B14: Standard | C14: 900 | D14: 1140 | E14: 1500 | F14: 1680 | G14: =(F14/C14)^(1/3)-1 -> 0.2312765
A15: Gilbert San Tan Vlg | B15: Standard | C15: 840 | D15: 1080 | E15: 1440 | F15: 1620 | G15: =(F15/C15)^(1/3)-1 -> 0.2447398
A16: Peoria Sports Complex | B16: Compact | C16: 780 | D16: 990 | E16: 1320 | F16: 1470 | G16: =(F16/C16)^(1/3)-1 -> 0.23521032
A17: Avondale Gateway | B17: Compact | C17: 720 | D17: 930 | E17: 1200 | F17: 1350 | G17: =(F17/C17)^(1/3)-1 -> 0.23310604
A18: Surprise Village Sq | B18: Compact | C18: 660 | D18: 840 | E18: 1080 | F18: 1200 | G18: =(F18/C18)^(1/3)-1 -> 0.22052244
A19: Goodyear Village | B19: Compact | C19: 600 | D19: 780 | E19: 960 | F19: 1080 | G19: =(F19/C19)^(1/3)-1 -> 0.2164404
A20: Queen Creek (Newest) | B20: Compact | C20: 180 | D20: 270 | E20: 660 | F20: 540 | G20: =(F20/C20)^(1/3)-1 -> 0.44224957
A21: TOTAL — All 12 Locations | C21: =SUM(C9:C20) -> 10800 | D21: =SUM(D9:D20) -> 13590 | E21: =SUM(E9:E20) -> 18000 | F21: =SUM(F9:F20) -> 19800 | G21: =(F21/C21)^(1/3)-1 -> 0.22390341
A23: Total FY2025E = $19,800K — consistent with Assumptions base year. Store revenues are illustrative. Queen Creek opened Q4 FY2022 (partial year).
A26: CONTACT INFORMATION
A28: Name | B28: Muhammad Zeenat Ullah
A29: Credentials | B29: CA Finalist (ICAP) | Ex-KPMG | QBO Pro Advisor | Excel Expert
A30: Speciality | B30: Financial modeling, DCF valuation, Financial Forecasting, bookkeeping & Excel reporting for US-based clients
A31: Email | B31: zeenatullah.bookkeeper@gmail.com
A32: WhatsApp | B32: +44 7577 845321
A33: Free Quote | B33: Send your data — I will provide a free Quote within 2 hours at no charge
A35: This is a sample portfolio project prepared by Muhammad Zeenat Ullah (CA Finalist ICAP | Ex-KPMG | QBO Pro Advisor | Excel Expert) to demonstrate financial modeling capability. All company names, financials, and projections are fictional and for illustrative purposes only.
