Workbook

Sheet Cover
B4: Muhammad Zeenat Ullah
B8: CA Finalist (ICAP) · QBO ProAdvisor · Excel Expert
B11: PORTFOLIO PROJECT
B12: Formula Rebuild & Reconstruction HR Payroll Spreadsheet System
B15: Fixed 200+ broken formulas · Built 85 new formulas · System runs 80% faster
B17: CLIENT | D17: DURATION
B18: Summit HR Solutions, Atlanta GA | D18: 4 Days
B20: TOOLS USED | D20: DELIVERABLES
B21: Excel · Advanced Formulas · Dynamic Arrays · SUMIFS · INDEX-MATCH | D21: Fixed Formula Library · New Formulas · Documentation
B23: IMPACT | D23: PAY FREQUENCY
B24: Saved 6 hours/week — Payroll processing now error-free | D24: Bi-Weekly (26 periods/year)
B26: FORMULAS | D26: SCOPE
B27: INDEX-MATCH · Nested IF · SUMIFS · COUNTIF · IFERROR · IRS Pub 15-T W/H | D27: 20 Employees · 5 Departments · Federal + GA Payroll
A31: CONTACT
A32: zeenatullah.bookkeeper@gmail.com · WhatsApp: +44 7577 845321
A33: CA Finalist (ICAP) · QuickBooks Online ProAdvisor · Excel Expert
A34: Portfolio Sample · Client name and all employee data are entirely fictitious · Created to demonstrate formula-building expertise

Sheet Project Summary
A1: PAYROLL FORMULA REBUILD | Summit HR Solutions, Atlanta GA
A2: Prepared by: Muhammad Zeenat Ullah · CA Finalist (ICAP) · QBO ProAdvisor · Excel Expert
B4: 200+ | D4: 85 | F4: 6 hrs | H4: 80%
B5: Broken Formulas Fixed | D5: New Formulas Built | F5: Saved Every Week | H5: Faster Processing
A8: THE SITUATION
B9: WHAT WAS BROKEN | D9: WHAT IT WAS COSTING | G9: WHAT I DELIVERED
B10: Payroll formulas showing errors — numbers could not be trusted | D10: Payroll team manually checking every cell before each run: 6 hours wasted every week | G10: 100% error-free. Every number calculates automatically. Zero manual checking needed.
B11: Federal tax withheld at wrong flat rate — same % for every employee | D11: Employees over/under-withheld. Real risk of IRS underpayment penalties and employee complaints | G11: Correct IRS withholding for every employee based on their salary, filing status, and tax bracket.
B12: Overtime paid at wrong rate — extra pay going out every check | D12: $200–$400 overpaid per overtime employee per pay period. Multiplied across the team = significant loss | G12: Overtime calculated exactly per federal FLSA law. Employees paid correctly — not a dollar more or less.
B13: Salary formulas using wrong pay period divisor | D13: Salaried employees underpaid by approx 8% each check — payroll liability and employee trust issue | G13: All salaries divided correctly for bi-weekly schedule. Every employee paid exact contracted amount.
B14: Year-to-date totals ignoring bonuses and variable pay | D14: W-2 preparation inaccurate. Tax filings at risk. Employees questioning their YTD figures. | G14: True YTD totals pulling from complete payroll history. Accurate for W-2s, audits, and employee records.
B15: Social Security over-deducted for higher earners | D15: High earners over-deducted by up to $847/year. Company exposed to correction and reimbursement costs | G15: SS withholding automatically stops at the IRS annual wage base. Zero over-deduction risk.
B16: Lookup formulas breaking when columns moved | D16: Manual formula repairs needed every pay run — adding to the 6-hour weekly correction burden | G16: Formulas rebuilt so they cannot break from column changes. Works reliably every pay run, permanently.
A18: WHY HIRE ME
B19: CA Finalist (ICAP) | D19: Internationally recognized accounting qualification. I understand payroll not just as formulas, but as financial compliance — taxes, FLSA, IRS rules, and reporting accuracy.
B20: QBO ProAdvisor | D20: Certified in QuickBooks Online. I connect Excel payroll data seamlessly with your accounting software — no double entry, no reconciliation headaches.
B21: Excel Expert | D21: I build spreadsheets that work without you needing to understand a single formula. You enter data. The system does the rest. Permanently.
B22: US Payroll Specific | D22: This workbook uses real IRS Publication 15-T 2024 tables, actual FLSA overtime rules, Georgia state flat tax (5.49%), Social Security wage base ($176,100), and FUTA/SUTA rates. Not generic — built for US compliance.
B23: Portfolio, Not a Template | D23: Every formula in this workbook was written from scratch. Nothing downloaded. Nothing templated. This is original work — which means I can build the same for your specific business needs.
A26: Ready to fix your spreadsheet? — zeenatullah.bookkeeper@gmail.com | WhatsApp: +44 7577 845321 | Muhammad Zeenat Ullah · CA Finalist (ICAP) · QBO ProAdvisor · Excel Expert
A28: Muhammad Zeenat Ullah | CA Finalist (ICAP) | QBO ProAdvisor | Excel Expert | zeenatullah.bookkeeper@gmail.com | WhatsApp: +44 7577 845321
A29: Portfolio Sample — Client name, employee names, and all figures are entirely fictitious. Created to demonstrate advanced Excel payroll formula expertise.

Sheet Before vs After
A1: BEFORE vs AFTER | 10 Real Problems Found and Fixed | Summit HR Solutions
A2: Muhammad Zeenat Ullah · CA Finalist (ICAP) · QBO ProAdvisor · Excel Expert · zeenatullah.bookkeeper@gmail.com
B4: WHAT WAS BROKEN | C4: ERROR IT CAUSED | D4: BUSINESS COST | E4: WHAT I FIXED / BUILT
B5: 1. Employee lookup formulas returning blank results — employee names, rates, and departments not pulling into payroll rows | C5: Payroll rows for affected employees were empty — pay could not be calculated without manual data entry every run | D5: 6+ hours/week of manual data entry. High risk of entry mistakes causing wrong pay amounts | E5: Rebuilt all lookups so they find employee data automatically and reliably — even when the employee list is reorganized or expanded
B6: 2. Federal income tax calculated at a single flat percentage for every employee regardless of salary or filing status | C6: Employees over-withheld or under-withheld on federal tax every single pay period — non-compliant with IRS rules | D6: Risk of IRS underpayment penalties. Employee complaints about wrong take-home pay. Potential back-corrections needed | E6: Federal tax now calculated using official IRS 2024 tables — correct amount for each employee based on their exact salary and filing status
B7: 3. Overtime pay formula multiplying all hours by 1.5x whenever an employee worked overtime | C7: Employees whose regular hours were also multiplied received $200–$400 extra per overtime pay period | D7: Direct payroll overpayment every period overtime occurred. Federal FLSA compliance violation — legal exposure | E7: Overtime recalculated using the FLSA-required method: straight pay for all hours plus a premium only on overtime hours — legally correct
B8: 4. Annual salary divided by 12 (monthly amount) in a bi-weekly payroll system that should divide by 26 | C8: Every salaried employee was underpaid by approximately 8% each pay period | D8: For a $78,000/year employee: $500 underpaid every two weeks. Payroll liability and serious employee trust damage | E8: All salary formulas corrected to bi-weekly division. Every salaried employee now receives exactly their contracted pay each period
B9: 5. Year-to-date totals calculated by multiplying the current pay period amount by the number of periods | C9: YTD figures completely ignored bonuses, overtime variation, and any pay rate changes made during the year | D9: Inaccurate W-2 preparation risk. Employee YTD queries unanswerable. Year-end tax filing exposure | E9: YTD now totals actual payroll history period by period — accurate for every employee regardless of bonuses or variable pay
B10: 6. Social Security deduction applied at 6.2% continuously with no annual wage base limit | C10: High-earning employees kept being deducted Social Security beyond the IRS annual limit of $176,100 | D10: Up to $847 over-deducted per high earner per year. Company required to refund the difference — administrative cost and employee dissatisfaction | E10: Social Security automatically stops deducting the moment an employee reaches the annual wage base. Zero over-deduction possible
B11: 7. Department payroll totals calculated manually or by hardcoded cell ranges that broke when rows changed | C11: Department cost reports were wrong or unavailable — management could not see accurate payroll by department | D11: Management decisions based on incorrect cost data. Budget vs actual comparisons unreliable | E11: Department totals now calculate automatically using the entire payroll data — update instantly when any employee data changes
B12: 8. Georgia state income tax applied to take-home pay after deductions instead of gross wages | C12: State tax under-withheld for every employee — tax base was smaller than it should legally be | D12: Potential Georgia DOR underpayment exposure for all 20 employees across every pay period | E12: Georgia 5.49% flat tax now correctly applied to gross wages — compliant with Georgia Department of Revenue requirements
B13: 9. Benefit deduction formulas returning a blank space instead of zero when an employee had no election | C13: Every total and net pay formula downstream of those cells returned errors — net pay uncalculable | D13: Payroll could not be completed without manually deleting the problematic cells each run — added to the correction burden | E13: All benefit formulas return zero when no deduction applies — net pay and totals calculate cleanly with no manual intervention
B14: 10. Conditional formatting error-highlight rules pointing to a worksheet that had been deleted | C14: Color-coded alerts completely non-functional — payroll errors were invisible until they caused problems | D14: Staff had no early warning system. Errors only discovered after checks were already processed or distributed | E14: Visual alert system fully rebuilt — errors, anomalies, and employees approaching tax limits are all highlighted automatically in color
A15: RESULT: 200+ formulas fixed · 85 new formulas built · 6 hours/week saved · IRS compliant · FLSA compliant · Zero errors remaining
A17: Have a broken spreadsheet? Get in touch: zeenatullah.bookkeeper@gmail.com | WhatsApp: +44 7577 845321
A19: Muhammad Zeenat Ullah | CA Finalist (ICAP) | QBO ProAdvisor | Excel Expert | zeenatullah.bookkeeper@gmail.com | WhatsApp: +44 7577 845321
A20: Portfolio Sample — Client name, employee names, and all figures are entirely fictitious. Created to demonstrate advanced Excel payroll formula expertise.

Sheet Formula Showcase
A1: FORMULA SHOWCASE | Every Formula Built & Fixed | Summit HR Solutions Payroll System
A2: Muhammad Zeenat Ullah · CA Finalist (ICAP) · QBO ProAdvisor · Excel Expert · zeenatullah.bookkeeper@gmail.com · +44 7577 845321
A3: LIVE RESULTS BELOW — Every formula in the Result column is actively pulling real data from the Payroll Register and Employee Master in this workbook. Nothing is hardcoded.
A5: FORMULA USAGE SUMMARY — How Many Times Each Formula Was Used Across This Workbook
B6: FORMULA TYPE | C6: TIMES USED
B7: INDEX-MATCH | C7: 120+ | D7: Lookup formula. Replaces VLOOKUP. Used to pull every employee attribute (name, rate, department, tax rate, benefits) from the Employee Master into the Payroll Register. Works in any direction. Cannot break when columns move.
B8: Nested IF | C8: 20 | D8: Decision formula. Used to calculate federal income tax withholding — checks filing status (MFJ vs Single), then tests 7 tax bracket thresholds in sequence to find the correct IRS percentage. Each employee's withholding calculated precisely per IRS Pub 15-T 2024.
B9: SUMIFS | C9: 48+ | D9: Conditional sum formula. Used in Department Summary to total gross pay, taxes, and deductions per department. Used in YTD Summary to total each employee's year-to-date figures. Updates automatically every pay period.
B10: IFERROR | C10: 100+ | D10: Error-protection formula. Wraps every single lookup formula in the workbook. If an employee ID is not found, returns zero instead of crashing the row with an error. Prevents one bad cell from breaking an entire payroll run.
B11: ROUND | C11: 60+ | D11: Precision formula. Wraps every tax and deduction calculation. Ensures Social Security (6.2%), Medicare (1.45%), and Georgia state tax (5.49%) are always calculated to exactly 2 decimal places — no rounding errors accumulating across 26 pay periods.
B12: COUNTIF | C12: 7 | D12: Counting formula. Used in Department Summary to count employees per department, and in Dashboard to count total active employees. Updates instantly when employee status changes.
B13: SUM | C13: 50+ | D13: Totalling formula. Used in every row to sum gross pay components, tax components, and deduction components. Used in every totals row to sum across all 20 employees. All totals rows use SUM — nothing is manually entered.
B14: IF | C14: 40+ | D14: Logic formula. Used to distinguish salaried vs hourly pay (salary divides annual by 26, hourly multiplies rate by hours), to apply FLSA overtime premium for hourly employees only, and to stop Social Security withholding at the annual wage base.
A16: LIVE DEMONSTRATIONS — Each result below is a real formula pulling live data from this workbook
B17: FORMULA TYPE | C17: LIVE RESULT | D17: FORMULA USED (display) | E17: PLAIN-ENGLISH EXPLANATION
B18: INDEX-MATCH (Employee Lookup) | C18: =IFERROR(INDEX('Employee Master'!B$4:B$23,MATCH("E-1001",'Employee Master'!A$4:A$23,0)),"Not Found") -> Anderson | D18: IFERROR( INDEX( EmployeeName_Range, MATCH( EmpID, EmpID_Range, 0 ) ), "" ) | E18: Finds employee E-1001 in the Employee Master and returns their last name. Uses MATCH to locate the row, INDEX to retrieve the value. IFERROR prevents errors if the ID is missing.
B19: INDEX-MATCH (Salary Lookup) | C19: =IFERROR(INDEX('Employee Master'!I$4:I$23,MATCH("E-1003",'Employee Master'!A$4:A$23,0)),0) -> 125000 | D19: IFERROR( INDEX( AnnualSalary_Range, MATCH( EmpID, EmpID_Range, 0 ) ), 0 ) | E19: Retrieves the annual salary of employee E-1003 (Williams, Controller) from the Employee Master. The same pattern is repeated for every data field: rate, department, filing status, benefits.
B20: INDEX-MATCH (Hourly Rate) | C20: =IFERROR(INDEX('Employee Master'!J$4:J$23,MATCH("E-1009",'Employee Master'!A$4:A$23,0)),0) -> 24.5 | D20: IFERROR( INDEX( HourlyRate_Range, MATCH( EmpID, EmpID_Range, 0 ) ), 0 ) | E20: Retrieves the hourly rate for E-1009 (Wilson, Warehouse Lead) — an hourly employee. The IF formula in gross pay then uses this rate multiplied by hours worked.
B21: IF — Salary vs Hourly (Gross Pay) | C21: =IF(INDEX('Employee Master'!G$4:G$23,MATCH("E-1001",'Employee Master'!A$4:A$23,0))="Salary",INDEX('Employee Master'!I$4:I$23,MATCH("E-1001",'Employee Master'!A$4:A$23,0))/26,INDEX('Employee Master'!J$4:J$23,MATCH("E-1001",'Employee Master'!A$4:A$23,0))*80) -> 4423.0769 | D21: IF( PayType = Salary, AnnualSalary / 26, HourlyRate * RegHours ) | E21: Checks whether the employee is Salaried or Hourly. Salaried employees get annual salary divided by 26 (bi-weekly). Hourly employees get rate multiplied by hours. One formula handles both pay types.
B22: IF — FLSA Overtime (Half-Time Premium) | C22: =IFERROR(INDEX('Employee Master'!J$4:J$23,MATCH("E-1009",'Employee Master'!A$4:A$23,0))*5.5*0.5,0) -> 67.375 | D22: IF( PayType = Hourly, HourlyRate * OT_Hours * 0.5, 0 ) | E22: Calculates the FLSA overtime premium for E-1009 who worked 5.5 OT hours this period. Only the half-time premium (0.5x) is added — the straight-time pay is already included in regular gross. FLSA-compliant.
B23: Nested IF (Federal Withholding MFJ) | C23: =IFERROR(IF((INDEX('Payroll Register'!M$4:M$23,MATCH("E-1001",'Payroll Register'!A$4:A$23,0))*26)<=14600,(INDEX('Payroll Register'!M$4:M$23,MATCH("E-1001",'Payroll Register'!A$4:A$23,0))*26)*0.1,IF((INDEX('Payroll Register'!M$4:M$23,MATCH("E-1001",'Payroll Register'!A$4:A$23,0))*26)<=57750,1460+((INDEX('Payroll Register'!M$4:M$23,MATCH("E-1001",'Payroll Register'!A$4:A$23,0))*26)-14600)*0.12,IF((INDEX('Payroll Register'!M$4:M$23,MATCH("E-1001",'Payroll Register'!A$4:A$23,0))*26)<=113600,6628+((INDEX('Payroll Register'!M$4:M$23,MATCH("E-1001",'Payroll Register'!A$4:A$23,0))*26)-57750)*0.22,18914+((INDEX('Payroll Register'!M$4:M$23,MATCH("E-1001",'Payroll Register'!A$4:A$23,0))*26)-113600)*0.24)))/26,0) -> 740.38462 | D23: IF( Annual<=14600, Annual*10%, IF( Annual<=57750, 1460+(Annual-14600)*12%, IF( Annual<=113600, 6628+(Annual-57750)*22%, 18914+(Annual-113600)*24% ) ) ) / 26 | E23: IRS Pub 15-T 2024 Percentage Method for Married Filing Jointly. Annualizes bi-weekly gross (x26), tests each bracket threshold in sequence, calculates annual tax at correct marginal rate, divides by 26 for per-period withholding. Anderson (E-1001, $115K MFJ) should show ~$740.
B24: Nested IF (Federal Withholding Single) | C24: =IFERROR(IF((INDEX('Payroll Register'!M$4:M$23,MATCH("E-1005",'Payroll Register'!A$4:A$23,0))*26)<=7300,(INDEX('Payroll Register'!M$4:M$23,MATCH("E-1005",'Payroll Register'!A$4:A$23,0))*26)*0.1,IF((INDEX('Payroll Register'!M$4:M$23,MATCH("E-1005",'Payroll Register'!A$4:A$23,0))*26)<=28875,730+((INDEX('Payroll Register'!M$4:M$23,MATCH("E-1005",'Payroll Register'!A$4:A$23,0))*26)-7300)*0.12,IF((INDEX('Payroll Register'!M$4:M$23,MATCH("E-1005",'Payroll Register'!A$4:A$23,0))*26)<=56875,3319+((INDEX('Payroll Register'!M$4:M$23,MATCH("E-1005",'Payroll Register'!A$4:A$23,0))*26)-28875)*0.22,9479+((INDEX('Payroll Register'!M$4:M$23,MATCH("E-1005",'Payroll Register'!A$4:A$23,0))*26)-56875)*0.24)))/26,0) -> 348.71154 | D24: IF( Annual<=7300, Annual*10%, IF( Annual<=28875, 730+(Annual-7300)*12%, IF( Annual<=56875, 3319+(Annual-28875)*22%, 9479+(Annual-56875)*24% ) ) ) / 26 | E24: IRS Pub 15-T 2024 Single filer table. Davis (E-1005, $55K Single) falls in the 22% bracket. Formula annualizes, finds the bracket, calculates tax at correct marginal rate, divides by 26. Should show ~$349.
B25: ROUND — Social Security (6.2% with Wage Base) | C25: =ROUND(IFERROR(INDEX('Payroll Register'!M$4:M$23,MATCH("E-1001",'Payroll Register'!A$4:A$23,0)),0)*0.062,2) -> 274.23 | D25: ROUND( GrossTotal * 0.062, 2 ) | E25: Calculates employee Social Security contribution at 6.2% for Anderson (E-1001). ROUND ensures exactly 2 decimal places — no floating point rounding errors accumulating across 26 pay periods. Full wage base monitor is in YTD Summary.
B26: ROUND — Medicare (1.45% No Wage Base) | C26: =ROUND(IFERROR(INDEX('Payroll Register'!M$4:M$23,MATCH("E-1001",'Payroll Register'!A$4:A$23,0)),0)*0.0145,2) -> 64.13 | D26: ROUND( GrossTotal * 0.0145, 2 ) | E26: Calculates Medicare (HI) tax at 1.45% with no wage base limit. An additional 0.9% applies for wages over $200K annually — monitored in YTD Summary. ROUND prevents cent-level rounding errors.
B27: ROUND — Georgia State Tax (5.49% Flat Rate) | C27: =ROUND(IFERROR(INDEX('Payroll Register'!M$4:M$23,MATCH("E-1001",'Payroll Register'!A$4:A$23,0)),0)*INDEX('Employee Master'!N$4:N$23,MATCH("E-1001",'Employee Master'!A$4:A$23,0)),2) -> 242.83 | D27: ROUND( GrossTotal * INDEX( GA_Rate_Range, MATCH( EmpID, EmpID_Range, 0 ) ), 2 ) | E27: Georgia flat income tax at 5.49% (effective Jan 1 2024) applied to gross wages. Rate is pulled from Employee Master via INDEX-MATCH — if the rate changes, update one cell and the entire payroll updates automatically.
B28: SUMIFS — Department Gross Pay Total | C28: =SUMIFS('Payroll Register'!M$4:M$23,'Payroll Register'!D$4:D$23,"Finance") -> 9692.3077 | D28: SUMIFS( GrossPay_Range, Department_Range, "Finance" ) | E28: Totals gross pay for all Finance department employees in the current pay period. Automatically includes any new Finance employees added to the register. Used across all 6 departments in the Department Summary sheet.
B29: SUMIFS — Department Total Tax Withheld | C29: =SUMIFS('Payroll Register'!R$4:R$23,'Payroll Register'!D$4:D$23,"Information Technology") -> 3571.1877 | D29: SUMIFS( TotalTax_Range, Department_Range, "Information Technology" ) | E29: Totals all tax withheld (federal + SS + Medicare + GA) for the IT department. Management can see total tax burden per department at a glance. Same SUMIFS pattern used for gross, taxes, deductions, and net across all departments.
B30: SUMIFS — YTD (Prior + Current) | C30: =SUMIFS('Prior YTD (Jan-May)'!E$4:E$23,'Prior YTD (Jan-May)'!A$4:A$23,"E-1015")+SUMIFS('Payroll Register'!M$4:M$23,'Payroll Register'!A$4:A$23,"E-1015") -> 69384.612 | D30: SUMIFS( PriorHistory_Gross, EmpID_Range, ThisEmployee ) + SUMIFS( CurrentRegister_Gross, EmpID_Range, ThisEmployee ) | E30: True YTD gross for VP of Sales (E-1015 White) — sums verified prior 10 periods from the Prior YTD sheet plus the current period from the Payroll Register. Includes Q1 and Q2 bonuses already paid. Accurate for W-2 preparation.
B31: SUMIFS — YTD Total Tax Withheld | C31: =SUMIFS('Prior YTD (Jan-May)'!J$4:J$23,'Prior YTD (Jan-May)'!A$4:A$23,"E-1003")+SUMIFS('Payroll Register'!R$4:R$23,'Payroll Register'!A$4:A$23,"E-1003") -> 16108.652 | D31: SUMIFS( PriorTax, EmpID, Employee ) + SUMIFS( CurrentTax, EmpID, Employee ) | E31: Year-to-date total taxes withheld for Williams (E-1003, Controller). Combines prior 10 periods with current period. Accurate cumulative tax figure for year-end reporting and employee tax queries.
B32: COUNTIF — Active Employee Count | C32: =COUNTIF('Employee Master'!K$4:K$23,"Active") -> 20 | D32: COUNTIF( Status_Range, "Active" ) | E32: Counts all employees with Active status in the Employee Master. Used in the Dashboard KPI card. If an employee is terminated (status changed to Inactive), this count automatically decreases and payroll rows are excluded from totals.
B33: COUNTIF — Department Headcount | C33: =COUNTIF('Payroll Register'!D$4:D$23,"Sales") -> 4 | D33: COUNTIF( Department_Range, "Sales" ) | E33: Counts employees in the Sales department for the Department Summary. Management sees headcount alongside payroll cost — enabling cost-per-employee analysis by department. Updates automatically when employees are added or change departments.
B34: IFERROR — Lookup Protection | C34: =IFERROR(INDEX('Employee Master'!B$4:B$23,MATCH("E-9999",'Employee Master'!A$4:A$23,0)),"Employee Not Found") -> Employee Not Found | D34: IFERROR( INDEX( MATCH( ... ) ), "Employee Not Found" ) | E34: Demonstrates error protection — E-9999 does not exist. Without IFERROR this returns a lookup error that cascades into gross pay, taxes, and net pay, breaking the entire row. With IFERROR it returns clean text. Every single lookup in this workbook is wrapped in IFERROR.
B35: IFERROR — Division Protection | C35: =IFERROR(INDEX('Employee Master'!O$4:O$23,MATCH("E-1008",'Employee Master'!A$4:A$23,0))/26,0) -> 11.346154 | D35: IFERROR( BenefitAnnual / 26, 0 ) | E35: Divides E-1008's annual health insurance premium by 26 for the per-period deduction. IFERROR returns 0 if the employee has no benefit election (NULL value) — preventing a division error from crashing the deduction column for that employee.
B36: SUM — Gross Components (Per Employee Row) | C36: =IFERROR(INDEX('Payroll Register'!I$4:I$23,MATCH("E-1015",'Payroll Register'!A$4:A$23,0))+INDEX('Payroll Register'!J$4:J$23,MATCH("E-1015",'Payroll Register'!A$4:A$23,0))+INDEX('Payroll Register'!K$4:K$23,MATCH("E-1015",'Payroll Register'!A$4:A$23,0))+INDEX('Payroll Register'!L$4:L$23,MATCH("E-1015",'Payroll Register'!A$4:A$23,0)),0) -> 7807.6923 | D36: SUM( BasePay, OT_Premium, HolidayPay, Bonus ) | E36: Total gross pay for E-1015 (White, VP Sales) = base salary/26 + overtime premium + holiday pay + bonus/commission. Each component is separate so management can see exactly what drives gross pay. This period includes a $2,500 commission payment.
B37: SUM — Net Pay (Gross minus All Deductions) | C37: =IFERROR(INDEX('Payroll Register'!M$4:M$23,MATCH("E-1001",'Payroll Register'!A$4:A$23,0))-INDEX('Payroll Register'!R$4:R$23,MATCH("E-1001",'Payroll Register'!A$4:A$23,0))-INDEX('Payroll Register'!X$4:X$23,MATCH("E-1001",'Payroll Register'!A$4:A$23,0)),0) -> 2801.1223 | D37: GrossTotal - TotalTaxWithheld - TotalBenefitDeductions | E37: Net take-home pay for Anderson (E-1001, HR Director): gross minus all taxes (federal, SS, Medicare, GA) minus all benefit deductions (health, dental, vision, 401k, life insurance). This is the amount deposited directly to the employee's bank account.
A40: Muhammad Zeenat Ullah | CA Finalist (ICAP) | QBO ProAdvisor | Excel Expert | zeenatullah.bookkeeper@gmail.com | WhatsApp: +44 7577 845321
A41: Portfolio Sample — All company names, employee names, and figures are entirely fictitious. Created to demonstrate advanced Excel payroll formula expertise.

Sheet Dashboard
A1: PAYROLL DASHBOARD | SUMMIT HR SOLUTIONS | Atlanta, GA | Pay Period: June 1–14, 2026
A2: Bi-Weekly · Check Date: June 19, 2026 · 11 Pay Periods YTD · Fed W/H: IRS Pub 15-T Percentage Method · All figures in USD
A4: Total Gross Payroll | D4: Total Net Pay | G4: Total Tax Withheld | J4: Total Deductions | M4: Active Employees
A5: ='Payroll Register'!M24 -> 63678.106 | D5: ='Payroll Register'!Y24 -> 40164.22 | G5: ='Payroll Register'!R24 -> 19263.955 | J5: ='Payroll Register'!X24 -> 4249.9308 | M5: =COUNTIF('Employee Master'!K4:K23,"Active") -> 20
A8: DEPARTMENT BREAKDOWN — CURRENT PAY PERIOD (from Dept Summary via SUMIFS)
A9: Department | B9: Headcount | C9: Gross Pay | D9: Tax W/H | E9: Deductions | F9: Net Pay | G9: % of Gross
A10: Human Resources | B10: ='Dept Summary'!B4 -> 2 | C10: ='Dept Summary'!C4 -> 7423.0769 | D10: ='Dept Summary'!H4 -> 2275.3515 | E10: ='Dept Summary'!I4 -> 444.80308 | F10: ='Dept Summary'!J4 -> 4702.9223 | G10: =C10/'Dept Summary'!C10 -> 0.11657189
A11: Finance | B11: ='Dept Summary'!B5 -> 3 | C11: ='Dept Summary'!C5 -> 9692.3077 | D11: ='Dept Summary'!H5 -> 2959.1462 | E11: ='Dept Summary'!I5 -> 661.54 | F11: ='Dept Summary'!J5 -> 6071.6215 | G11: =C11/'Dept Summary'!C10 -> 0.15220785
A12: Operations | B12: ='Dept Summary'!B6 -> 5 | C12: ='Dept Summary'!C6 -> 11663.221 | D12: ='Dept Summary'!H6 -> 3404.2856 | E12: ='Dept Summary'!I6 -> 604.41923 | F12: ='Dept Summary'!J6 -> 7654.5163 | G12: =C12/'Dept Summary'!C10 -> 0.18315905
A13: Information Technology | B13: ='Dept Summary'!B7 -> 4 | C13: ='Dept Summary'!C7 -> 12088.923 | D13: ='Dept Summary'!H7 -> 3571.1877 | E13: ='Dept Summary'!I7 -> 856.01462 | F13: ='Dept Summary'!J7 -> 7661.7208 | G13: =C13/'Dept Summary'!C10 -> 0.18984426
A14: Sales | B14: ='Dept Summary'!B8 -> 4 | C14: ='Dept Summary'!C8 -> 16425.962 | D14: ='Dept Summary'!H8 -> 5159.9569 | E14: ='Dept Summary'!I8 -> 1211.0369 | F14: ='Dept Summary'!J8 -> 10054.968 | G14: =C14/'Dept Summary'!C10 -> 0.25795305
A15: Marketing | B15: ='Dept Summary'!B9 -> 2 | C15: ='Dept Summary'!C9 -> 6384.6154 | D15: ='Dept Summary'!H9 -> 1894.0269 | E15: ='Dept Summary'!I9 -> 472.11692 | F15: ='Dept Summary'!J9 -> 4018.4715 | G15: =C15/'Dept Summary'!C10 -> 0.1002639
A16: TOTAL | B16: =SUM(B10:B15) -> 20 | C16: =SUM(C10:C15) -> 63678.106 | D16: =SUM(D10:D15) -> 19263.955 | E16: =SUM(E10:E15) -> 4249.9308 | F16: =SUM(F10:F15) -> 40164.22 | G16: =SUM(G10:G15) -> 1
A18: CONFIDENTIAL — Internal Use Only | Summit HR Solutions | Federal W/H per IRS Pub 15-T (2024) — verify brackets for 2026 upon IRS release | Formulas: INDEX-MATCH · SUMIFS · Nested IF · IFERROR · COUNTIF · Dynamic Arrays
A20: Prepared by: Muhammad Zeenat Ullah | CA Finalist (ICAP) · QBO ProAdvisor · Excel Expert | zeenatullah.bookkeeper@gmail.com | WA: +44 7577 845321
A21: Portfolio Sample — All employee names, SSNs, and company data are entirely fictitious and created solely to demonstrate financial formula expertise.

Sheet YTD Summary
A1: YEAR-TO-DATE EARNINGS & TAX SUMMARY | January 1 – June 14, 2026 (11 Pay Periods) | Summit HR Solutions
A2: Formulas used: SUMIFS · INDEX-MATCH · IFERROR · SUM · ROUND · MAX · Nested IF · Division · Arithmetic — Muhammad Zeenat Ullah · CA Finalist (ICAP) · QBO ProAdvisor
A4: SUMIFS | C4: INDEX-MATCH | E4: IFERROR | G4: SUM | I4: ROUND | K4: MAX | M4: Nested IF | O4: Arithmetic
A5: Emp ID | B5: Last Name [INDEX-MATCH] | C5: First Name [INDEX-MATCH] | D5: Department [INDEX-MATCH] | E5: YTD Gross [SUMIFS] | F5: YTD Fed W/H [SUMIFS] | G5: YTD SS Tax [SUMIFS] | H5: YTD Medicare [SUMIFS] | I5: YTD GA Tax [SUMIFS] | J5: YTD Total Tax [SUM] | K5: YTD Health [SUMIFS] | L5: YTD Dental [SUMIFS] | M5: YTD Vision [SUMIFS] | N5: YTD 401(k) [SUMIFS] | O5: YTD Total Ded [SUM] | P5: YTD Net Pay [SUM] | Q5: Eff Tax Rate [ROUND] | R5: 401k % of Gross [ROUND] | S5: SS Base Remaining [MAX] | T5: SS Wage Base Status [Nested IF] | U5: Projected Annual [Arithmetic] | V5: Periods Remaining [Arithmetic]
A6: E-1001 | B6: =IFERROR(INDEX('Employee Master'!B$4:B$23,MATCH(A6,'Employee Master'!A$4:A$23,0)),"") -> Anderson | C6: =IFERROR(INDEX('Employee Master'!C$4:C$23,MATCH(A6,'Employee Master'!A$4:A$23,0)),"") -> Michael | D6: =IFERROR(INDEX('Employee Master'!E$4:E$23,MATCH(A6,'Employee Master'!A$4:A$23,0)),"") -> Human Resources | E6: =SUMIFS('Prior YTD (Jan-May)'!E$4:E$23,'Prior YTD (Jan-May)'!A$4:A$23,A6)+SUMIFS('Payroll Register'!M$4:M$23,'Payroll Register'!A$4:A$23,A6) -> 48653.847 | F6: =SUMIFS('Prior YTD (Jan-May)'!F$4:F$23,'Prior YTD (Jan-May)'!A$4:A$23,A6)+SUMIFS('Payroll Register'!N$4:N$23,'Payroll Register'!A$4:A$23,A6) -> 8144.2346 | G6: =SUMIFS('Prior YTD (Jan-May)'!G$4:G$23,'Prior YTD (Jan-May)'!A$4:A$23,A6)+SUMIFS('Payroll Register'!O$4:O$23,'Payroll Register'!A$4:A$23,A6) -> 3016.54 | H6: =SUMIFS('Prior YTD (Jan-May)'!H$4:H$23,'Prior YTD (Jan-May)'!A$4:A$23,A6)+SUMIFS('Payroll Register'!P$4:P$23,'Payroll Register'!A$4:A$23,A6) -> 705.48 | I6: =SUMIFS('Prior YTD (Jan-May)'!I$4:I$23,'Prior YTD (Jan-May)'!A$4:A$23,A6)+SUMIFS('Payroll Register'!Q$4:Q$23,'Payroll Register'!A$4:A$23,A6) -> 2671.1 | J6: =SUM(F6:I6) -> 14537.355 | K6: =SUMIFS('Prior YTD (Jan-May)'!K$4:K$23,'Prior YTD (Jan-May)'!A$4:A$23,A6)+SUMIFS('Payroll Register'!S$4:S$23,'Payroll Register'!A$4:A$23,A6) -> 359.61231 | L6: =SUMIFS('Prior YTD (Jan-May)'!L$4:L$23,'Prior YTD (Jan-May)'!A$4:A$23,A6)+SUMIFS('Payroll Register'!T$4:T$23,'Payroll Register'!A$4:A$23,A6) -> 19.040769 | M6: =SUMIFS('Prior YTD (Jan-May)'!M$4:M$23,'Prior YTD (Jan-May)'!A$4:A$23,A6)+SUMIFS('Payroll Register'!U$4:U$23,'Payroll Register'!A$4:A$23,A6) -> 6.3469231 | N6: =SUMIFS('Prior YTD (Jan-May)'!N$4:N$23,'Prior YTD (Jan-May)'!A$4:A$23,A6)+SUMIFS('Payroll Register'!V$4:V$23,'Payroll Register'!A$4:A$23,A6) -> 2919.23 | O6: =SUM(K6:N6) -> 3304.23 | P6: =E6-J6-O6 -> 30812.262 | Q6: =IFERROR(ROUND(J6/E6,4),0) -> 0.2988 | R6: =IFERROR(ROUND(N6/E6,4),0) -> 0.06 | S6: =MAX(0,176100-E6) -> 127446.15 | T6: =IF(E6>=176100,"BASE REACHED — STOP SS",IF(E6>=149685,"WARNING: >85% Used",IF(E6>=114465,"MONITOR: >65% Used","Within Safe Limit"))) -> Within Safe Limit | U6: =ROUND(E6/11*26,2) -> 115000 | V6: =26-11 -> 15
A7: E-1002 | B7: =IFERROR(INDEX('Employee Master'!B$4:B$23,MATCH(A7,'Employee Master'!A$4:A$23,0)),"") -> Johnson | C7: =IFERROR(INDEX('Employee Master'!C$4:C$23,MATCH(A7,'Employee Master'!A$4:A$23,0)),"") -> Sarah | D7: =IFERROR(INDEX('Employee Master'!E$4:E$23,MATCH(A7,'Employee Master'!A$4:A$23,0)),"") -> Human Resources | E7: =SUMIFS('Prior YTD (Jan-May)'!E$4:E$23,'Prior YTD (Jan-May)'!A$4:A$23,A7)+SUMIFS('Payroll Register'!M$4:M$23,'Payroll Register'!A$4:A$23,A7) -> 33000 | F7: =SUMIFS('Prior YTD (Jan-May)'!F$4:F$23,'Prior YTD (Jan-May)'!A$4:A$23,A7)+SUMIFS('Payroll Register'!N$4:N$23,'Payroll Register'!A$4:A$23,A7) -> 6155.3469 | G7: =SUMIFS('Prior YTD (Jan-May)'!G$4:G$23,'Prior YTD (Jan-May)'!A$4:A$23,A7)+SUMIFS('Payroll Register'!O$4:O$23,'Payroll Register'!A$4:A$23,A7) -> 2046 | H7: =SUMIFS('Prior YTD (Jan-May)'!H$4:H$23,'Prior YTD (Jan-May)'!A$4:A$23,A7)+SUMIFS('Payroll Register'!P$4:P$23,'Payroll Register'!A$4:A$23,A7) -> 478.5 | I7: =SUMIFS('Prior YTD (Jan-May)'!I$4:I$23,'Prior YTD (Jan-May)'!A$4:A$23,A7)+SUMIFS('Payroll Register'!Q$4:Q$23,'Payroll Register'!A$4:A$23,A7) -> 1811.7 | J7: =SUM(F7:I7) -> 10491.547 | K7: =SUMIFS('Prior YTD (Jan-May)'!K$4:K$23,'Prior YTD (Jan-May)'!A$4:A$23,A7)+SUMIFS('Payroll Register'!S$4:S$23,'Payroll Register'!A$4:A$23,A7) -> 232.69385 | L7: =SUMIFS('Prior YTD (Jan-May)'!L$4:L$23,'Prior YTD (Jan-May)'!A$4:A$23,A7)+SUMIFS('Payroll Register'!T$4:T$23,'Payroll Register'!A$4:A$23,A7) -> 19.040769 | M7: =SUMIFS('Prior YTD (Jan-May)'!M$4:M$23,'Prior YTD (Jan-May)'!A$4:A$23,A7)+SUMIFS('Payroll Register'!U$4:U$23,'Payroll Register'!A$4:A$23,A7) -> 6.3469231 | N7: =SUMIFS('Prior YTD (Jan-May)'!N$4:N$23,'Prior YTD (Jan-May)'!A$4:A$23,A7)+SUMIFS('Payroll Register'!V$4:V$23,'Payroll Register'!A$4:A$23,A7) -> 1320 | O7: =SUM(K7:N7) -> 1578.0815 | P7: =E7-J7-O7 -> 20930.372 | Q7: =IFERROR(ROUND(J7/E7,4),0) -> 0.3179 | R7: =IFERROR(ROUND(N7/E7,4),0) -> 0.04 | S7: =MAX(0,176100-E7) -> 143100 | T7: =IF(E7>=176100,"BASE REACHED — STOP SS",IF(E7>=149685,"WARNING: >85% Used",IF(E7>=114465,"MONITOR: >65% Used","Within Safe Limit"))) -> Within Safe Limit | U7: =ROUND(E7/11*26,2) -> 78000 | V7: =26-11 -> 15
A8: E-1003 | B8: =IFERROR(INDEX('Employee Master'!B$4:B$23,MATCH(A8,'Employee Master'!A$4:A$23,0)),"") -> Williams | C8: =IFERROR(INDEX('Employee Master'!C$4:C$23,MATCH(A8,'Employee Master'!A$4:A$23,0)),"") -> David | D8: =IFERROR(INDEX('Employee Master'!E$4:E$23,MATCH(A8,'Employee Master'!A$4:A$23,0)),"") -> Finance | E8: =SUMIFS('Prior YTD (Jan-May)'!E$4:E$23,'Prior YTD (Jan-May)'!A$4:A$23,A8)+SUMIFS('Payroll Register'!M$4:M$23,'Payroll Register'!A$4:A$23,A8) -> 52884.612 | F8: =SUMIFS('Prior YTD (Jan-May)'!F$4:F$23,'Prior YTD (Jan-May)'!A$4:A$23,A8)+SUMIFS('Payroll Register'!N$4:N$23,'Payroll Register'!A$4:A$23,A8) -> 9159.6123 | G8: =SUMIFS('Prior YTD (Jan-May)'!G$4:G$23,'Prior YTD (Jan-May)'!A$4:A$23,A8)+SUMIFS('Payroll Register'!O$4:O$23,'Payroll Register'!A$4:A$23,A8) -> 3278.85 | H8: =SUMIFS('Prior YTD (Jan-May)'!H$4:H$23,'Prior YTD (Jan-May)'!A$4:A$23,A8)+SUMIFS('Payroll Register'!P$4:P$23,'Payroll Register'!A$4:A$23,A8) -> 766.83 | I8: =SUMIFS('Prior YTD (Jan-May)'!I$4:I$23,'Prior YTD (Jan-May)'!A$4:A$23,A8)+SUMIFS('Payroll Register'!Q$4:Q$23,'Payroll Register'!A$4:A$23,A8) -> 2903.36 | J8: =SUM(F8:I8) -> 16108.652 | K8: =SUMIFS('Prior YTD (Jan-May)'!K$4:K$23,'Prior YTD (Jan-May)'!A$4:A$23,A8)+SUMIFS('Payroll Register'!S$4:S$23,'Payroll Register'!A$4:A$23,A8) -> 359.61231 | L8: =SUMIFS('Prior YTD (Jan-May)'!L$4:L$23,'Prior YTD (Jan-May)'!A$4:A$23,A8)+SUMIFS('Payroll Register'!T$4:T$23,'Payroll Register'!A$4:A$23,A8) -> 19.040769 | M8: =SUMIFS('Prior YTD (Jan-May)'!M$4:M$23,'Prior YTD (Jan-May)'!A$4:A$23,A8)+SUMIFS('Payroll Register'!U$4:U$23,'Payroll Register'!A$4:A$23,A8) -> 6.3469231 | N8: =SUMIFS('Prior YTD (Jan-May)'!N$4:N$23,'Prior YTD (Jan-May)'!A$4:A$23,A8)+SUMIFS('Payroll Register'!V$4:V$23,'Payroll Register'!A$4:A$23,A8) -> 4230.77 | O8: =SUM(K8:N8) -> 4615.77 | P8: =E8-J8-O8 -> 32160.19 | Q8: =IFERROR(ROUND(J8/E8,4),0) -> 0.3046 | R8: =IFERROR(ROUND(N8/E8,4),0) -> 0.08 | S8: =MAX(0,176100-E8) -> 123215.39 | T8: =IF(E8>=176100,"BASE REACHED — STOP SS",IF(E8>=149685,"WARNING: >85% Used",IF(E8>=114465,"MONITOR: >65% Used","Within Safe Limit"))) -> Within Safe Limit | U8: =ROUND(E8/11*26,2) -> 124999.99 | V8: =26-11 -> 15
A9: E-1004 | B9: =IFERROR(INDEX('Employee Master'!B$4:B$23,MATCH(A9,'Employee Master'!A$4:A$23,0)),"") -> Brown | C9: =IFERROR(INDEX('Employee Master'!C$4:C$23,MATCH(A9,'Employee Master'!A$4:A$23,0)),"") -> Jessica | D9: =IFERROR(INDEX('Employee Master'!E$4:E$23,MATCH(A9,'Employee Master'!A$4:A$23,0)),"") -> Finance | E9: =SUMIFS('Prior YTD (Jan-May)'!E$4:E$23,'Prior YTD (Jan-May)'!A$4:A$23,A9)+SUMIFS('Payroll Register'!M$4:M$23,'Payroll Register'!A$4:A$23,A9) -> 30461.541 | F9: =SUMIFS('Prior YTD (Jan-May)'!F$4:F$23,'Prior YTD (Jan-May)'!A$4:A$23,A9)+SUMIFS('Payroll Register'!N$4:N$23,'Payroll Register'!A$4:A$23,A9) -> 5546.1123 | G9: =SUMIFS('Prior YTD (Jan-May)'!G$4:G$23,'Prior YTD (Jan-May)'!A$4:A$23,A9)+SUMIFS('Payroll Register'!O$4:O$23,'Payroll Register'!A$4:A$23,A9) -> 1888.61 | H9: =SUMIFS('Prior YTD (Jan-May)'!H$4:H$23,'Prior YTD (Jan-May)'!A$4:A$23,A9)+SUMIFS('Payroll Register'!P$4:P$23,'Payroll Register'!A$4:A$23,A9) -> 441.69 | I9: =SUMIFS('Prior YTD (Jan-May)'!I$4:I$23,'Prior YTD (Jan-May)'!A$4:A$23,A9)+SUMIFS('Payroll Register'!Q$4:Q$23,'Payroll Register'!A$4:A$23,A9) -> 1672.34 | J9: =SUM(F9:I9) -> 9548.7523 | K9: =SUMIFS('Prior YTD (Jan-May)'!K$4:K$23,'Prior YTD (Jan-May)'!A$4:A$23,A9)+SUMIFS('Payroll Register'!S$4:S$23,'Payroll Register'!A$4:A$23,A9) -> 232.69385 | L9: =SUMIFS('Prior YTD (Jan-May)'!L$4:L$23,'Prior YTD (Jan-May)'!A$4:A$23,A9)+SUMIFS('Payroll Register'!T$4:T$23,'Payroll Register'!A$4:A$23,A9) -> 19.040769 | M9: =SUMIFS('Prior YTD (Jan-May)'!M$4:M$23,'Prior YTD (Jan-May)'!A$4:A$23,A9)+SUMIFS('Payroll Register'!U$4:U$23,'Payroll Register'!A$4:A$23,A9) -> 6.3469231 | N9: =SUMIFS('Prior YTD (Jan-May)'!N$4:N$23,'Prior YTD (Jan-May)'!A$4:A$23,A9)+SUMIFS('Payroll Register'!V$4:V$23,'Payroll Register'!A$4:A$23,A9) -> 1523.08 | O9: =SUM(K9:N9) -> 1781.1615 | P9: =E9-J9-O9 -> 19131.627 | Q9: =IFERROR(ROUND(J9/E9,4),0) -> 0.3135 | R9: =IFERROR(ROUND(N9/E9,4),0) -> 0.05 | S9: =MAX(0,176100-E9) -> 145638.46 | T9: =IF(E9>=176100,"BASE REACHED — STOP SS",IF(E9>=149685,"WARNING: >85% Used",IF(E9>=114465,"MONITOR: >65% Used","Within Safe Limit"))) -> Within Safe Limit | U9: =ROUND(E9/11*26,2) -> 72000.01 | V9: =26-11 -> 15
A10: E-1005 | B10: =IFERROR(INDEX('Employee Master'!B$4:B$23,MATCH(A10,'Employee Master'!A$4:A$23,0)),"") -> Davis | C10: =IFERROR(INDEX('Employee Master'!C$4:C$23,MATCH(A10,'Employee Master'!A$4:A$23,0)),"") -> Robert | D10: =IFERROR(INDEX('Employee Master'!E$4:E$23,MATCH(A10,'Employee Master'!A$4:A$23,0)),"") -> Finance | E10: =SUMIFS('Prior YTD (Jan-May)'!E$4:E$23,'Prior YTD (Jan-May)'!A$4:A$23,A10)+SUMIFS('Payroll Register'!M$4:M$23,'Payroll Register'!A$4:A$23,A10) -> 23269.235 | F10: =SUMIFS('Prior YTD (Jan-May)'!F$4:F$23,'Prior YTD (Jan-May)'!A$4:A$23,A10)+SUMIFS('Payroll Register'!N$4:N$23,'Payroll Register'!A$4:A$23,A10) -> 3835.8315 | G10: =SUMIFS('Prior YTD (Jan-May)'!G$4:G$23,'Prior YTD (Jan-May)'!A$4:A$23,A10)+SUMIFS('Payroll Register'!O$4:O$23,'Payroll Register'!A$4:A$23,A10) -> 1442.69 | H10: =SUMIFS('Prior YTD (Jan-May)'!H$4:H$23,'Prior YTD (Jan-May)'!A$4:A$23,A10)+SUMIFS('Payroll Register'!P$4:P$23,'Payroll Register'!A$4:A$23,A10) -> 337.4 | I10: =SUMIFS('Prior YTD (Jan-May)'!I$4:I$23,'Prior YTD (Jan-May)'!A$4:A$23,A10)+SUMIFS('Payroll Register'!Q$4:Q$23,'Payroll Register'!A$4:A$23,A10) -> 1277.48 | J10: =SUM(F10:I10) -> 6893.4015 | K10: =SUMIFS('Prior YTD (Jan-May)'!K$4:K$23,'Prior YTD (Jan-May)'!A$4:A$23,A10)+SUMIFS('Payroll Register'!S$4:S$23,'Payroll Register'!A$4:A$23,A10) -> 124.80615 | L10: =SUMIFS('Prior YTD (Jan-May)'!L$4:L$23,'Prior YTD (Jan-May)'!A$4:A$23,A10)+SUMIFS('Payroll Register'!T$4:T$23,'Payroll Register'!A$4:A$23,A10) -> 19.040769 | M10: =SUMIFS('Prior YTD (Jan-May)'!M$4:M$23,'Prior YTD (Jan-May)'!A$4:A$23,A10)+SUMIFS('Payroll Register'!U$4:U$23,'Payroll Register'!A$4:A$23,A10) -> 6.3469231 | N10: =SUMIFS('Prior YTD (Jan-May)'!N$4:N$23,'Prior YTD (Jan-May)'!A$4:A$23,A10)+SUMIFS('Payroll Register'!V$4:V$23,'Payroll Register'!A$4:A$23,A10) -> 698.08 | O10: =SUM(K10:N10) -> 848.27385 | P10: =E10-J10-O10 -> 15527.559 | Q10: =IFERROR(ROUND(J10/E10,4),0) -> 0.2962 | R10: =IFERROR(ROUND(N10/E10,4),0) -> 0.03 | S10: =MAX(0,176100-E10) -> 152830.77 | T10: =IF(E10>=176100,"BASE REACHED — STOP SS",IF(E10>=149685,"WARNING: >85% Used",IF(E10>=114465,"MONITOR: >65% Used","Within Safe Limit"))) -> Within Safe Limit | U10: =ROUND(E10/11*26,2) -> 55000.01 | V10: =26-11 -> 15
A11: E-1006 | B11: =IFERROR(INDEX('Employee Master'!B$4:B$23,MATCH(A11,'Employee Master'!A$4:A$23,0)),"") -> Martinez | C11: =IFERROR(INDEX('Employee Master'!C$4:C$23,MATCH(A11,'Employee Master'!A$4:A$23,0)),"") -> Elena | D11: =IFERROR(INDEX('Employee Master'!E$4:E$23,MATCH(A11,'Employee Master'!A$4:A$23,0)),"") -> Operations | E11: =SUMIFS('Prior YTD (Jan-May)'!E$4:E$23,'Prior YTD (Jan-May)'!A$4:A$23,A11)+SUMIFS('Payroll Register'!M$4:M$23,'Payroll Register'!A$4:A$23,A11) -> 40192.306 | F11: =SUMIFS('Prior YTD (Jan-May)'!F$4:F$23,'Prior YTD (Jan-May)'!A$4:A$23,A11)+SUMIFS('Payroll Register'!N$4:N$23,'Payroll Register'!A$4:A$23,A11) -> 6271.2654 | G11: =SUMIFS('Prior YTD (Jan-May)'!G$4:G$23,'Prior YTD (Jan-May)'!A$4:A$23,A11)+SUMIFS('Payroll Register'!O$4:O$23,'Payroll Register'!A$4:A$23,A11) -> 2491.92 | H11: =SUMIFS('Prior YTD (Jan-May)'!H$4:H$23,'Prior YTD (Jan-May)'!A$4:A$23,A11)+SUMIFS('Payroll Register'!P$4:P$23,'Payroll Register'!A$4:A$23,A11) -> 582.79 | I11: =SUMIFS('Prior YTD (Jan-May)'!I$4:I$23,'Prior YTD (Jan-May)'!A$4:A$23,A11)+SUMIFS('Payroll Register'!Q$4:Q$23,'Payroll Register'!A$4:A$23,A11) -> 2206.56 | J11: =SUM(F11:I11) -> 11552.535 | K11: =SUMIFS('Prior YTD (Jan-May)'!K$4:K$23,'Prior YTD (Jan-May)'!A$4:A$23,A11)+SUMIFS('Payroll Register'!S$4:S$23,'Payroll Register'!A$4:A$23,A11) -> 359.61231 | L11: =SUMIFS('Prior YTD (Jan-May)'!L$4:L$23,'Prior YTD (Jan-May)'!A$4:A$23,A11)+SUMIFS('Payroll Register'!T$4:T$23,'Payroll Register'!A$4:A$23,A11) -> 19.040769 | M11: =SUMIFS('Prior YTD (Jan-May)'!M$4:M$23,'Prior YTD (Jan-May)'!A$4:A$23,A11)+SUMIFS('Payroll Register'!U$4:U$23,'Payroll Register'!A$4:A$23,A11) -> 6.3469231 | N11: =SUMIFS('Prior YTD (Jan-May)'!N$4:N$23,'Prior YTD (Jan-May)'!A$4:A$23,A11)+SUMIFS('Payroll Register'!V$4:V$23,'Payroll Register'!A$4:A$23,A11) -> 2813.46 | O11: =SUM(K11:N11) -> 3198.46 | P11: =E11-J11-O11 -> 25441.311 | Q11: =IFERROR(ROUND(J11/E11,4),0) -> 0.2874 | R11: =IFERROR(ROUND(N11/E11,4),0) -> 0.07 | S11: =MAX(0,176100-E11) -> 135907.69 | T11: =IF(E11>=176100,"BASE REACHED — STOP SS",IF(E11>=149685,"WARNING: >85% Used",IF(E11>=114465,"MONITOR: >65% Used","Within Safe Limit"))) -> Within Safe Limit | U11: =ROUND(E11/11*26,2) -> 95000 | V11: =26-11 -> 15
A12: E-1007 | B12: =IFERROR(INDEX('Employee Master'!B$4:B$23,MATCH(A12,'Employee Master'!A$4:A$23,0)),"") -> Garcia | C12: =IFERROR(INDEX('Employee Master'!C$4:C$23,MATCH(A12,'Employee Master'!A$4:A$23,0)),"") -> Carlos | D12: =IFERROR(INDEX('Employee Master'!E$4:E$23,MATCH(A12,'Employee Master'!A$4:A$23,0)),"") -> Operations | E12: =SUMIFS('Prior YTD (Jan-May)'!E$4:E$23,'Prior YTD (Jan-May)'!A$4:A$23,A12)+SUMIFS('Payroll Register'!M$4:M$23,'Payroll Register'!A$4:A$23,A12) -> 27500 | F12: =SUMIFS('Prior YTD (Jan-May)'!F$4:F$23,'Prior YTD (Jan-May)'!A$4:A$23,A12)+SUMIFS('Payroll Register'!N$4:N$23,'Payroll Register'!A$4:A$23,A12) -> 4835.3469 | G12: =SUMIFS('Prior YTD (Jan-May)'!G$4:G$23,'Prior YTD (Jan-May)'!A$4:A$23,A12)+SUMIFS('Payroll Register'!O$4:O$23,'Payroll Register'!A$4:A$23,A12) -> 1705 | H12: =SUMIFS('Prior YTD (Jan-May)'!H$4:H$23,'Prior YTD (Jan-May)'!A$4:A$23,A12)+SUMIFS('Payroll Register'!P$4:P$23,'Payroll Register'!A$4:A$23,A12) -> 398.75 | I12: =SUMIFS('Prior YTD (Jan-May)'!I$4:I$23,'Prior YTD (Jan-May)'!A$4:A$23,A12)+SUMIFS('Payroll Register'!Q$4:Q$23,'Payroll Register'!A$4:A$23,A12) -> 1509.75 | J12: =SUM(F12:I12) -> 8448.8469 | K12: =SUMIFS('Prior YTD (Jan-May)'!K$4:K$23,'Prior YTD (Jan-May)'!A$4:A$23,A12)+SUMIFS('Payroll Register'!S$4:S$23,'Payroll Register'!A$4:A$23,A12) -> 262.30615 | L12: =SUMIFS('Prior YTD (Jan-May)'!L$4:L$23,'Prior YTD (Jan-May)'!A$4:A$23,A12)+SUMIFS('Payroll Register'!T$4:T$23,'Payroll Register'!A$4:A$23,A12) -> 19.040769 | M12: =SUMIFS('Prior YTD (Jan-May)'!M$4:M$23,'Prior YTD (Jan-May)'!A$4:A$23,A12)+SUMIFS('Payroll Register'!U$4:U$23,'Payroll Register'!A$4:A$23,A12) -> 6.3469231 | N12: =SUMIFS('Prior YTD (Jan-May)'!N$4:N$23,'Prior YTD (Jan-May)'!A$4:A$23,A12)+SUMIFS('Payroll Register'!V$4:V$23,'Payroll Register'!A$4:A$23,A12) -> 1375 | O12: =SUM(K12:N12) -> 1662.6938 | P12: =E12-J12-O12 -> 17388.459 | Q12: =IFERROR(ROUND(J12/E12,4),0) -> 0.3072 | R12: =IFERROR(ROUND(N12/E12,4),0) -> 0.05 | S12: =MAX(0,176100-E12) -> 148600 | T12: =IF(E12>=176100,"BASE REACHED — STOP SS",IF(E12>=149685,"WARNING: >85% Used",IF(E12>=114465,"MONITOR: >65% Used","Within Safe Limit"))) -> Within Safe Limit | U12: =ROUND(E12/11*26,2) -> 65000 | V12: =26-11 -> 15
A13: E-1008 | B13: =IFERROR(INDEX('Employee Master'!B$4:B$23,MATCH(A13,'Employee Master'!A$4:A$23,0)),"") -> Miller | C13: =IFERROR(INDEX('Employee Master'!C$4:C$23,MATCH(A13,'Employee Master'!A$4:A$23,0)),"") -> Amanda | D13: =IFERROR(INDEX('Employee Master'!E$4:E$23,MATCH(A13,'Employee Master'!A$4:A$23,0)),"") -> Operations | E13: =SUMIFS('Prior YTD (Jan-May)'!E$4:E$23,'Prior YTD (Jan-May)'!A$4:A$23,A13)+SUMIFS('Payroll Register'!M$4:M$23,'Payroll Register'!A$4:A$23,A13) -> 22000 | F13: =SUMIFS('Prior YTD (Jan-May)'!F$4:F$23,'Prior YTD (Jan-May)'!A$4:A$23,A13)+SUMIFS('Payroll Register'!N$4:N$23,'Payroll Register'!A$4:A$23,A13) -> 3556.5969 | G13: =SUMIFS('Prior YTD (Jan-May)'!G$4:G$23,'Prior YTD (Jan-May)'!A$4:A$23,A13)+SUMIFS('Payroll Register'!O$4:O$23,'Payroll Register'!A$4:A$23,A13) -> 1364 | H13: =SUMIFS('Prior YTD (Jan-May)'!H$4:H$23,'Prior YTD (Jan-May)'!A$4:A$23,A13)+SUMIFS('Payroll Register'!P$4:P$23,'Payroll Register'!A$4:A$23,A13) -> 319 | I13: =SUMIFS('Prior YTD (Jan-May)'!I$4:I$23,'Prior YTD (Jan-May)'!A$4:A$23,A13)+SUMIFS('Payroll Register'!Q$4:Q$23,'Payroll Register'!A$4:A$23,A13) -> 1207.8 | J13: =SUM(F13:I13) -> 6447.3969 | K13: =SUMIFS('Prior YTD (Jan-May)'!K$4:K$23,'Prior YTD (Jan-May)'!A$4:A$23,A13)+SUMIFS('Payroll Register'!S$4:S$23,'Payroll Register'!A$4:A$23,A13) -> 124.80615 | L13: =SUMIFS('Prior YTD (Jan-May)'!L$4:L$23,'Prior YTD (Jan-May)'!A$4:A$23,A13)+SUMIFS('Payroll Register'!T$4:T$23,'Payroll Register'!A$4:A$23,A13) -> 19.040769 | M13: =SUMIFS('Prior YTD (Jan-May)'!M$4:M$23,'Prior YTD (Jan-May)'!A$4:A$23,A13)+SUMIFS('Payroll Register'!U$4:U$23,'Payroll Register'!A$4:A$23,A13) -> 0 | N13: =SUMIFS('Prior YTD (Jan-May)'!N$4:N$23,'Prior YTD (Jan-May)'!A$4:A$23,A13)+SUMIFS('Payroll Register'!V$4:V$23,'Payroll Register'!A$4:A$23,A13) -> 660 | O13: =SUM(K13:N13) -> 803.84692 | P13: =E13-J13-O13 -> 14748.756 | Q13: =IFERROR(ROUND(J13/E13,4),0) -> 0.2931 | R13: =IFERROR(ROUND(N13/E13,4),0) -> 0.03 | S13: =MAX(0,176100-E13) -> 154100 | T13: =IF(E13>=176100,"BASE REACHED — STOP SS",IF(E13>=149685,"WARNING: >85% Used",IF(E13>=114465,"MONITOR: >65% Used","Within Safe Limit"))) -> Within Safe Limit | U13: =ROUND(E13/11*26,2) -> 52000 | V13: =26-11 -> 15
A14: E-1009 | B14: =IFERROR(INDEX('Employee Master'!B$4:B$23,MATCH(A14,'Employee Master'!A$4:A$23,0)),"") -> Wilson | C14: =IFERROR(INDEX('Employee Master'!C$4:C$23,MATCH(A14,'Employee Master'!A$4:A$23,0)),"") -> James | D14: =IFERROR(INDEX('Employee Master'!E$4:E$23,MATCH(A14,'Employee Master'!A$4:A$23,0)),"") -> Operations | E14: =SUMIFS('Prior YTD (Jan-May)'!E$4:E$23,'Prior YTD (Jan-May)'!A$4:A$23,A14)+SUMIFS('Payroll Register'!M$4:M$23,'Payroll Register'!A$4:A$23,A14) -> 23023.875 | F14: =SUMIFS('Prior YTD (Jan-May)'!F$4:F$23,'Prior YTD (Jan-May)'!A$4:A$23,A14)+SUMIFS('Payroll Register'!N$4:N$23,'Payroll Register'!A$4:A$23,A14) -> 3781.8494 | G14: =SUMIFS('Prior YTD (Jan-May)'!G$4:G$23,'Prior YTD (Jan-May)'!A$4:A$23,A14)+SUMIFS('Payroll Register'!O$4:O$23,'Payroll Register'!A$4:A$23,A14) -> 1427.48 | H14: =SUMIFS('Prior YTD (Jan-May)'!H$4:H$23,'Prior YTD (Jan-May)'!A$4:A$23,A14)+SUMIFS('Payroll Register'!P$4:P$23,'Payroll Register'!A$4:A$23,A14) -> 333.85 | I14: =SUMIFS('Prior YTD (Jan-May)'!I$4:I$23,'Prior YTD (Jan-May)'!A$4:A$23,A14)+SUMIFS('Payroll Register'!Q$4:Q$23,'Payroll Register'!A$4:A$23,A14) -> 1264.01 | J14: =SUM(F14:I14) -> 6807.1894 | K14: =SUMIFS('Prior YTD (Jan-May)'!K$4:K$23,'Prior YTD (Jan-May)'!A$4:A$23,A14)+SUMIFS('Payroll Register'!S$4:S$23,'Payroll Register'!A$4:A$23,A14) -> 124.80615 | L14: =SUMIFS('Prior YTD (Jan-May)'!L$4:L$23,'Prior YTD (Jan-May)'!A$4:A$23,A14)+SUMIFS('Payroll Register'!T$4:T$23,'Payroll Register'!A$4:A$23,A14) -> 19.040769 | M14: =SUMIFS('Prior YTD (Jan-May)'!M$4:M$23,'Prior YTD (Jan-May)'!A$4:A$23,A14)+SUMIFS('Payroll Register'!U$4:U$23,'Payroll Register'!A$4:A$23,A14) -> 6.3469231 | N14: =SUMIFS('Prior YTD (Jan-May)'!N$4:N$23,'Prior YTD (Jan-May)'!A$4:A$23,A14)+SUMIFS('Payroll Register'!V$4:V$23,'Payroll Register'!A$4:A$23,A14) -> 690.71 | O14: =SUM(K14:N14) -> 840.90385 | P14: =E14-J14-O14 -> 15375.782 | Q14: =IFERROR(ROUND(J14/E14,4),0) -> 0.2957 | R14: =IFERROR(ROUND(N14/E14,4),0) -> 0.03 | S14: =MAX(0,176100-E14) -> 153076.12 | T14: =IF(E14>=176100,"BASE REACHED — STOP SS",IF(E14>=149685,"WARNING: >85% Used",IF(E14>=114465,"MONITOR: >65% Used","Within Safe Limit"))) -> Within Safe Limit | U14: =ROUND(E14/11*26,2) -> 54420.07 | V14: =26-11 -> 15
A15: E-1010 | B15: =IFERROR(INDEX('Employee Master'!B$4:B$23,MATCH(A15,'Employee Master'!A$4:A$23,0)),"") -> Moore | C15: =IFERROR(INDEX('Employee Master'!C$4:C$23,MATCH(A15,'Employee Master'!A$4:A$23,0)),"") -> Patricia | D15: =IFERROR(INDEX('Employee Master'!E$4:E$23,MATCH(A15,'Employee Master'!A$4:A$23,0)),"") -> Operations | E15: =SUMIFS('Prior YTD (Jan-May)'!E$4:E$23,'Prior YTD (Jan-May)'!A$4:A$23,A15)+SUMIFS('Payroll Register'!M$4:M$23,'Payroll Register'!A$4:A$23,A15) -> 17281.25 | F15: =SUMIFS('Prior YTD (Jan-May)'!F$4:F$23,'Prior YTD (Jan-May)'!A$4:A$23,A15)+SUMIFS('Payroll Register'!N$4:N$23,'Payroll Register'!A$4:A$23,A15) -> 2518.4669 | G15: =SUMIFS('Prior YTD (Jan-May)'!G$4:G$23,'Prior YTD (Jan-May)'!A$4:A$23,A15)+SUMIFS('Payroll Register'!O$4:O$23,'Payroll Register'!A$4:A$23,A15) -> 1071.44 | H15: =SUMIFS('Prior YTD (Jan-May)'!H$4:H$23,'Prior YTD (Jan-May)'!A$4:A$23,A15)+SUMIFS('Payroll Register'!P$4:P$23,'Payroll Register'!A$4:A$23,A15) -> 250.58 | I15: =SUMIFS('Prior YTD (Jan-May)'!I$4:I$23,'Prior YTD (Jan-May)'!A$4:A$23,A15)+SUMIFS('Payroll Register'!Q$4:Q$23,'Payroll Register'!A$4:A$23,A15) -> 948.74 | J15: =SUM(F15:I15) -> 4789.2269 | K15: =SUMIFS('Prior YTD (Jan-May)'!K$4:K$23,'Prior YTD (Jan-May)'!A$4:A$23,A15)+SUMIFS('Payroll Register'!S$4:S$23,'Payroll Register'!A$4:A$23,A15) -> 124.80615 | L15: =SUMIFS('Prior YTD (Jan-May)'!L$4:L$23,'Prior YTD (Jan-May)'!A$4:A$23,A15)+SUMIFS('Payroll Register'!T$4:T$23,'Payroll Register'!A$4:A$23,A15) -> 19.040769 | M15: =SUMIFS('Prior YTD (Jan-May)'!M$4:M$23,'Prior YTD (Jan-May)'!A$4:A$23,A15)+SUMIFS('Payroll Register'!U$4:U$23,'Payroll Register'!A$4:A$23,A15) -> 0 | N15: =SUMIFS('Prior YTD (Jan-May)'!N$4:N$23,'Prior YTD (Jan-May)'!A$4:A$23,A15)+SUMIFS('Payroll Register'!V$4:V$23,'Payroll Register'!A$4:A$23,A15) -> 0 | O15: =SUM(K15:N15) -> 143.84692 | P15: =E15-J15-O15 -> 12348.176 | Q15: =IFERROR(ROUND(J15/E15,4),0) -> 0.2771 | R15: =IFERROR(ROUND(N15/E15,4),0) -> 0 | S15: =MAX(0,176100-E15) -> 158818.75 | T15: =IF(E15>=176100,"BASE REACHED — STOP SS",IF(E15>=149685,"WARNING: >85% Used",IF(E15>=114465,"MONITOR: >65% Used","Within Safe Limit"))) -> Within Safe Limit | U15: =ROUND(E15/11*26,2) -> 40846.59 | V15: =26-11 -> 15
A16: E-1011 | B16: =IFERROR(INDEX('Employee Master'!B$4:B$23,MATCH(A16,'Employee Master'!A$4:A$23,0)),"") -> Taylor | C16: =IFERROR(INDEX('Employee Master'!C$4:C$23,MATCH(A16,'Employee Master'!A$4:A$23,0)),"") -> Kevin | D16: =IFERROR(INDEX('Employee Master'!E$4:E$23,MATCH(A16,'Employee Master'!A$4:A$23,0)),"") -> Information Technology | E16: =SUMIFS('Prior YTD (Jan-May)'!E$4:E$23,'Prior YTD (Jan-May)'!A$4:A$23,A16)+SUMIFS('Payroll Register'!M$4:M$23,'Payroll Register'!A$4:A$23,A16) -> 44423.072 | F16: =SUMIFS('Prior YTD (Jan-May)'!F$4:F$23,'Prior YTD (Jan-May)'!A$4:A$23,A16)+SUMIFS('Payroll Register'!N$4:N$23,'Payroll Register'!A$4:A$23,A16) -> 7202.0408 | G16: =SUMIFS('Prior YTD (Jan-May)'!G$4:G$23,'Prior YTD (Jan-May)'!A$4:A$23,A16)+SUMIFS('Payroll Register'!O$4:O$23,'Payroll Register'!A$4:A$23,A16) -> 2754.23 | H16: =SUMIFS('Prior YTD (Jan-May)'!H$4:H$23,'Prior YTD (Jan-May)'!A$4:A$23,A16)+SUMIFS('Payroll Register'!P$4:P$23,'Payroll Register'!A$4:A$23,A16) -> 644.14 | I16: =SUMIFS('Prior YTD (Jan-May)'!I$4:I$23,'Prior YTD (Jan-May)'!A$4:A$23,A16)+SUMIFS('Payroll Register'!Q$4:Q$23,'Payroll Register'!A$4:A$23,A16) -> 2438.83 | J16: =SUM(F16:I16) -> 13039.241 | K16: =SUMIFS('Prior YTD (Jan-May)'!K$4:K$23,'Prior YTD (Jan-May)'!A$4:A$23,A16)+SUMIFS('Payroll Register'!S$4:S$23,'Payroll Register'!A$4:A$23,A16) -> 359.61231 | L16: =SUMIFS('Prior YTD (Jan-May)'!L$4:L$23,'Prior YTD (Jan-May)'!A$4:A$23,A16)+SUMIFS('Payroll Register'!T$4:T$23,'Payroll Register'!A$4:A$23,A16) -> 19.040769 | M16: =SUMIFS('Prior YTD (Jan-May)'!M$4:M$23,'Prior YTD (Jan-May)'!A$4:A$23,A16)+SUMIFS('Payroll Register'!U$4:U$23,'Payroll Register'!A$4:A$23,A16) -> 6.3469231 | N16: =SUMIFS('Prior YTD (Jan-May)'!N$4:N$23,'Prior YTD (Jan-May)'!A$4:A$23,A16)+SUMIFS('Payroll Register'!V$4:V$23,'Payroll Register'!A$4:A$23,A16) -> 3553.85 | O16: =SUM(K16:N16) -> 3938.85 | P16: =E16-J16-O16 -> 27444.981 | Q16: =IFERROR(ROUND(J16/E16,4),0) -> 0.2935 | R16: =IFERROR(ROUND(N16/E16,4),0) -> 0.08 | S16: =MAX(0,176100-E16) -> 131676.93 | T16: =IF(E16>=176100,"BASE REACHED — STOP SS",IF(E16>=149685,"WARNING: >85% Used",IF(E16>=114465,"MONITOR: >65% Used","Within Safe Limit"))) -> Within Safe Limit | U16: =ROUND(E16/11*26,2) -> 104999.99 | V16: =26-11 -> 15
A17: E-1012 | B17: =IFERROR(INDEX('Employee Master'!B$4:B$23,MATCH(A17,'Employee Master'!A$4:A$23,0)),"") -> Anderson | C17: =IFERROR(INDEX('Employee Master'!C$4:C$23,MATCH(A17,'Employee Master'!A$4:A$23,0)),"") -> Lisa | D17: =IFERROR(INDEX('Employee Master'!E$4:E$23,MATCH(A17,'Employee Master'!A$4:A$23,0)),"") -> Information Technology | E17: =SUMIFS('Prior YTD (Jan-May)'!E$4:E$23,'Prior YTD (Jan-May)'!A$4:A$23,A17)+SUMIFS('Payroll Register'!M$4:M$23,'Payroll Register'!A$4:A$23,A17) -> 34692.306 | F17: =SUMIFS('Prior YTD (Jan-May)'!F$4:F$23,'Prior YTD (Jan-May)'!A$4:A$23,A17)+SUMIFS('Payroll Register'!N$4:N$23,'Payroll Register'!A$4:A$23,A17) -> 5061.2654 | G17: =SUMIFS('Prior YTD (Jan-May)'!G$4:G$23,'Prior YTD (Jan-May)'!A$4:A$23,A17)+SUMIFS('Payroll Register'!O$4:O$23,'Payroll Register'!A$4:A$23,A17) -> 2150.92 | H17: =SUMIFS('Prior YTD (Jan-May)'!H$4:H$23,'Prior YTD (Jan-May)'!A$4:A$23,A17)+SUMIFS('Payroll Register'!P$4:P$23,'Payroll Register'!A$4:A$23,A17) -> 503.04 | I17: =SUMIFS('Prior YTD (Jan-May)'!I$4:I$23,'Prior YTD (Jan-May)'!A$4:A$23,A17)+SUMIFS('Payroll Register'!Q$4:Q$23,'Payroll Register'!A$4:A$23,A17) -> 1904.61 | J17: =SUM(F17:I17) -> 9619.8354 | K17: =SUMIFS('Prior YTD (Jan-May)'!K$4:K$23,'Prior YTD (Jan-May)'!A$4:A$23,A17)+SUMIFS('Payroll Register'!S$4:S$23,'Payroll Register'!A$4:A$23,A17) -> 359.61231 | L17: =SUMIFS('Prior YTD (Jan-May)'!L$4:L$23,'Prior YTD (Jan-May)'!A$4:A$23,A17)+SUMIFS('Payroll Register'!T$4:T$23,'Payroll Register'!A$4:A$23,A17) -> 19.040769 | M17: =SUMIFS('Prior YTD (Jan-May)'!M$4:M$23,'Prior YTD (Jan-May)'!A$4:A$23,A17)+SUMIFS('Payroll Register'!U$4:U$23,'Payroll Register'!A$4:A$23,A17) -> 6.3469231 | N17: =SUMIFS('Prior YTD (Jan-May)'!N$4:N$23,'Prior YTD (Jan-May)'!A$4:A$23,A17)+SUMIFS('Payroll Register'!V$4:V$23,'Payroll Register'!A$4:A$23,A17) -> 2081.54 | O17: =SUM(K17:N17) -> 2466.54 | P17: =E17-J17-O17 -> 22605.931 | Q17: =IFERROR(ROUND(J17/E17,4),0) -> 0.2773 | R17: =IFERROR(ROUND(N17/E17,4),0) -> 0.06 | S17: =MAX(0,176100-E17) -> 141407.69 | T17: =IF(E17>=176100,"BASE REACHED — STOP SS",IF(E17>=149685,"WARNING: >85% Used",IF(E17>=114465,"MONITOR: >65% Used","Within Safe Limit"))) -> Within Safe Limit | U17: =ROUND(E17/11*26,2) -> 82000 | V17: =26-11 -> 15
... A25: E-1020 | B25: =IFERROR(INDEX('Employee Master'!B$4:B$23,MATCH(A25,'Employee Master'!A$4:A$23,0)),"") -> Martinez | C25: =IFERROR(INDEX('Employee Master'!C$4:C$23,MATCH(A25,'Employee Master'!A$4:A$23,0)),"") -> Sofia | D25: =IFERROR(INDEX('Employee Master'!E$4:E$23,MATCH(A25,'Employee Master'!A$4:A$23,0)),"") -> Marketing | E25: =SUMIFS('Prior YTD (Jan-May)'!E$4:E$23,'Prior YTD (Jan-May)'!A$4:A$23,A25)+SUMIFS('Payroll Register'!M$4:M$23,'Payroll Register'!A$4:A$23,A25) -> 24538.459 | F25: =SUMIFS('Prior YTD (Jan-May)'!F$4:F$23,'Prior YTD (Jan-May)'!A$4:A$23,A25)+SUMIFS('Payroll Register'!N$4:N$23,'Payroll Register'!A$4:A$23,A25) -> 4124.5715 | G25: =SUMIFS('Prior YTD (Jan-May)'!G$4:G$23,'Prior YTD (Jan-May)'!A$4:A$23,A25)+SUMIFS('Payroll Register'!O$4:O$23,'Payroll Register'!A$4:A$23,A25) -> 1521.39 | H25: =SUMIFS('Prior YTD (Jan-May)'!H$4:H$23,'Prior YTD (Jan-May)'!A$4:A$23,A25)+SUMIFS('Payroll Register'!P$4:P$23,'Payroll Register'!A$4:A$23,A25) -> 355.81 | I25: =SUMIFS('Prior YTD (Jan-May)'!I$4:I$23,'Prior YTD (Jan-May)'!A$4:A$23,A25)+SUMIFS('Payroll Register'!Q$4:Q$23,'Payroll Register'!A$4:A$23,A25) -> 1347.16 | J25: =SUM(F25:I25) -> 7348.9315 | K25: =SUMIFS('Prior YTD (Jan-May)'!K$4:K$23,'Prior YTD (Jan-May)'!A$4:A$23,A25)+SUMIFS('Payroll Register'!S$4:S$23,'Payroll Register'!A$4:A$23,A25) -> 124.80615 | L25: =SUMIFS('Prior YTD (Jan-May)'!L$4:L$23,'Prior YTD (Jan-May)'!A$4:A$23,A25)+SUMIFS('Payroll Register'!T$4:T$23,'Payroll Register'!A$4:A$23,A25) -> 19.040769 | M25: =SUMIFS('Prior YTD (Jan-May)'!M$4:M$23,'Prior YTD (Jan-May)'!A$4:A$23,A25)+SUMIFS('Payroll Register'!U$4:U$23,'Payroll Register'!A$4:A$23,A25) -> 6.3469231 | N25: =SUMIFS('Prior YTD (Jan-May)'!N$4:N$23,'Prior YTD (Jan-May)'!A$4:A$23,A25)+SUMIFS('Payroll Register'!V$4:V$23,'Payroll Register'!A$4:A$23,A25) -> 981.54 | O25: =SUM(K25:N25) -> 1131.7338 | P25: =E25-J25-O25 -> 16057.794 | Q25: =IFERROR(ROUND(J25/E25,4),0) -> 0.2995 | R25: =IFERROR(ROUND(N25/E25,4),0) -> 0.04 | S25: =MAX(0,176100-E25) -> 151561.54 | T25: =IF(E25>=176100,"BASE REACHED — STOP SS",IF(E25>=149685,"WARNING: >85% Used",IF(E25>=114465,"MONITOR: >65% Used","Within Safe Limit"))) -> Within Safe Limit | U25: =ROUND(E25/11*26,2) -> 57999.99 | V25: =26-11 -> 15
A26: COMPANY TOTALS — YTD JAN 1 TO JUN 14, 2026 | E26: =SUM(E6:E25) -> 672533.15 | F26: =SUM(F6:F25) -> 113275.36 | G26: =SUM(G6:G25) -> 41697.07 | H26: =SUM(H6:H25) -> 9751.75 | I26: =SUM(I6:I25) -> 36922.07 | J26: =SUM(J6:J25) -> 201646.25 | K26: =SUM(K6:K25) -> 4835.7354 | L26: =SUM(L6:L25) -> 380.81538 | ... P26: =SUM(P6:P25) -> 426561.61 | Q26: =IFERROR(ROUND(AVERAGE(Q6:Q25),4),0) -> 0.2969 | R26: =IFERROR(ROUND(AVERAGE(R6:R25),4),0) -> 0.0485 | S26: =MAX(0,3522000-SUM(E6:E25)) -> 2849466.9 | U26: =SUM(U6:U25) -> 1589623.8 | V26: =26-11 -> 15
A28: FORMULA KEY — Every formula type used in this sheet and what it does
B29: INDEX-MATCH | D29: Columns B, C, D | E29: Pulls employee Last Name, First Name, and Department from Employee Master by matching Emp ID. Works even if the Employee Master columns are rearranged. Wrapped in IFERROR so missing IDs return blank instead of an error.
B30: SUMIFS | D30: Columns E–I, K–N | E30: Sums each payroll figure (gross, federal tax, SS, Medicare, GA tax, health, dental, vision, 401k) by matching Employee ID across both the Prior YTD sheet (10 periods) and the current Payroll Register. This is the core of accurate YTD — real history, not a multiplication.
B31: SUM | D31: Columns J, O, P | E31: Column J: sums Federal + SS + Medicare + GA tax to give total tax withheld. Column O: sums all four benefit deductions. Column P: Gross minus Total Tax minus Total Deductions = Net Pay. These aggregate the SUMIFS results into summary figures.
B32: ROUND | D32: Columns Q, R | E32: Column Q: ROUND(Total Tax / Gross, 4) = effective tax rate as a percentage. Column R: ROUND(YTD 401k / Gross, 4) = actual 401k contribution rate. ROUND ensures clean percentages — prevents 15.999999% displaying instead of 16.00%.
B33: MAX | D33: Column S | E33: MAX(0, 176100 - YTD Gross) = how much Social Security wage capacity each employee has remaining. MAX(0, ...) ensures the result never goes negative for employees who have already crossed the base. Critical for payroll compliance — SS withholding must stop at $176,100.
B34: Nested IF | D34: Column T | E34: Three-level IF checks YTD Gross against SS wage base thresholds: IF >= $176,100 → BASE REACHED — STOP SS (red highlight), IF >= $149,685 (85%) → WARNING: monitor closely (orange), IF >= $114,465 (65%) → MONITOR: approaching. Gives payroll staff an automated early-warning system for SS compliance.
B35: Arithmetic | D35: Columns U, V | E35: Column U: ROUND(YTD Gross / 11 * 26, 2) = projected full-year gross at current run rate. Useful for year-end bonus planning and W-2 estimation. Column V: 26 - 11 = 15 pay periods remaining in 2026. Simple arithmetic, but explicitly shown so every calculation in the sheet is visible and verifiable.
A38: Muhammad Zeenat Ullah | CA Finalist (ICAP) | QBO ProAdvisor | Excel Expert | zeenatullah.bookkeeper@gmail.com | WhatsApp: +44 7577 845321
A39: Portfolio Sample — All company names, employee names, and figures are entirely fictitious. Created to demonstrate advanced Excel payroll formula expertise.

Sheet Employee Master
A1: SUMMIT HR SOLUTIONS | EMPLOYEE MASTER DATABASE
A2: Atlanta, GA · Pay Period: June 1–14, 2026 · Bi-Weekly (26 pay periods/year) · Currency: USD
A3: Emp ID | B3: Last Name | C3: First Name | D3: SSN (Last 4) | E3: Department | F3: Job Title | G3: Pay Type | H3: Hire Date | I3: Annual Salary | J3: Hourly Rate | K3: Status | L3: Fed Filing Status | M3: Allowances | N3: GA Tax Rate | O3: Health Ins ($) | P3: Dental ($) | Q3: Vision ($) | R3: 401(k) % | S3: Life Ins ($) | T3: Direct Deposit
A4: E-1001 | B4: Anderson | C4: Michael | D4: 4521 | E4: Human Resources | F4: HR Director | G4: Salary | H4: 01/15/2018 | I4: 115000 | K4: Active | L4: MFJ | M4: 2 | N4: 0.0549 | O4: 850 | P4: 45 | Q4: 15 | R4: 0.06 | T4: Yes
A5: E-1002 | B5: Johnson | C5: Sarah | D5: 8834 | E5: Human Resources | F5: HR Business Partner | G5: Salary | H5: 03/20/2019 | I5: 78000 | K5: Active | L5: Single | M5: 1 | N5: 0.0549 | O5: 550 | P5: 45 | Q5: 15 | R5: 0.04 | S5: 25 | T5: Yes
A6: E-1003 | B6: Williams | C6: David | D6: 2277 | E6: Finance | F6: Controller | G6: Salary | H6: 07/08/2017 | I6: 125000 | K6: Active | L6: MFJ | M6: 3 | N6: 0.0549 | O6: 850 | P6: 45 | Q6: 15 | R6: 0.08 | S6: 25 | T6: Yes
A7: E-1004 | B7: Brown | C7: Jessica | D7: 6690 | E7: Finance | F7: Senior Accountant | G7: Salary | H7: 11/01/2020 | I7: 72000 | K7: Active | L7: Single | M7: 1 | N7: 0.0549 | O7: 550 | P7: 45 | Q7: 15 | R7: 0.05 | S7: 25 | T7: Yes
A8: E-1005 | B8: Davis | C8: Robert | D8: 3315 | E8: Finance | F8: Staff Accountant | G8: Salary | H8: 05/14/2022 | I8: 55000 | K8: Active | L8: Single | M8: 0 | N8: 0.0549 | O8: 295 | P8: 45 | Q8: 15 | R8: 0.03 | S8: 25 | T8: Yes
A9: E-1006 | B9: Martinez | C9: Elena | D9: 9930 | E9: Operations | F9: Operations Manager | G9: Salary | H9: 09/30/2016 | I9: 95000 | K9: Active | L9: MFJ | M9: 2 | N9: 0.0549 | O9: 850 | P9: 45 | Q9: 15 | R9: 0.07 | S9: 25 | T9: Yes
A10: E-1007 | B10: Garcia | C10: Carlos | D10: 9901 | E10: Operations | F10: Production Supervisor | G10: Salary | H10: 02/18/2021 | I10: 65000 | K10: Active | L10: HOH | M10: 3 | N10: 0.0549 | O10: 620 | P10: 45 | Q10: 15 | R10: 0.05 | S10: 25 | T10: Yes
A11: E-1008 | B11: Miller | C11: Amanda | D11: 4433 | E11: Operations | F11: Operations Analyst | G11: Salary | H11: 08/22/2023 | I11: 52000 | K11: Active | L11: Single | M11: 1 | N11: 0.0549 | O11: 295 | P11: 45 | Q11: 0 | R11: 0.03 | S11: 25 | T11: Yes
A12: E-1009 | B12: Wilson | C12: James | D12: 5566 | E12: Operations | F12: Warehouse Lead | G12: Hourly | H12: 04/03/2019 | J12: 24.5 | K12: Active | L12: Single | M12: 1 | N12: 0.0549 | O12: 295 | P12: 45 | Q12: 15 | R12: 0.03 | S12: 25 | T12: Yes
A13: E-1010 | B13: Moore | C13: Patricia | D13: 8821 | E13: Operations | F13: Shipping Coordinator | G13: Hourly | H13: 10/11/2020 | J13: 19.75 | K13: Active | L13: Single | M13: 0 | N13: 0.0549 | O13: 295 | P13: 45 | Q13: 0 | R13: 0 | S13: 25 | T13: Yes
A14: E-1011 | B14: Taylor | C14: Kevin | D14: 3344 | E14: Information Technology | F14: IT Manager | G14: Salary | H14: 06/05/2015 | I14: 105000 | K14: Active | L14: MFJ | M14: 2 | N14: 0.0549 | O14: 850 | P14: 45 | Q14: 15 | R14: 0.08 | S14: 25 | T14: Yes
A15: E-1012 | B15: Anderson | C15: Lisa | D15: 7788 | E15: Information Technology | F15: Systems Analyst | G15: Salary | H15: 01/09/2021 | I15: 82000 | K15: Active | L15: MFJ | M15: 2 | N15: 0.0549 | O15: 850 | P15: 45 | Q15: 15 | R15: 0.06 | S15: 25 | T15: Yes
A16: E-1013 | B16: Thomas | C16: Brian | D16: 2255 | E16: Information Technology | F16: Network Engineer | G16: Salary | H16: 03/14/2022 | I16: 88000 | K16: Active | L16: Single | M16: 1 | N16: 0.0549 | O16: 550 | P16: 45 | Q16: 15 | R16: 0.06 | S16: 25 | T16: Yes
A17: E-1014 | B17: Jackson | C17: Nicole | D17: 6677 | E17: Information Technology | F17: Help Desk Spec. | G17: Hourly | H17: 07/20/2023 | J17: 21 | K17: Active | L17: Single | M17: 1 | N17: 0.0549 | O17: 295 | P17: 45 | Q17: 0 | R17: 0.02 | S17: 25 | T17: Yes
A18: E-1015 | B18: White | C18: Christopher | D18: 9988 | E18: Sales | F18: VP of Sales | G18: Salary | H18: 05/28/2014 | I18: 138000 | K18: Active | L18: MFJ | M18: 4 | N18: 0.0549 | O18: 850 | P18: 45 | Q18: 15 | R18: 0.1 | S18: 25 | T18: Yes
A19: E-1016 | B19: Harris | C19: Megan | D19: 1123 | E19: Sales | F19: Senior Account Exec | G19: Salary | H19: 02/14/2019 | I19: 74000 | K19: Active | L19: MFJ | M19: 2 | N19: 0.0549 | O19: 850 | P19: 45 | Q19: 15 | R19: 0.05 | S19: 25 | T19: Yes
A20: E-1017 | B20: Martin | C20: Tyler | D20: 4456 | E20: Sales | F20: Account Executive | G20: Salary | H20: 09/08/2021 | I20: 62000 | K20: Active | L20: Single | M20: 1 | N20: 0.0549 | O20: 295 | P20: 45 | Q20: 15 | R20: 0.04 | S20: 25 | T20: Yes
A21: E-1018 | B21: Thompson | C21: Ashley | D21: 7723 | E21: Sales | F21: Sales Coordinator | G21: Hourly | H21: 06/16/2022 | J21: 18.5 | K21: Active | L21: Single | M21: 0 | N21: 0.0549 | O21: 295 | P21: 45 | Q21: 0 | R21: 0 | S21: 25 | T21: Yes
A22: E-1019 | B22: Garcia | C22: Marcus | D22: 3312 | E22: Marketing | F22: Marketing Director | G22: Salary | H22: 11/03/2017 | I22: 108000 | K22: Active | L22: MFJ | M22: 2 | N22: 0.0549 | O22: 850 | P22: 45 | Q22: 15 | R22: 0.08 | S22: 25 | T22: Yes
A23: E-1020 | B23: Martinez | C23: Sofia | D23: 8894 | E23: Marketing | F23: Digital Mktg Specialist | G23: Salary | H23: 04/25/2023 | I23: 58000 | K23: Active | L23: Single | M23: 1 | N23: 0.0549 | O23: 295 | P23: 45 | Q23: 15 | R23: 0.04 | S23: 25 | T23: Yes
A25: Prepared by: Muhammad Zeenat Ullah | CA Finalist (ICAP) · QBO ProAdvisor · Excel Expert | zeenatullah.bookkeeper@gmail.com | WA: +44 7577 845321
A26: Portfolio Sample — All employee names, SSNs, and company data are entirely fictitious and created solely to demonstrate financial formula expertise.

Sheet Payroll Register
A1: PAYROLL REGISTER | Summit HR Solutions | Pay Period: June 1–14, 2026 | Check Date: June 19, 2026
A2: IRS Pub 15-T 2024 Percentage Method · SS Wage Base $176,100 · GA Flat 5.49% · Medicare 1.45% · FICA 6.2%
A3: Emp ID | B3: Last Name | C3: First Name | D3: Department | E3: Pay Type | F3: Reg Hrs | G3: OT Hrs | H3: Holiday Hrs | I3: Base Pay | J3: OT Premium | K3: Holiday Pay | L3: Bonus / Comm | M3: GROSS TOTAL | N3: Federal W/H | O3: Soc Sec (6.2%) | P3: Medicare (1.45%) | Q3: GA State (5.49%) | R3: TOTAL TAX W/H | S3: Health Ins | T3: Dental | U3: Vision | V3: 401(k) | W3: Life Ins | X3: TOTAL DEDUCTIONS | Y3: NET PAY
A4: E-1001 | B4: =INDEX('Employee Master'!B$4:B$23,MATCH(A4,'Employee Master'!A$4:A$23,0)) -> Anderson | C4: =INDEX('Employee Master'!C$4:C$23,MATCH(A4,'Employee Master'!A$4:A$23,0)) -> Michael | D4: =INDEX('Employee Master'!E$4:E$23,MATCH(A4,'Employee Master'!A$4:A$23,0)) -> Human Resources | E4: =INDEX('Employee Master'!G$4:G$23,MATCH(A4,'Employee Master'!A$4:A$23,0)) -> Salary | F4: 80 | G4: 0 | H4: 0 | I4: =IF(E4="Salary",INDEX('Employee Master'!I$4:I$23,MATCH(A4,'Employee Master'!A$4:A$23,0))/26,INDEX('Employee Master'!J$4:J$23,MATCH(A4,'Employee Master'!A$4:A$23,0))*F4) -> 4423.0769 | J4: =IF(E4="Hourly",INDEX('Employee Master'!J$4:J$23,MATCH(A4,'Employee Master'!A$4:A$23,0))*G4*0.5,0) -> 0 | K4: =IF(E4="Hourly",INDEX('Employee Master'!J$4:J$23,MATCH(A4,'Employee Master'!A$4:A$23,0))*H4,0) -> 0 | L4: 0 | M4: =SUM(I4:L4) -> 4423.0769 | N4: =IFERROR(IF(INDEX('Employee Master'!L$4:L$23,MATCH(A4,'Employee Master'!A$4:A$23,0))="MFJ",IF((M4*26)<=14600,(M4*26)*0.1,IF((M4*26)<=57750,1460+((M4*26)-14600)*0.12,IF((M4*26)<=113600,6628+((M4*26)-57750)*0.22,IF((M4*26)<=225600,18914+((M4*26)-113600)*0.24,IF((M4*26)<=537550,45794+((M4*26)-225600)*0.32,IF((M4*26)<=643450,145538+((M4*26)-537550)*0.35,182648+((M4*26)-643450)*0.37))))))/26,IF((M4*26)<=7300,(M4*26)*0.1,IF((M4*26)<=28875,730+((M4*26)-7300)*0.12,IF((M4*26)<=56875,3319+((M4*26)-28875)*0.22,IF((M4*26)<=112875,9479+((M4*26)-56875)*0.24,IF((M4*26)<=268850,23009+((M4*26)-112875)*0.32,IF((M4*26)<=321800,72937+((M4*26)-268850)*0.35,91487+((M4*26)-321800)*0.37))))))/26),0) -> 740.38462 | O4: =ROUND(M4*0.062,2) -> 274.23 | P4: =ROUND(M4*0.0145,2) -> 64.13 | Q4: =ROUND(M4*INDEX('Employee Master'!N$4:N$23,MATCH(A4,'Employee Master'!A$4:A$23,0)),2) -> 242.83 | R4: =SUM(N4:Q4) -> 1321.5746 | S4: =IFERROR(INDEX('Employee Master'!O$4:O$23,MATCH(A4,'Employee Master'!A$4:A$23,0))/26,0) -> 32.692308 | T4: =IFERROR(INDEX('Employee Master'!P$4:P$23,MATCH(A4,'Employee Master'!A$4:A$23,0))/26,0) -> 1.7307692 | U4: =IFERROR(INDEX('Employee Master'!Q$4:Q$23,MATCH(A4,'Employee Master'!A$4:A$23,0))/26,0) -> 0.57692308 | V4: =ROUND(M4*IFERROR(INDEX('Employee Master'!R$4:R$23,MATCH(A4,'Employee Master'!A$4:A$23,0)),0),2) -> 265.38 | W4: =IFERROR(INDEX('Employee Master'!S$4:S$23,MATCH(A4,'Employee Master'!A$4:A$23,0))/26,0) -> 0 | X4: =SUM(S4:W4) -> 300.38 | Y4: =M4-R4-X4 -> 2801.1223
A5: E-1002 | B5: =INDEX('Employee Master'!B$4:B$23,MATCH(A5,'Employee Master'!A$4:A$23,0)) -> Johnson | C5: =INDEX('Employee Master'!C$4:C$23,MATCH(A5,'Employee Master'!A$4:A$23,0)) -> Sarah | D5: =INDEX('Employee Master'!E$4:E$23,MATCH(A5,'Employee Master'!A$4:A$23,0)) -> Human Resources | E5: =INDEX('Employee Master'!G$4:G$23,MATCH(A5,'Employee Master'!A$4:A$23,0)) -> Salary | F5: 80 | G5: 0 | H5: 0 | I5: =IF(E5="Salary",INDEX('Employee Master'!I$4:I$23,MATCH(A5,'Employee Master'!A$4:A$23,0))/26,INDEX('Employee Master'!J$4:J$23,MATCH(A5,'Employee Master'!A$4:A$23,0))*F5) -> 3000 | J5: =IF(E5="Hourly",INDEX('Employee Master'!J$4:J$23,MATCH(A5,'Employee Master'!A$4:A$23,0))*G5*0.5,0) -> 0 | K5: =IF(E5="Hourly",INDEX('Employee Master'!J$4:J$23,MATCH(A5,'Employee Master'!A$4:A$23,0))*H5,0) -> 0 | L5: 0 | M5: =SUM(I5:L5) -> 3000 | N5: =IFERROR(IF(INDEX('Employee Master'!L$4:L$23,MATCH(A5,'Employee Master'!A$4:A$23,0))="MFJ",IF((M5*26)<=14600,(M5*26)*0.1,IF((M5*26)<=57750,1460+((M5*26)-14600)*0.12,IF((M5*26)<=113600,6628+((M5*26)-57750)*0.22,IF((M5*26)<=225600,18914+((M5*26)-113600)*0.24,IF((M5*26)<=537550,45794+((M5*26)-225600)*0.32,IF((M5*26)<=643450,145538+((M5*26)-537550)*0.35,182648+((M5*26)-643450)*0.37))))))/26,IF((M5*26)<=7300,(M5*26)*0.1,IF((M5*26)<=28875,730+((M5*26)-7300)*0.12,IF((M5*26)<=56875,3319+((M5*26)-28875)*0.22,IF((M5*26)<=112875,9479+((M5*26)-56875)*0.24,IF((M5*26)<=268850,23009+((M5*26)-112875)*0.32,IF((M5*26)<=321800,72937+((M5*26)-268850)*0.35,91487+((M5*26)-321800)*0.37))))))/26),0) -> 559.57692 | O5: =ROUND(M5*0.062,2) -> 186 | P5: =ROUND(M5*0.0145,2) -> 43.5 | Q5: =ROUND(M5*INDEX('Employee Master'!N$4:N$23,MATCH(A5,'Employee Master'!A$4:A$23,0)),2) -> 164.7 | R5: =SUM(N5:Q5) -> 953.77692 | S5: =IFERROR(INDEX('Employee Master'!O$4:O$23,MATCH(A5,'Employee Master'!A$4:A$23,0))/26,0) -> 21.153846 | T5: =IFERROR(INDEX('Employee Master'!P$4:P$23,MATCH(A5,'Employee Master'!A$4:A$23,0))/26,0) -> 1.7307692 | U5: =IFERROR(INDEX('Employee Master'!Q$4:Q$23,MATCH(A5,'Employee Master'!A$4:A$23,0))/26,0) -> 0.57692308 | V5: =ROUND(M5*IFERROR(INDEX('Employee Master'!R$4:R$23,MATCH(A5,'Employee Master'!A$4:A$23,0)),0),2) -> 120 | W5: =IFERROR(INDEX('Employee Master'!S$4:S$23,MATCH(A5,'Employee Master'!A$4:A$23,0))/26,0) -> 0.96153846 | X5: =SUM(S5:W5) -> 144.42308 | Y5: =M5-R5-X5 -> 1901.8
A6: E-1003 | B6: =INDEX('Employee Master'!B$4:B$23,MATCH(A6,'Employee Master'!A$4:A$23,0)) -> Williams | C6: =INDEX('Employee Master'!C$4:C$23,MATCH(A6,'Employee Master'!A$4:A$23,0)) -> David | D6: =INDEX('Employee Master'!E$4:E$23,MATCH(A6,'Employee Master'!A$4:A$23,0)) -> Finance | E6: =INDEX('Employee Master'!G$4:G$23,MATCH(A6,'Employee Master'!A$4:A$23,0)) -> Salary | F6: 80 | G6: 0 | H6: 0 | I6: =IF(E6="Salary",INDEX('Employee Master'!I$4:I$23,MATCH(A6,'Employee Master'!A$4:A$23,0))/26,INDEX('Employee Master'!J$4:J$23,MATCH(A6,'Employee Master'!A$4:A$23,0))*F6) -> 4807.6923 | J6: =IF(E6="Hourly",INDEX('Employee Master'!J$4:J$23,MATCH(A6,'Employee Master'!A$4:A$23,0))*G6*0.5,0) -> 0 | K6: =IF(E6="Hourly",INDEX('Employee Master'!J$4:J$23,MATCH(A6,'Employee Master'!A$4:A$23,0))*H6,0) -> 0 | L6: 0 | M6: =SUM(I6:L6) -> 4807.6923 | N6: =IFERROR(IF(INDEX('Employee Master'!L$4:L$23,MATCH(A6,'Employee Master'!A$4:A$23,0))="MFJ",IF((M6*26)<=14600,(M6*26)*0.1,IF((M6*26)<=57750,1460+((M6*26)-14600)*0.12,IF((M6*26)<=113600,6628+((M6*26)-57750)*0.22,IF((M6*26)<=225600,18914+((M6*26)-113600)*0.24,IF((M6*26)<=537550,45794+((M6*26)-225600)*0.32,IF((M6*26)<=643450,145538+((M6*26)-537550)*0.35,182648+((M6*26)-643450)*0.37))))))/26,IF((M6*26)<=7300,(M6*26)*0.1,IF((M6*26)<=28875,730+((M6*26)-7300)*0.12,IF((M6*26)<=56875,3319+((M6*26)-28875)*0.22,IF((M6*26)<=112875,9479+((M6*26)-56875)*0.24,IF((M6*26)<=268850,23009+((M6*26)-112875)*0.32,IF((M6*26)<=321800,72937+((M6*26)-268850)*0.35,91487+((M6*26)-321800)*0.37))))))/26),0) -> 832.69231 | O6: =ROUND(M6*0.062,2) -> 298.08 | P6: =ROUND(M6*0.0145,2) -> 69.71 | Q6: =ROUND(M6*INDEX('Employee Master'!N$4:N$23,MATCH(A6,'Employee Master'!A$4:A$23,0)),2) -> 263.94 | R6: =SUM(N6:Q6) -> 1464.4223 | S6: =IFERROR(INDEX('Employee Master'!O$4:O$23,MATCH(A6,'Employee Master'!A$4:A$23,0))/26,0) -> 32.692308 | T6: =IFERROR(INDEX('Employee Master'!P$4:P$23,MATCH(A6,'Employee Master'!A$4:A$23,0))/26,0) -> 1.7307692 | U6: =IFERROR(INDEX('Employee Master'!Q$4:Q$23,MATCH(A6,'Employee Master'!A$4:A$23,0))/26,0) -> 0.57692308 | V6: =ROUND(M6*IFERROR(INDEX('Employee Master'!R$4:R$23,MATCH(A6,'Employee Master'!A$4:A$23,0)),0),2) -> 384.62 | W6: =IFERROR(INDEX('Employee Master'!S$4:S$23,MATCH(A6,'Employee Master'!A$4:A$23,0))/26,0) -> 0.96153846 | X6: =SUM(S6:W6) -> 420.58154 | Y6: =M6-R6-X6 -> 2922.6885
A7: E-1004 | B7: =INDEX('Employee Master'!B$4:B$23,MATCH(A7,'Employee Master'!A$4:A$23,0)) -> Brown | C7: =INDEX('Employee Master'!C$4:C$23,MATCH(A7,'Employee Master'!A$4:A$23,0)) -> Jessica | D7: =INDEX('Employee Master'!E$4:E$23,MATCH(A7,'Employee Master'!A$4:A$23,0)) -> Finance | E7: =INDEX('Employee Master'!G$4:G$23,MATCH(A7,'Employee Master'!A$4:A$23,0)) -> Salary | F7: 80 | G7: 2.5 | H7: 0 | I7: =IF(E7="Salary",INDEX('Employee Master'!I$4:I$23,MATCH(A7,'Employee Master'!A$4:A$23,0))/26,INDEX('Employee Master'!J$4:J$23,MATCH(A7,'Employee Master'!A$4:A$23,0))*F7) -> 2769.2308 | J7: =IF(E7="Hourly",INDEX('Employee Master'!J$4:J$23,MATCH(A7,'Employee Master'!A$4:A$23,0))*G7*0.5,0) -> 0 | K7: =IF(E7="Hourly",INDEX('Employee Master'!J$4:J$23,MATCH(A7,'Employee Master'!A$4:A$23,0))*H7,0) -> 0 | L7: 0 | M7: =SUM(I7:L7) -> 2769.2308 | N7: =IFERROR(IF(INDEX('Employee Master'!L$4:L$23,MATCH(A7,'Employee Master'!A$4:A$23,0))="MFJ",IF((M7*26)<=14600,(M7*26)*0.1,IF((M7*26)<=57750,1460+((M7*26)-14600)*0.12,IF((M7*26)<=113600,6628+((M7*26)-57750)*0.22,IF((M7*26)<=225600,18914+((M7*26)-113600)*0.24,IF((M7*26)<=537550,45794+((M7*26)-225600)*0.32,IF((M7*26)<=643450,145538+((M7*26)-537550)*0.35,182648+((M7*26)-643450)*0.37))))))/26,IF((M7*26)<=7300,(M7*26)*0.1,IF((M7*26)<=28875,730+((M7*26)-7300)*0.12,IF((M7*26)<=56875,3319+((M7*26)-28875)*0.22,IF((M7*26)<=112875,9479+((M7*26)-56875)*0.24,IF((M7*26)<=268850,23009+((M7*26)-112875)*0.32,IF((M7*26)<=321800,72937+((M7*26)-268850)*0.35,91487+((M7*26)-321800)*0.37))))))/26),0) -> 504.19231 | O7: =ROUND(M7*0.062,2) -> 171.69 | P7: =ROUND(M7*0.0145,2) -> 40.15 | Q7: =ROUND(M7*INDEX('Employee Master'!N$4:N$23,MATCH(A7,'Employee Master'!A$4:A$23,0)),2) -> 152.03 | R7: =SUM(N7:Q7) -> 868.06231 | S7: =IFERROR(INDEX('Employee Master'!O$4:O$23,MATCH(A7,'Employee Master'!A$4:A$23,0))/26,0) -> 21.153846 | T7: =IFERROR(INDEX('Employee Master'!P$4:P$23,MATCH(A7,'Employee Master'!A$4:A$23,0))/26,0) -> 1.7307692 | U7: =IFERROR(INDEX('Employee Master'!Q$4:Q$23,MATCH(A7,'Employee Master'!A$4:A$23,0))/26,0) -> 0.57692308 | V7: =ROUND(M7*IFERROR(INDEX('Employee Master'!R$4:R$23,MATCH(A7,'Employee Master'!A$4:A$23,0)),0),2) -> 138.46 | W7: =IFERROR(INDEX('Employee Master'!S$4:S$23,MATCH(A7,'Employee Master'!A$4:A$23,0))/26,0) -> 0.96153846 | X7: =SUM(S7:W7) -> 162.88308 | Y7: =M7-R7-X7 -> 1738.2854
A8: E-1005 | B8: =INDEX('Employee Master'!B$4:B$23,MATCH(A8,'Employee Master'!A$4:A$23,0)) -> Davis | C8: =INDEX('Employee Master'!C$4:C$23,MATCH(A8,'Employee Master'!A$4:A$23,0)) -> Robert | D8: =INDEX('Employee Master'!E$4:E$23,MATCH(A8,'Employee Master'!A$4:A$23,0)) -> Finance | E8: =INDEX('Employee Master'!G$4:G$23,MATCH(A8,'Employee Master'!A$4:A$23,0)) -> Salary | F8: 80 | G8: 0 | H8: 0 | I8: =IF(E8="Salary",INDEX('Employee Master'!I$4:I$23,MATCH(A8,'Employee Master'!A$4:A$23,0))/26,INDEX('Employee Master'!J$4:J$23,MATCH(A8,'Employee Master'!A$4:A$23,0))*F8) -> 2115.3846 | J8: =IF(E8="Hourly",INDEX('Employee Master'!J$4:J$23,MATCH(A8,'Employee Master'!A$4:A$23,0))*G8*0.5,0) -> 0 | K8: =IF(E8="Hourly",INDEX('Employee Master'!J$4:J$23,MATCH(A8,'Employee Master'!A$4:A$23,0))*H8,0) -> 0 | L8: 0 | M8: =SUM(I8:L8) -> 2115.3846 | N8: =IFERROR(IF(INDEX('Employee Master'!L$4:L$23,MATCH(A8,'Employee Master'!A$4:A$23,0))="MFJ",IF((M8*26)<=14600,(M8*26)*0.1,IF((M8*26)<=57750,1460+((M8*26)-14600)*0.12,IF((M8*26)<=113600,6628+((M8*26)-57750)*0.22,IF((M8*26)<=225600,18914+((M8*26)-113600)*0.24,IF((M8*26)<=537550,45794+((M8*26)-225600)*0.32,IF((M8*26)<=643450,145538+((M8*26)-537550)*0.35,182648+((M8*26)-643450)*0.37))))))/26,IF((M8*26)<=7300,(M8*26)*0.1,IF((M8*26)<=28875,730+((M8*26)-7300)*0.12,IF((M8*26)<=56875,3319+((M8*26)-28875)*0.22,IF((M8*26)<=112875,9479+((M8*26)-56875)*0.24,IF((M8*26)<=268850,23009+((M8*26)-112875)*0.32,IF((M8*26)<=321800,72937+((M8*26)-268850)*0.35,91487+((M8*26)-321800)*0.37))))))/26),0) -> 348.71154 | O8: =ROUND(M8*0.062,2) -> 131.15 | P8: =ROUND(M8*0.0145,2) -> 30.67 | Q8: =ROUND(M8*INDEX('Employee Master'!N$4:N$23,MATCH(A8,'Employee Master'!A$4:A$23,0)),2) -> 116.13 | R8: =SUM(N8:Q8) -> 626.66154 | S8: =IFERROR(INDEX('Employee Master'!O$4:O$23,MATCH(A8,'Employee Master'!A$4:A$23,0))/26,0) -> 11.346154 | T8: =IFERROR(INDEX('Employee Master'!P$4:P$23,MATCH(A8,'Employee Master'!A$4:A$23,0))/26,0) -> 1.7307692 | U8: =IFERROR(INDEX('Employee Master'!Q$4:Q$23,MATCH(A8,'Employee Master'!A$4:A$23,0))/26,0) -> 0.57692308 | V8: =ROUND(M8*IFERROR(INDEX('Employee Master'!R$4:R$23,MATCH(A8,'Employee Master'!A$4:A$23,0)),0),2) -> 63.46 | W8: =IFERROR(INDEX('Employee Master'!S$4:S$23,MATCH(A8,'Employee Master'!A$4:A$23,0))/26,0) -> 0.96153846 | X8: =SUM(S8:W8) -> 78.075385 | Y8: =M8-R8-X8 -> 1410.6477
A9: E-1006 | B9: =INDEX('Employee Master'!B$4:B$23,MATCH(A9,'Employee Master'!A$4:A$23,0)) -> Martinez | C9: =INDEX('Employee Master'!C$4:C$23,MATCH(A9,'Employee Master'!A$4:A$23,0)) -> Elena | D9: =INDEX('Employee Master'!E$4:E$23,MATCH(A9,'Employee Master'!A$4:A$23,0)) -> Operations | E9: =INDEX('Employee Master'!G$4:G$23,MATCH(A9,'Employee Master'!A$4:A$23,0)) -> Salary | F9: 80 | G9: 0 | H9: 0 | I9: =IF(E9="Salary",INDEX('Employee Master'!I$4:I$23,MATCH(A9,'Employee Master'!A$4:A$23,0))/26,INDEX('Employee Master'!J$4:J$23,MATCH(A9,'Employee Master'!A$4:A$23,0))*F9) -> 3653.8462 | J9: =IF(E9="Hourly",INDEX('Employee Master'!J$4:J$23,MATCH(A9,'Employee Master'!A$4:A$23,0))*G9*0.5,0) -> 0 | K9: =IF(E9="Hourly",INDEX('Employee Master'!J$4:J$23,MATCH(A9,'Employee Master'!A$4:A$23,0))*H9,0) -> 0 | L9: 0 | M9: =SUM(I9:L9) -> 3653.8462 | N9: =IFERROR(IF(INDEX('Employee Master'!L$4:L$23,MATCH(A9,'Employee Master'!A$4:A$23,0))="MFJ",IF((M9*26)<=14600,(M9*26)*0.1,IF((M9*26)<=57750,1460+((M9*26)-14600)*0.12,IF((M9*26)<=113600,6628+((M9*26)-57750)*0.22,IF((M9*26)<=225600,18914+((M9*26)-113600)*0.24,IF((M9*26)<=537550,45794+((M9*26)-225600)*0.32,IF((M9*26)<=643450,145538+((M9*26)-537550)*0.35,182648+((M9*26)-643450)*0.37))))))/26,IF((M9*26)<=7300,(M9*26)*0.1,IF((M9*26)<=28875,730+((M9*26)-7300)*0.12,IF((M9*26)<=56875,3319+((M9*26)-28875)*0.22,IF((M9*26)<=112875,9479+((M9*26)-56875)*0.24,IF((M9*26)<=268850,23009+((M9*26)-112875)*0.32,IF((M9*26)<=321800,72937+((M9*26)-268850)*0.35,91487+((M9*26)-321800)*0.37))))))/26),0) -> 570.11538 | O9: =ROUND(M9*0.062,2) -> 226.54 | P9: =ROUND(M9*0.0145,2) -> 52.98 | Q9: =ROUND(M9*INDEX('Employee Master'!N$4:N$23,MATCH(A9,'Employee Master'!A$4:A$23,0)),2) -> 200.6 | R9: =SUM(N9:Q9) -> 1050.2354 | S9: =IFERROR(INDEX('Employee Master'!O$4:O$23,MATCH(A9,'Employee Master'!A$4:A$23,0))/26,0) -> 32.692308 | T9: =IFERROR(INDEX('Employee Master'!P$4:P$23,MATCH(A9,'Employee Master'!A$4:A$23,0))/26,0) -> 1.7307692 | U9: =IFERROR(INDEX('Employee Master'!Q$4:Q$23,MATCH(A9,'Employee Master'!A$4:A$23,0))/26,0) -> 0.57692308 | V9: =ROUND(M9*IFERROR(INDEX('Employee Master'!R$4:R$23,MATCH(A9,'Employee Master'!A$4:A$23,0)),0),2) -> 255.77 | W9: =IFERROR(INDEX('Employee Master'!S$4:S$23,MATCH(A9,'Employee Master'!A$4:A$23,0))/26,0) -> 0.96153846 | X9: =SUM(S9:W9) -> 291.73154 | Y9: =M9-R9-X9 -> 2311.8792
A10: E-1007 | B10: =INDEX('Employee Master'!B$4:B$23,MATCH(A10,'Employee Master'!A$4:A$23,0)) -> Garcia | C10: =INDEX('Employee Master'!C$4:C$23,MATCH(A10,'Employee Master'!A$4:A$23,0)) -> Carlos | D10: =INDEX('Employee Master'!E$4:E$23,MATCH(A10,'Employee Master'!A$4:A$23,0)) -> Operations | E10: =INDEX('Employee Master'!G$4:G$23,MATCH(A10,'Employee Master'!A$4:A$23,0)) -> Salary | F10: 80 | G10: 4 | H10: 0 | I10: =IF(E10="Salary",INDEX('Employee Master'!I$4:I$23,MATCH(A10,'Employee Master'!A$4:A$23,0))/26,INDEX('Employee Master'!J$4:J$23,MATCH(A10,'Employee Master'!A$4:A$23,0))*F10) -> 2500 | J10: =IF(E10="Hourly",INDEX('Employee Master'!J$4:J$23,MATCH(A10,'Employee Master'!A$4:A$23,0))*G10*0.5,0) -> 0 | K10: =IF(E10="Hourly",INDEX('Employee Master'!J$4:J$23,MATCH(A10,'Employee Master'!A$4:A$23,0))*H10,0) -> 0 | L10: 0 | M10: =SUM(I10:L10) -> 2500 | N10: =IFERROR(IF(INDEX('Employee Master'!L$4:L$23,MATCH(A10,'Employee Master'!A$4:A$23,0))="MFJ",IF((M10*26)<=14600,(M10*26)*0.1,IF((M10*26)<=57750,1460+((M10*26)-14600)*0.12,IF((M10*26)<=113600,6628+((M10*26)-57750)*0.22,IF((M10*26)<=225600,18914+((M10*26)-113600)*0.24,IF((M10*26)<=537550,45794+((M10*26)-225600)*0.32,IF((M10*26)<=643450,145538+((M10*26)-537550)*0.35,182648+((M10*26)-643450)*0.37))))))/26,IF((M10*26)<=7300,(M10*26)*0.1,IF((M10*26)<=28875,730+((M10*26)-7300)*0.12,IF((M10*26)<=56875,3319+((M10*26)-28875)*0.22,IF((M10*26)<=112875,9479+((M10*26)-56875)*0.24,IF((M10*26)<=268850,23009+((M10*26)-112875)*0.32,IF((M10*26)<=321800,72937+((M10*26)-268850)*0.35,91487+((M10*26)-321800)*0.37))))))/26),0) -> 439.57692 | O10: =ROUND(M10*0.062,2) -> 155 | P10: =ROUND(M10*0.0145,2) -> 36.25 | Q10: =ROUND(M10*INDEX('Employee Master'!N$4:N$23,MATCH(A10,'Employee Master'!A$4:A$23,0)),2) -> 137.25 | R10: =SUM(N10:Q10) -> 768.07692 | S10: =IFERROR(INDEX('Employee Master'!O$4:O$23,MATCH(A10,'Employee Master'!A$4:A$23,0))/26,0) -> 23.846154 | T10: =IFERROR(INDEX('Employee Master'!P$4:P$23,MATCH(A10,'Employee Master'!A$4:A$23,0))/26,0) -> 1.7307692 | U10: =IFERROR(INDEX('Employee Master'!Q$4:Q$23,MATCH(A10,'Employee Master'!A$4:A$23,0))/26,0) -> 0.57692308 | V10: =ROUND(M10*IFERROR(INDEX('Employee Master'!R$4:R$23,MATCH(A10,'Employee Master'!A$4:A$23,0)),0),2) -> 125 | W10: =IFERROR(INDEX('Employee Master'!S$4:S$23,MATCH(A10,'Employee Master'!A$4:A$23,0))/26,0) -> 0.96153846 | X10: =SUM(S10:W10) -> 152.11538 | Y10: =M10-R10-X10 -> 1579.8077
A11: E-1008 | B11: =INDEX('Employee Master'!B$4:B$23,MATCH(A11,'Employee Master'!A$4:A$23,0)) -> Miller | C11: =INDEX('Employee Master'!C$4:C$23,MATCH(A11,'Employee Master'!A$4:A$23,0)) -> Amanda | D11: =INDEX('Employee Master'!E$4:E$23,MATCH(A11,'Employee Master'!A$4:A$23,0)) -> Operations | E11: =INDEX('Employee Master'!G$4:G$23,MATCH(A11,'Employee Master'!A$4:A$23,0)) -> Salary | F11: 80 | G11: 0 | H11: 0 | I11: =IF(E11="Salary",INDEX('Employee Master'!I$4:I$23,MATCH(A11,'Employee Master'!A$4:A$23,0))/26,INDEX('Employee Master'!J$4:J$23,MATCH(A11,'Employee Master'!A$4:A$23,0))*F11) -> 2000 | J11: =IF(E11="Hourly",INDEX('Employee Master'!J$4:J$23,MATCH(A11,'Employee Master'!A$4:A$23,0))*G11*0.5,0) -> 0 | K11: =IF(E11="Hourly",INDEX('Employee Master'!J$4:J$23,MATCH(A11,'Employee Master'!A$4:A$23,0))*H11,0) -> 0 | L11: 0 | M11: =SUM(I11:L11) -> 2000 | N11: =IFERROR(IF(INDEX('Employee Master'!L$4:L$23,MATCH(A11,'Employee Master'!A$4:A$23,0))="MFJ",IF((M11*26)<=14600,(M11*26)*0.1,IF((M11*26)<=57750,1460+((M11*26)-14600)*0.12,IF((M11*26)<=113600,6628+((M11*26)-57750)*0.22,IF((M11*26)<=225600,18914+((M11*26)-113600)*0.24,IF((M11*26)<=537550,45794+((M11*26)-225600)*0.32,IF((M11*26)<=643450,145538+((M11*26)-537550)*0.35,182648+((M11*26)-643450)*0.37))))))/26,IF((M11*26)<=7300,(M11*26)*0.1,IF((M11*26)<=28875,730+((M11*26)-7300)*0.12,IF((M11*26)<=56875,3319+((M11*26)-28875)*0.22,IF((M11*26)<=112875,9479+((M11*26)-56875)*0.24,IF((M11*26)<=268850,23009+((M11*26)-112875)*0.32,IF((M11*26)<=321800,72937+((M11*26)-268850)*0.35,91487+((M11*26)-321800)*0.37))))))/26),0) -> 323.32692 | O11: =ROUND(M11*0.062,2) -> 124 | P11: =ROUND(M11*0.0145,2) -> 29 | Q11: =ROUND(M11*INDEX('Employee Master'!N$4:N$23,MATCH(A11,'Employee Master'!A$4:A$23,0)),2) -> 109.8 | R11: =SUM(N11:Q11) -> 586.12692 | S11: =IFERROR(INDEX('Employee Master'!O$4:O$23,MATCH(A11,'Employee Master'!A$4:A$23,0))/26,0) -> 11.346154 | T11: =IFERROR(INDEX('Employee Master'!P$4:P$23,MATCH(A11,'Employee Master'!A$4:A$23,0))/26,0) -> 1.7307692 | U11: =IFERROR(INDEX('Employee Master'!Q$4:Q$23,MATCH(A11,'Employee Master'!A$4:A$23,0))/26,0) -> 0 | V11: =ROUND(M11*IFERROR(INDEX('Employee Master'!R$4:R$23,MATCH(A11,'Employee Master'!A$4:A$23,0)),0),2) -> 60 | W11: =IFERROR(INDEX('Employee Master'!S$4:S$23,MATCH(A11,'Employee Master'!A$4:A$23,0))/26,0) -> 0.96153846 | X11: =SUM(S11:W11) -> 74.038462 | Y11: =M11-R11-X11 -> 1339.8346
A12: E-1009 | B12: =INDEX('Employee Master'!B$4:B$23,MATCH(A12,'Employee Master'!A$4:A$23,0)) -> Wilson | C12: =INDEX('Employee Master'!C$4:C$23,MATCH(A12,'Employee Master'!A$4:A$23,0)) -> James | D12: =INDEX('Employee Master'!E$4:E$23,MATCH(A12,'Employee Master'!A$4:A$23,0)) -> Operations | E12: =INDEX('Employee Master'!G$4:G$23,MATCH(A12,'Employee Master'!A$4:A$23,0)) -> Hourly | F12: 76 | G12: 5.5 | H12: 0 | I12: =IF(E12="Salary",INDEX('Employee Master'!I$4:I$23,MATCH(A12,'Employee Master'!A$4:A$23,0))/26,INDEX('Employee Master'!J$4:J$23,MATCH(A12,'Employee Master'!A$4:A$23,0))*F12) -> 1862 | J12: =IF(E12="Hourly",INDEX('Employee Master'!J$4:J$23,MATCH(A12,'Employee Master'!A$4:A$23,0))*G12*0.5,0) -> 67.375 | K12: =IF(E12="Hourly",INDEX('Employee Master'!J$4:J$23,MATCH(A12,'Employee Master'!A$4:A$23,0))*H12,0) -> 0 | L12: 0 | M12: =SUM(I12:L12) -> 1929.375 | N12: =IFERROR(IF(INDEX('Employee Master'!L$4:L$23,MATCH(A12,'Employee Master'!A$4:A$23,0))="MFJ",IF((M12*26)<=14600,(M12*26)*0.1,IF((M12*26)<=57750,1460+((M12*26)-14600)*0.12,IF((M12*26)<=113600,6628+((M12*26)-57750)*0.22,IF((M12*26)<=225600,18914+((M12*26)-113600)*0.24,IF((M12*26)<=537550,45794+((M12*26)-225600)*0.32,IF((M12*26)<=643450,145538+((M12*26)-537550)*0.35,182648+((M12*26)-643450)*0.37))))))/26,IF((M12*26)<=7300,(M12*26)*0.1,IF((M12*26)<=28875,730+((M12*26)-7300)*0.12,IF((M12*26)<=56875,3319+((M12*26)-28875)*0.22,IF((M12*26)<=112875,9479+((M12*26)-56875)*0.24,IF((M12*26)<=268850,23009+((M12*26)-112875)*0.32,IF((M12*26)<=321800,72937+((M12*26)-268850)*0.35,91487+((M12*26)-321800)*0.37))))))/26),0) -> 307.78942 | O12: =ROUND(M12*0.062,2) -> 119.62 | P12: =ROUND(M12*0.0145,2) -> 27.98 | Q12: =ROUND(M12*INDEX('Employee Master'!N$4:N$23,MATCH(A12,'Employee Master'!A$4:A$23,0)),2) -> 105.92 | R12: =SUM(N12:Q12) -> 561.30942 | S12: =IFERROR(INDEX('Employee Master'!O$4:O$23,MATCH(A12,'Employee Master'!A$4:A$23,0))/26,0) -> 11.346154 | T12: =IFERROR(INDEX('Employee Master'!P$4:P$23,MATCH(A12,'Employee Master'!A$4:A$23,0))/26,0) -> 1.7307692 | U12: =IFERROR(INDEX('Employee Master'!Q$4:Q$23,MATCH(A12,'Employee Master'!A$4:A$23,0))/26,0) -> 0.57692308 | V12: =ROUND(M12*IFERROR(INDEX('Employee Master'!R$4:R$23,MATCH(A12,'Employee Master'!A$4:A$23,0)),0),2) -> 57.88 | W12: =IFERROR(INDEX('Employee Master'!S$4:S$23,MATCH(A12,'Employee Master'!A$4:A$23,0))/26,0) -> 0.96153846 | X12: =SUM(S12:W12) -> 72.495385 | Y12: =M12-R12-X12 -> 1295.5702
A13: E-1010 | B13: =INDEX('Employee Master'!B$4:B$23,MATCH(A13,'Employee Master'!A$4:A$23,0)) -> Moore | C13: =INDEX('Employee Master'!C$4:C$23,MATCH(A13,'Employee Master'!A$4:A$23,0)) -> Patricia | D13: =INDEX('Employee Master'!E$4:E$23,MATCH(A13,'Employee Master'!A$4:A$23,0)) -> Operations | E13: =INDEX('Employee Master'!G$4:G$23,MATCH(A13,'Employee Master'!A$4:A$23,0)) -> Hourly | F13: 80 | G13: 0 | H13: 0 | I13: =IF(E13="Salary",INDEX('Employee Master'!I$4:I$23,MATCH(A13,'Employee Master'!A$4:A$23,0))/26,INDEX('Employee Master'!J$4:J$23,MATCH(A13,'Employee Master'!A$4:A$23,0))*F13) -> 1580 | J13: =IF(E13="Hourly",INDEX('Employee Master'!J$4:J$23,MATCH(A13,'Employee Master'!A$4:A$23,0))*G13*0.5,0) -> 0 | K13: =IF(E13="Hourly",INDEX('Employee Master'!J$4:J$23,MATCH(A13,'Employee Master'!A$4:A$23,0))*H13,0) -> 0 | L13: 0 | M13: =SUM(I13:L13) -> 1580 | N13: =IFERROR(IF(INDEX('Employee Master'!L$4:L$23,MATCH(A13,'Employee Master'!A$4:A$23,0))="MFJ",IF((M13*26)<=14600,(M13*26)*0.1,IF((M13*26)<=57750,1460+((M13*26)-14600)*0.12,IF((M13*26)<=113600,6628+((M13*26)-57750)*0.22,IF((M13*26)<=225600,18914+((M13*26)-113600)*0.24,IF((M13*26)<=537550,45794+((M13*26)-225600)*0.32,IF((M13*26)<=643450,145538+((M13*26)-537550)*0.35,182648+((M13*26)-643450)*0.37))))))/26,IF((M13*26)<=7300,(M13*26)*0.1,IF((M13*26)<=28875,730+((M13*26)-7300)*0.12,IF((M13*26)<=56875,3319+((M13*26)-28875)*0.22,IF((M13*26)<=112875,9479+((M13*26)-56875)*0.24,IF((M13*26)<=268850,23009+((M13*26)-112875)*0.32,IF((M13*26)<=321800,72937+((M13*26)-268850)*0.35,91487+((M13*26)-321800)*0.37))))))/26),0) -> 230.92692 | O13: =ROUND(M13*0.062,2) -> 97.96 | P13: =ROUND(M13*0.0145,2) -> 22.91 | Q13: =ROUND(M13*INDEX('Employee Master'!N$4:N$23,MATCH(A13,'Employee Master'!A$4:A$23,0)),2) -> 86.74 | R13: =SUM(N13:Q13) -> 438.53692 | S13: =IFERROR(INDEX('Employee Master'!O$4:O$23,MATCH(A13,'Employee Master'!A$4:A$23,0))/26,0) -> 11.346154 | T13: =IFERROR(INDEX('Employee Master'!P$4:P$23,MATCH(A13,'Employee Master'!A$4:A$23,0))/26,0) -> 1.7307692 | U13: =IFERROR(INDEX('Employee Master'!Q$4:Q$23,MATCH(A13,'Employee Master'!A$4:A$23,0))/26,0) -> 0 | V13: =ROUND(M13*IFERROR(INDEX('Employee Master'!R$4:R$23,MATCH(A13,'Employee Master'!A$4:A$23,0)),0),2) -> 0 | W13: =IFERROR(INDEX('Employee Master'!S$4:S$23,MATCH(A13,'Employee Master'!A$4:A$23,0))/26,0) -> 0.96153846 | X13: =SUM(S13:W13) -> 14.038462 | Y13: =M13-R13-X13 -> 1127.4246
A14: E-1011 | B14: =INDEX('Employee Master'!B$4:B$23,MATCH(A14,'Employee Master'!A$4:A$23,0)) -> Taylor | C14: =INDEX('Employee Master'!C$4:C$23,MATCH(A14,'Employee Master'!A$4:A$23,0)) -> Kevin | D14: =INDEX('Employee Master'!E$4:E$23,MATCH(A14,'Employee Master'!A$4:A$23,0)) -> Information Technology | E14: =INDEX('Employee Master'!G$4:G$23,MATCH(A14,'Employee Master'!A$4:A$23,0)) -> Salary | F14: 80 | G14: 0 | H14: 0 | I14: =IF(E14="Salary",INDEX('Employee Master'!I$4:I$23,MATCH(A14,'Employee Master'!A$4:A$23,0))/26,INDEX('Employee Master'!J$4:J$23,MATCH(A14,'Employee Master'!A$4:A$23,0))*F14) -> 4038.4615 | J14: =IF(E14="Hourly",INDEX('Employee Master'!J$4:J$23,MATCH(A14,'Employee Master'!A$4:A$23,0))*G14*0.5,0) -> 0 | K14: =IF(E14="Hourly",INDEX('Employee Master'!J$4:J$23,MATCH(A14,'Employee Master'!A$4:A$23,0))*H14,0) -> 0 | L14: 0 | M14: =SUM(I14:L14) -> 4038.4615 | N14: =IFERROR(IF(INDEX('Employee Master'!L$4:L$23,MATCH(A14,'Employee Master'!A$4:A$23,0))="MFJ",IF((M14*26)<=14600,(M14*26)*0.1,IF((M14*26)<=57750,1460+((M14*26)-14600)*0.12,IF((M14*26)<=113600,6628+((M14*26)-57750)*0.22,IF((M14*26)<=225600,18914+((M14*26)-113600)*0.24,IF((M14*26)<=537550,45794+((M14*26)-225600)*0.32,IF((M14*26)<=643450,145538+((M14*26)-537550)*0.35,182648+((M14*26)-643450)*0.37))))))/26,IF((M14*26)<=7300,(M14*26)*0.1,IF((M14*26)<=28875,730+((M14*26)-7300)*0.12,IF((M14*26)<=56875,3319+((M14*26)-28875)*0.22,IF((M14*26)<=112875,9479+((M14*26)-56875)*0.24,IF((M14*26)<=268850,23009+((M14*26)-112875)*0.32,IF((M14*26)<=321800,72937+((M14*26)-268850)*0.35,91487+((M14*26)-321800)*0.37))))))/26),0) -> 654.73077 | O14: =ROUND(M14*0.062,2) -> 250.38 | P14: =ROUND(M14*0.0145,2) -> 58.56 | Q14: =ROUND(M14*INDEX('Employee Master'!N$4:N$23,MATCH(A14,'Employee Master'!A$4:A$23,0)),2) -> 221.71 | R14: =SUM(N14:Q14) -> 1185.3808 | S14: =IFERROR(INDEX('Employee Master'!O$4:O$23,MATCH(A14,'Employee Master'!A$4:A$23,0))/26,0) -> 32.692308 | T14: =IFERROR(INDEX('Employee Master'!P$4:P$23,MATCH(A14,'Employee Master'!A$4:A$23,0))/26,0) -> 1.7307692 | U14: =IFERROR(INDEX('Employee Master'!Q$4:Q$23,MATCH(A14,'Employee Master'!A$4:A$23,0))/26,0) -> 0.57692308 | V14: =ROUND(M14*IFERROR(INDEX('Employee Master'!R$4:R$23,MATCH(A14,'Employee Master'!A$4:A$23,0)),0),2) -> 323.08 | W14: =IFERROR(INDEX('Employee Master'!S$4:S$23,MATCH(A14,'Employee Master'!A$4:A$23,0))/26,0) -> 0.96153846 | X14: =SUM(S14:W14) -> 359.04154 | Y14: =M14-R14-X14 -> 2494.0392
A15: E-1012 | B15: =INDEX('Employee Master'!B$4:B$23,MATCH(A15,'Employee Master'!A$4:A$23,0)) -> Anderson | C15: =INDEX('Employee Master'!C$4:C$23,MATCH(A15,'Employee Master'!A$4:A$23,0)) -> Lisa | D15: =INDEX('Employee Master'!E$4:E$23,MATCH(A15,'Employee Master'!A$4:A$23,0)) -> Information Technology | E15: =INDEX('Employee Master'!G$4:G$23,MATCH(A15,'Employee Master'!A$4:A$23,0)) -> Salary | F15: 80 | G15: 3 | H15: 0 | I15: =IF(E15="Salary",INDEX('Employee Master'!I$4:I$23,MATCH(A15,'Employee Master'!A$4:A$23,0))/26,INDEX('Employee Master'!J$4:J$23,MATCH(A15,'Employee Master'!A$4:A$23,0))*F15) -> 3153.8462 | J15: =IF(E15="Hourly",INDEX('Employee Master'!J$4:J$23,MATCH(A15,'Employee Master'!A$4:A$23,0))*G15*0.5,0) -> 0 | K15: =IF(E15="Hourly",INDEX('Employee Master'!J$4:J$23,MATCH(A15,'Employee Master'!A$4:A$23,0))*H15,0) -> 0 | L15: 0 | M15: =SUM(I15:L15) -> 3153.8462 | N15: =IFERROR(IF(INDEX('Employee Master'!L$4:L$23,MATCH(A15,'Employee Master'!A$4:A$23,0))="MFJ",IF((M15*26)<=14600,(M15*26)*0.1,IF((M15*26)<=57750,1460+((M15*26)-14600)*0.12,IF((M15*26)<=113600,6628+((M15*26)-57750)*0.22,IF((M15*26)<=225600,18914+((M15*26)-113600)*0.24,IF((M15*26)<=537550,45794+((M15*26)-225600)*0.32,IF((M15*26)<=643450,145538+((M15*26)-537550)*0.35,182648+((M15*26)-643450)*0.37))))))/26,IF((M15*26)<=7300,(M15*26)*0.1,IF((M15*26)<=28875,730+((M15*26)-7300)*0.12,IF((M15*26)<=56875,3319+((M15*26)-28875)*0.22,IF((M15*26)<=112875,9479+((M15*26)-56875)*0.24,IF((M15*26)<=268850,23009+((M15*26)-112875)*0.32,IF((M15*26)<=321800,72937+((M15*26)-268850)*0.35,91487+((M15*26)-321800)*0.37))))))/26),0) -> 460.11538 | O15: =ROUND(M15*0.062,2) -> 195.54 | P15: =ROUND(M15*0.0145,2) -> 45.73 | Q15: =ROUND(M15*INDEX('Employee Master'!N$4:N$23,MATCH(A15,'Employee Master'!A$4:A$23,0)),2) -> 173.15 | R15: =SUM(N15:Q15) -> 874.53538 | S15: =IFERROR(INDEX('Employee Master'!O$4:O$23,MATCH(A15,'Employee Master'!A$4:A$23,0))/26,0) -> 32.692308 | T15: =IFERROR(INDEX('Employee Master'!P$4:P$23,MATCH(A15,'Employee Master'!A$4:A$23,0))/26,0) -> 1.7307692 | U15: =IFERROR(INDEX('Employee Master'!Q$4:Q$23,MATCH(A15,'Employee Master'!A$4:A$23,0))/26,0) -> 0.57692308 | V15: =ROUND(M15*IFERROR(INDEX('Employee Master'!R$4:R$23,MATCH(A15,'Employee Master'!A$4:A$23,0)),0),2) -> 189.23 | W15: =IFERROR(INDEX('Employee Master'!S$4:S$23,MATCH(A15,'Employee Master'!A$4:A$23,0))/26,0) -> 0.96153846 | X15: =SUM(S15:W15) -> 225.19154 | Y15: =M15-R15-X15 -> 2054.1192
... A23: E-1020 | B23: =INDEX('Employee Master'!B$4:B$23,MATCH(A23,'Employee Master'!A$4:A$23,0)) -> Martinez | C23: =INDEX('Employee Master'!C$4:C$23,MATCH(A23,'Employee Master'!A$4:A$23,0)) -> Sofia | D23: =INDEX('Employee Master'!E$4:E$23,MATCH(A23,'Employee Master'!A$4:A$23,0)) -> Marketing | E23: =INDEX('Employee Master'!G$4:G$23,MATCH(A23,'Employee Master'!A$4:A$23,0)) -> Salary | F23: 80 | G23: 0 | H23: 0 | I23: =IF(E23="Salary",INDEX('Employee Master'!I$4:I$23,MATCH(A23,'Employee Master'!A$4:A$23,0))/26,INDEX('Employee Master'!J$4:J$23,MATCH(A23,'Employee Master'!A$4:A$23,0))*F23) -> 2230.7692 | J23: =IF(E23="Hourly",INDEX('Employee Master'!J$4:J$23,MATCH(A23,'Employee Master'!A$4:A$23,0))*G23*0.5,0) -> 0 | K23: =IF(E23="Hourly",INDEX('Employee Master'!J$4:J$23,MATCH(A23,'Employee Master'!A$4:A$23,0))*H23,0) -> 0 | L23: 0 | M23: =SUM(I23:L23) -> 2230.7692 | N23: =IFERROR(IF(INDEX('Employee Master'!L$4:L$23,MATCH(A23,'Employee Master'!A$4:A$23,0))="MFJ",IF((M23*26)<=14600,(M23*26)*0.1,IF((M23*26)<=57750,1460+((M23*26)-14600)*0.12,IF((M23*26)<=113600,6628+((M23*26)-57750)*0.22,IF((M23*26)<=225600,18914+((M23*26)-113600)*0.24,IF((M23*26)<=537550,45794+((M23*26)-225600)*0.32,IF((M23*26)<=643450,145538+((M23*26)-537550)*0.35,182648+((M23*26)-643450)*0.37))))))/26,IF((M23*26)<=7300,(M23*26)*0.1,IF((M23*26)<=28875,730+((M23*26)-7300)*0.12,IF((M23*26)<=56875,3319+((M23*26)-28875)*0.22,IF((M23*26)<=112875,9479+((M23*26)-56875)*0.24,IF((M23*26)<=268850,23009+((M23*26)-112875)*0.32,IF((M23*26)<=321800,72937+((M23*26)-268850)*0.35,91487+((M23*26)-321800)*0.37))))))/26),0) -> 374.96154 | O23: =ROUND(M23*0.062,2) -> 138.31 | P23: =ROUND(M23*0.0145,2) -> 32.35 | Q23: =ROUND(M23*INDEX('Employee Master'!N$4:N$23,MATCH(A23,'Employee Master'!A$4:A$23,0)),2) -> 122.47 | R23: =SUM(N23:Q23) -> 668.09154 | S23: =IFERROR(INDEX('Employee Master'!O$4:O$23,MATCH(A23,'Employee Master'!A$4:A$23,0))/26,0) -> 11.346154 | T23: =IFERROR(INDEX('Employee Master'!P$4:P$23,MATCH(A23,'Employee Master'!A$4:A$23,0))/26,0) -> 1.7307692 | U23: =IFERROR(INDEX('Employee Master'!Q$4:Q$23,MATCH(A23,'Employee Master'!A$4:A$23,0))/26,0) -> 0.57692308 | V23: =ROUND(M23*IFERROR(INDEX('Employee Master'!R$4:R$23,MATCH(A23,'Employee Master'!A$4:A$23,0)),0),2) -> 89.23 | W23: =IFERROR(INDEX('Employee Master'!S$4:S$23,MATCH(A23,'Employee Master'!A$4:A$23,0))/26,0) -> 0.96153846 | X23: =SUM(S23:W23) -> 103.84538 | Y23: =M23-R23-X23 -> 1458.8323
A24: PAYROLL TOTALS — CURRENT PERIOD | F24: =SUM(F4:F23) -> 1583 | G24: =SUM(G4:G23) -> 21 | H24: =SUM(H4:H23) -> 0 | I24: =SUM(I4:I23) -> 59110.731 | J24: =SUM(J4:J23) -> 67.375 | K24: =SUM(K4:K23) -> 0 | L24: =SUM(L4:L23) -> 4500 | M24: =SUM(M4:M23) -> 63678.106 | ... Y24: =SUM(Y4:Y23) -> 40164.22
A26: Prepared by: Muhammad Zeenat Ullah | CA Finalist (ICAP) · QBO ProAdvisor · Excel Expert | zeenatullah.bookkeeper@gmail.com | WA: +44 7577 845321
A27: Portfolio Sample — All employee names, SSNs, and company data are entirely fictitious and created solely to demonstrate financial formula expertise.

Sheet Prior YTD (Jan-May)
A1: PRIOR YEAR-TO-DATE SUMMARY | January 1 – May 31, 2026 | 10 Pay Periods Completed
A2: Verified payroll totals. Source: Payroll runs PP01–PP10. Values used by YTD Summary via cell reference formulas.
A3: Emp ID | B3: Last Name | C3: First Name | D3: Department | E3: YTD Gross | F3: YTD Fed W/H | G3: YTD SS Tax | H3: YTD Medicare | I3: YTD GA Tax | J3: YTD Total Tax | K3: YTD Health | L3: YTD Dental | M3: YTD Vision | N3: YTD 401(k) | O3: YTD Total Ded | P3: YTD Net Pay
A4: E-1001 | B4: Anderson | C4: Michael | D4: Human Resources | E4: 44230.77 | F4: 7403.85 | G4: 2742.31 | H4: 641.35 | I4: 2428.27 | J4: 13215.78 | K4: 326.92 | L4: 17.31 | M4: 5.77 | N4: 2653.85 | O4: 3013.47 | P4: 28001.52
A5: E-1002 | B5: Johnson | C5: Sarah | D5: Human Resources | E5: 30000 | F5: 5595.77 | G5: 1860 | H5: 435 | I5: 1647 | J5: 9537.77 | K5: 211.54 | L5: 17.31 | M5: 5.77 | N5: 1200 | O5: 1444.24 | P5: 19017.99
A6: E-1003 | B6: Williams | C6: David | D6: Finance | E6: 48076.92 | F6: 8326.92 | G6: 2980.77 | H6: 697.12 | I6: 2639.42 | J6: 14644.23 | K6: 326.92 | L6: 17.31 | M6: 5.77 | N6: 3846.15 | O6: 4205.77 | P6: 29226.92
A7: E-1004 | B7: Brown | C7: Jessica | D7: Finance | E7: 27692.31 | F7: 5041.92 | G7: 1716.92 | H7: 401.54 | I7: 1520.31 | J7: 8680.69 | K7: 211.54 | L7: 17.31 | M7: 5.77 | N7: 1384.62 | O7: 1628.86 | P7: 17382.76
A8: E-1005 | B8: Davis | C8: Robert | D8: Finance | E8: 21153.85 | F8: 3487.12 | G8: 1311.54 | H8: 306.73 | I8: 1161.35 | J8: 6266.74 | K8: 113.46 | L8: 17.31 | M8: 5.77 | N8: 634.62 | O8: 780.78 | P8: 14106.33
A9: E-1006 | B9: Martinez | C9: Elena | D9: Operations | E9: 36538.46 | F9: 5701.15 | G9: 2265.38 | H9: 529.81 | I9: 2005.96 | J9: 10502.3 | K9: 326.92 | L9: 17.31 | M9: 5.77 | N9: 2557.69 | O9: 2917.31 | P9: 23118.85
A10: E-1007 | B10: Garcia | C10: Carlos | D10: Operations | E10: 25000 | F10: 4395.77 | G10: 1550 | H10: 362.5 | I10: 1372.5 | J10: 7680.77 | K10: 238.46 | L10: 17.31 | M10: 5.77 | N10: 1250 | O10: 1521.16 | P10: 15798.07
A11: E-1008 | B11: Miller | C11: Amanda | D11: Operations | E11: 20000 | F11: 3233.27 | G11: 1240 | H11: 290 | I11: 1098 | J11: 5861.27 | K11: 113.46 | L11: 17.31 | M11: 0 | N11: 600 | O11: 740.39 | P11: 13398.34
A12: E-1009 | B12: Wilson | C12: James | D12: Operations | E12: 21094.5 | F12: 3474.06 | G12: 1307.86 | H12: 305.87 | I12: 1158.09 | J12: 6245.88 | K12: 113.46 | L12: 17.31 | M12: 5.77 | N12: 632.83 | O12: 778.99 | P12: 14069.63
A13: E-1010 | B13: Moore | C13: Patricia | D13: Operations | E13: 15701.25 | F13: 2287.54 | G13: 973.48 | H13: 227.67 | I13: 862 | J13: 4350.69 | K13: 113.46 | L13: 17.31 | M13: 0 | N13: 0 | O13: 140.39 | P13: 11210.17
A14: E-1011 | B14: Taylor | C14: Kevin | D14: Information Technology | E14: 40384.61 | F14: 6547.31 | G14: 2503.85 | H14: 585.58 | I14: 2217.12 | J14: 11853.86 | K14: 326.92 | L14: 17.31 | M14: 5.77 | N14: 3230.77 | O14: 3590.39 | P14: 24940.36
A15: E-1012 | B15: Anderson | C15: Lisa | D15: Information Technology | E15: 31538.46 | F15: 4601.15 | G15: 1955.38 | H15: 457.31 | I15: 1731.46 | J15: 8745.3 | K15: 326.92 | L15: 17.31 | M15: 5.77 | N15: 1892.31 | O15: 2251.93 | P15: 20541.23
... A23: E-1020 | B23: Martinez | C23: Sofia | D23: Marketing | E23: 22307.69 | F23: 3749.61 | G23: 1383.08 | H23: 323.46 | I23: 1224.69 | J23: 6680.84 | K23: 113.46 | L23: 17.31 | M23: 5.77 | N23: 892.31 | O23: 1038.47 | P23: 14588.38
A24: YTD TOTALS — JAN 1 TO MAY 31, 2026 | E24: =SUM(E4:E23) -> 608855.04 | F24: =SUM(F4:F23) -> 102378.72 | G24: =SUM(G4:G23) -> 37749.02 | H24: =SUM(H4:H23) -> 8828.42 | I24: =SUM(I4:I23) -> 33426.14 | J24: =SUM(J4:J23) -> 182382.3 | K24: =SUM(K4:K23) -> 4396.12 | L24: =SUM(L4:L23) -> 346.2 | ... P24: =SUM(P4:P23) -> 386186.72
A26: ⚠ SS WAGE BASE MONITOR (2026: $176,100): No employee has reached the SS wage base YTD through May 31. Highest earner (E-1015 White) YTD gross ~$56,000. Monitor monthly — VP-level employees may approach base by Q4.
A28: Prepared by: Muhammad Zeenat Ullah | CA Finalist (ICAP) · QBO ProAdvisor · Excel Expert | zeenatullah.bookkeeper@gmail.com | WA: +44 7577 845321
A29: Portfolio Sample — All employee names, SSNs, and company data are entirely fictitious and created solely to demonstrate financial formula expertise.

Sheet Tax Tables
A1: TAX WITHHOLDING REFERENCE | IRS Pub 15-T (2024) | ⚠ Verify against IRS Pub 15-T release for Tax Year 2026
A2: Percentage Method Tables for Automated Payroll Systems — Annual Payroll Period | Use: Annualize bi-weekly gross (×26), look up bracket, compute annual tax, divide by 26
A3: TABLE 1 — MARRIED FILING JOINTLY (MFJ)
A4: Bracket | B4: Annual Wages Over | C4: Annual Wages Not Over | D4: Base W/H Amount | E4: Marginal Rate | F4: Example (Gross/pd) | G4: Example W/H per pd
A5: Bracket 1 | B5: 0 | C5: 14600 | D5: 0 | E5: 0.1 | F5: 280.76923 | G5: 28.076923
A6: Bracket 2 | B6: 14600 | C6: 57750 | D6: 1460 | E6: 0.12 | F6: 1391.3462 | G6: 155.73077
A7: Bracket 3 | B7: 57750 | C7: 113600 | D7: 6628 | E7: 0.22 | F7: 3295.1923 | G7: 491.21154
A8: Bracket 4 | B8: 113600 | C8: 225600 | D8: 18914 | E8: 0.24 | F8: 6523.0769 | G8: 1244.3846
A9: Bracket 5 | B9: 225600 | C9: 537550 | D9: 45794 | E9: 0.32 | F9: 14675.962 | G9: 3681
A10: Bracket 6 | B10: 537550 | C10: 643450 | D10: 145538 | E10: 0.35 | F10: 22711.538 | G10: 6310.4038
A11: Bracket 7 | B11: 643450 | C11: No Limit | D11: 182648 | E11: 0.37 | F11: 26671.154 | G11: 7736.4615
A13: TABLE 2 — SINGLE / MARRIED FILING SEPARATELY / HEAD OF HOUSEHOLD (use Single table for HOH)
A14: Bracket | B14: Annual Wages Over | C14: Annual Wages Not Over | D14: Base W/H Amount | E14: Marginal Rate | F14: Example (Gross/pd) | G14: Example W/H per pd
A15: Bracket 1 | B15: 0 | C15: 7300 | D15: 0 | E15: 0.1 | F15: 140.38462 | G15: 14.038462
A16: Bracket 2 | B16: 7300 | C16: 28875 | D16: 730 | E16: 0.12 | F16: 695.67308 | G16: 77.865385
A17: Bracket 3 | B17: 28875 | C17: 56875 | D17: 3319 | E17: 0.22 | F17: 1649.0385 | G17: 246.11538
A18: Bracket 4 | B18: 56875 | C18: 112875 | D18: 9479 | E18: 0.24 | F18: 3264.4231 | G18: 623.03846
A19: Bracket 5 | B19: 112875 | C19: 268850 | D19: 23009 | E19: 0.32 | F19: 7340.8654 | G19: 1844.8077
A20: Bracket 6 | B20: 268850 | C20: 321800 | D20: 72937 | E20: 0.35 | F20: 11358.654 | G20: 3161.6635
A21: Bracket 7 | B21: 321800 | C21: No Limit | D21: 91487 | E21: 0.37 | F21: 13338.462 | G21: 3874.5
A23: TABLE 3 — FICA & GEORGIA STATE TAX RATES (2026)
A24: Tax | B24: EE Rate | C24: ER Rate | D24: Annual Wage Base | E24: Notes
A25: Social Security (OASDI) | B25: 6.20% | C25: 6.20% | D25: $176,100 | E25: Max EE + ER each: $10,918.20 (2026)
A26: Medicare (HI) | B26: 1.45% | C26: 1.45% | D26: No Limit | E26: Additional EE 0.9% on wages over $200K
A27: Additional Medicare | B27: 0.90% | C27: N/A | D27: Over $200K | E27: Employee only — NOT matched by employer
A28: FUTA (Federal Unemp.) | B28: N/A | C28: 6.00% | D28: $7,000 | E28: Net rate 0.6% with full state SUTA credit
A29: GA SUTA (State Unemp.) | B29: N/A | C29: 2.70% | D29: $9,500 | E29: New employer rate — experienced employers vary
A30: Georgia Income Tax | B30: 5.49% | C30: N/A | D30: No Limit | E30: Flat rate effective Jan 1, 2024 — no brackets
A32: Prepared by: Muhammad Zeenat Ullah | CA Finalist (ICAP) · QBO ProAdvisor · Excel Expert | zeenatullah.bookkeeper@gmail.com | WA: +44 7577 845321
A33: Portfolio Sample — All employee names, SSNs, and company data are entirely fictitious and created solely to demonstrate financial formula expertise.

Sheet Deductions Schedule
A1: BENEFITS & DEDUCTIONS SCHEDULE | Summit HR Solutions | Plan Year 2026
A2: Pre-tax deductions reduce federal/state taxable wages. Post-tax: Voluntary Life, Roth 401(k) if elected.
A3: Plan Code | B3: Plan Name | C3: Carrier | D3: Coverage | E3: Annual Premium | F3: EE Annual | G3: ER Annual | H3: EE / Pay Period | I3: ER / Pay Period | J3: Pre-Tax? | K3: Plan Type | L3: 2026 IRS Limit
A4: MED-EO | B4: Medical — Ee Only | C4: BCBS GA | D4: Employee | E4: 7700 | F4: 3120 | G4: 4580 | H4: =F4/26 -> 120 | I4: =G4/26 -> 176.15385 | J4: Yes | K4: PPO/HSA | L4: N/A
A5: MED-ES | B5: Medical — Ee+Spouse | C5: BCBS GA | D5: Ee+Spouse | E5: 14300 | F5: 7150 | G5: 7150 | H5: =F5/26 -> 275 | I5: =G5/26 -> 275 | J5: Yes | K5: PPO/HSA | L5: N/A
A6: MED-FA | B6: Medical — Family | C6: BCBS GA | D6: Family | E6: 22100 | F6: 11050 | G6: 11050 | H6: =F6/26 -> 425 | I6: =G6/26 -> 425 | J6: Yes | K6: PPO/HSA | L6: N/A
A7: DEN-1 | B7: Dental | C7: Delta Dental | D7: All | E7: 1170 | F7: 1170 | G7: 0 | H7: =F7/26 -> 45 | I7: =G7/26 -> 0 | J7: Yes | K7: PPO | L7: N/A
A8: VIS-1 | B8: Vision | C8: VSP | D8: All | E8: 390 | F8: 390 | G8: 0 | H8: =F8/26 -> 15 | I8: =G8/26 -> 0 | J8: Yes | K8: Vision | L8: N/A
A9: LIFE-B | B9: Basic Life Ins | C9: MetLife | D9: 1x Salary | E9: 650 | F9: 0 | G9: 650 | H9: =F9/26 -> 0 | I9: =G9/26 -> 25 | J9: No | K9: Group Term | L9: N/A
A10: LIFE-V | B10: Voluntary Life | C10: MetLife | D10: Elective | E10: 650 | F10: 650 | G10: 0 | H10: =F10/26 -> 25 | I10: =G10/26 -> 0 | J10: No | K10: Voluntary | L10: N/A
A11: 401K | B11: 401(k) Traditional | C11: Fidelity | D11: % of Gross | E11: Variable | F11: EE Elects | G11: 50c/$ up to 6% | H11: See Register | I11: See Register | J11: Yes | K11: ERISA | L11: $23,500 EE / $70,000 Total
A12: HSA | B12: HSA (Medical) | C12: Fidelity | D12: HDHP | E12: 4300 | F12: 2150 | G12: 2150 | H12: Variable | I12: Variable | J12: Yes | K12: Sec. 223 | L12: $4,300 single / $8,550 family
A13: FSA-H | B13: Health FSA | C13: WageWorks | D13: All | E13: 3200 | F13: 3200 | G13: 0 | H13: Variable | I13: N/A | J13: Yes | K13: Sec. 125 | L13: $3,200/year
A14: FSA-D | B14: Dep. Care FSA | C14: WageWorks | D14: All | E14: 5000 | F14: 5000 | G14: 0 | H14: Variable | I14: N/A | J14: Yes | K14: Sec. 129 | L14: $5,000/year (married)
A16: Prepared by: Muhammad Zeenat Ullah | CA Finalist (ICAP) · QBO ProAdvisor · Excel Expert | zeenatullah.bookkeeper@gmail.com | WA: +44 7577 845321
A17: Portfolio Sample — All employee names, SSNs, and company data are entirely fictitious and created solely to demonstrate financial formula expertise.

Sheet Dept Summary
A1: DEPARTMENT PAYROLL SUMMARY | Current Pay Period | SUMIFS-Powered
A2: Auto-updates when Payroll Register changes. Formula: =SUMIFS(Gross Range, Dept Range, Department Name)
A3: Department | B3: # Employees | C3: Gross Pay | D3: Fed W/H | E3: SS Tax | F3: Medicare | G3: GA Tax | H3: Total Tax | I3: Total Deductions | J3: Net Payroll
A4: Human Resources | B4: =COUNTIF('Payroll Register'!D4:D23,A4) -> 2 | C4: =SUMIFS('Payroll Register'!M4:M23,'Payroll Register'!D4:D23,A4) -> 7423.0769 | D4: =SUMIFS('Payroll Register'!N4:N23,'Payroll Register'!D4:D23,A4) -> 1299.9615 | E4: =SUMIFS('Payroll Register'!O4:O23,'Payroll Register'!D4:D23,A4) -> 460.23 | F4: =SUMIFS('Payroll Register'!P4:P23,'Payroll Register'!D4:D23,A4) -> 107.63 | G4: =SUMIFS('Payroll Register'!Q4:Q23,'Payroll Register'!D4:D23,A4) -> 407.53 | H4: =SUMIFS('Payroll Register'!R4:R23,'Payroll Register'!D4:D23,A4) -> 2275.3515 | I4: =SUMIFS('Payroll Register'!X4:X23,'Payroll Register'!D4:D23,A4) -> 444.80308 | J4: =SUMIFS('Payroll Register'!Y4:Y23,'Payroll Register'!D4:D23,A4) -> 4702.9223
A5: Finance | B5: =COUNTIF('Payroll Register'!D4:D23,A5) -> 3 | C5: =SUMIFS('Payroll Register'!M4:M23,'Payroll Register'!D4:D23,A5) -> 9692.3077 | D5: =SUMIFS('Payroll Register'!N4:N23,'Payroll Register'!D4:D23,A5) -> 1685.5962 | E5: =SUMIFS('Payroll Register'!O4:O23,'Payroll Register'!D4:D23,A5) -> 600.92 | F5: =SUMIFS('Payroll Register'!P4:P23,'Payroll Register'!D4:D23,A5) -> 140.53 | G5: =SUMIFS('Payroll Register'!Q4:Q23,'Payroll Register'!D4:D23,A5) -> 532.1 | H5: =SUMIFS('Payroll Register'!R4:R23,'Payroll Register'!D4:D23,A5) -> 2959.1462 | I5: =SUMIFS('Payroll Register'!X4:X23,'Payroll Register'!D4:D23,A5) -> 661.54 | J5: =SUMIFS('Payroll Register'!Y4:Y23,'Payroll Register'!D4:D23,A5) -> 6071.6215
A6: Operations | B6: =COUNTIF('Payroll Register'!D4:D23,A6) -> 5 | C6: =SUMIFS('Payroll Register'!M4:M23,'Payroll Register'!D4:D23,A6) -> 11663.221 | D6: =SUMIFS('Payroll Register'!N4:N23,'Payroll Register'!D4:D23,A6) -> 1871.7356 | E6: =SUMIFS('Payroll Register'!O4:O23,'Payroll Register'!D4:D23,A6) -> 723.12 | F6: =SUMIFS('Payroll Register'!P4:P23,'Payroll Register'!D4:D23,A6) -> 169.12 | G6: =SUMIFS('Payroll Register'!Q4:Q23,'Payroll Register'!D4:D23,A6) -> 640.31 | H6: =SUMIFS('Payroll Register'!R4:R23,'Payroll Register'!D4:D23,A6) -> 3404.2856 | I6: =SUMIFS('Payroll Register'!X4:X23,'Payroll Register'!D4:D23,A6) -> 604.41923 | J6: =SUMIFS('Payroll Register'!Y4:Y23,'Payroll Register'!D4:D23,A6) -> 7654.5163
A7: Information Technology | B7: =COUNTIF('Payroll Register'!D4:D23,A7) -> 4 | C7: =SUMIFS('Payroll Register'!M4:M23,'Payroll Register'!D4:D23,A7) -> 12088.923 | D7: =SUMIFS('Payroll Register'!N4:N23,'Payroll Register'!D4:D23,A7) -> 1982.6977 | E7: =SUMIFS('Payroll Register'!O4:O23,'Payroll Register'!D4:D23,A7) -> 749.51 | F7: =SUMIFS('Payroll Register'!P4:P23,'Payroll Register'!D4:D23,A7) -> 175.29 | G7: =SUMIFS('Payroll Register'!Q4:Q23,'Payroll Register'!D4:D23,A7) -> 663.69 | H7: =SUMIFS('Payroll Register'!R4:R23,'Payroll Register'!D4:D23,A7) -> 3571.1877 | I7: =SUMIFS('Payroll Register'!X4:X23,'Payroll Register'!D4:D23,A7) -> 856.01462 | J7: =SUMIFS('Payroll Register'!Y4:Y23,'Payroll Register'!D4:D23,A7) -> 7661.7208
A8: Sales | B8: =COUNTIF('Payroll Register'!D4:D23,A8) -> 4 | C8: =SUMIFS('Payroll Register'!M4:M23,'Payroll Register'!D4:D23,A8) -> 16425.962 | D8: =SUMIFS('Payroll Register'!N4:N23,'Payroll Register'!D4:D23,A8) -> 3001.5769 | E8: =SUMIFS('Payroll Register'!O4:O23,'Payroll Register'!D4:D23,A8) -> 1018.42 | F8: =SUMIFS('Payroll Register'!P4:P23,'Payroll Register'!D4:D23,A8) -> 238.18 | G8: =SUMIFS('Payroll Register'!Q4:Q23,'Payroll Register'!D4:D23,A8) -> 901.78 | H8: =SUMIFS('Payroll Register'!R4:R23,'Payroll Register'!D4:D23,A8) -> 5159.9569 | I8: =SUMIFS('Payroll Register'!X4:X23,'Payroll Register'!D4:D23,A8) -> 1211.0369 | J8: =SUMIFS('Payroll Register'!Y4:Y23,'Payroll Register'!D4:D23,A8) -> 10054.968
A9: Marketing | B9: =COUNTIF('Payroll Register'!D4:D23,A9) -> 2 | C9: =SUMIFS('Payroll Register'!M4:M23,'Payroll Register'!D4:D23,A9) -> 6384.6154 | D9: =SUMIFS('Payroll Register'!N4:N23,'Payroll Register'!D4:D23,A9) -> 1055.0769 | E9: =SUMIFS('Payroll Register'!O4:O23,'Payroll Register'!D4:D23,A9) -> 395.85 | F9: =SUMIFS('Payroll Register'!P4:P23,'Payroll Register'!D4:D23,A9) -> 92.58 | G9: =SUMIFS('Payroll Register'!Q4:Q23,'Payroll Register'!D4:D23,A9) -> 350.52 | H9: =SUMIFS('Payroll Register'!R4:R23,'Payroll Register'!D4:D23,A9) -> 1894.0269 | I9: =SUMIFS('Payroll Register'!X4:X23,'Payroll Register'!D4:D23,A9) -> 472.11692 | J9: =SUMIFS('Payroll Register'!Y4:Y23,'Payroll Register'!D4:D23,A9) -> 4018.4715
A10: GRAND TOTAL | B10: =SUM(B4:B9) -> 20 | C10: =SUM(C4:C9) -> 63678.106 | D10: =SUM(D4:D9) -> 10896.645 | E10: =SUM(E4:E9) -> 3948.05 | F10: =SUM(F4:F9) -> 923.33 | G10: =SUM(G4:G9) -> 3495.93 | H10: =SUM(H4:H9) -> 19263.955 | I10: =SUM(I4:I9) -> 4249.9308 | J10: =SUM(J4:J9) -> 40164.22
A12: Prepared by: Muhammad Zeenat Ullah | CA Finalist (ICAP) · QBO ProAdvisor · Excel Expert | zeenatullah.bookkeeper@gmail.com | WA: +44 7577 845321
A13: Portfolio Sample — All employee names, SSNs, and company data are entirely fictitious and created solely to demonstrate financial formula expertise.

Sheet Formula Library
A1: PAYROLL FORMULA LIBRARY | Summit HR Solutions | IRS Pub 15-T Compliant
A2: Formula Name | B2: Category | C2: Formula Syntax (display only — see Payroll Register for live version) | D2: Purpose | E2: Input Cells | F2: Output / Notes
A3: INDEX-MATCH Lookup | B3: Lookup | C3: INDEX(Master!B$4:B$23, MATCH(EmpID, Master!A$4:A$23, 0)) | D3: Pull any employee attribute (name, salary, rate, filing status) by Emp ID. Replaces VLOOKUP — works in any direction. | E3: Emp ID | F3: Employee field value from master table
A4: Gross Pay — Salary | B4: Earnings | C4: IF(PayType="Salary", AnnualSalary/26, HourlyRate*RegHrs) | D4: Bi-weekly gross: salary÷26 for exempt staff; rate×hours for non-exempt. Division by 26 = bi-weekly standard. | E4: Pay Type, Annual Salary, Hourly Rate, Reg Hrs | F4: Gross base pay per period
A5: OT Premium (FLSA) | B5: Earnings | C5: IF(PayType="Hourly", HourlyRate * OT_Hrs * 0.5, 0) | D5: FLSA Section 7(a) half-time premium for non-exempt hours over 40/week. Salary non-exempt uses regular rate of pay method. | E5: Pay Type, Rate, OT Hours | F5: Overtime half-time premium — add to straight-time pay
A6: Federal W/H — MFJ (CORRECT) | B6: Tax — Federal | C6: IF((Gross*26)<=14600, (Gross*26)*0.10, IF((Gross*26)<=57750, 1460+(Gross*26-14600)*0.12, ...))/26 | D6: IRS Pub 15-T 2024 Percentage Method. ANNUALIZE gross (×26), apply MFJ bracket table, divide by 26. NOT comparing gross to annual brackets directly. | E6: Gross Total (bi-weekly), Filing Status = MFJ | F6: Federal income tax withheld per period — verified against IRS tables
A7: Federal W/H — Single/HOH | B7: Tax — Federal | C7: IF((Gross*26)<=7300, (Gross*26)*0.10, IF((Gross*26)<=28875, 730+(Gross*26-7300)*0.12, ...))/26 | D7: IRS Pub 15-T 2024 Single/MFS/HOH table. Same annualize-then-lookup method. HOH uses Single table here — add separate HOH table for full accuracy. | E7: Gross Total, Filing Status = Single/HOH | F7: Federal W/H per period
A8: Social Security 6.2% | B8: Tax — FICA | C8: ROUND(GrossTotal * 0.062, 2) | D8: Employee OASDI contribution. Must stop at $176,100 annual wage base (2026). Track via YTD Summary. | E8: Gross Total | F8: SS deduction — verify YTD against wage base
A9: Medicare 1.45% | B9: Tax — FICA | C9: ROUND(GrossTotal * 0.0145, 2) | D9: Employee Medicare (HI) — no wage base limit. Add 0.9% additional on employee wages over $200K ($250K MFJ). | E9: Gross Total | F9: Medicare withholding per period
A10: Georgia State Tax 5.49% | B10: Tax — State | C10: ROUND(GrossTotal * INDEX(GA_Rate_Range, MATCH(EmpID,ID_Range,0)), 2) | D10: Georgia flat income tax rate effective January 1, 2024. No brackets — straight percentage of gross pay. | E10: Gross Total, GA Rate from Employee Master | F10: GA state withholding per period
A11: 401(k) Pre-Tax | B11: Deductions | C11: ROUND(GrossTotal * INDEX(Rate_Range, MATCH(EmpID,ID_Range,0)), 2) | D11: Employee-elected pre-tax 401(k) contribution. Reduces federal/state taxable wages. 2026 IRS limit: $23,500 ($31,000 age 50+). | E11: Gross Total, 401k Election % from Employee Master | F11: 401k deduction per period
A12: SUMIFS Department | B12: Aggregation | C12: SUMIFS(GrossRange, DeptRange, "Human Resources") | D12: Sum payroll cost by department. Fully dynamic — updates every pay run. Extend to filter by pay type, period, etc. | E12: Department column (D), Gross column (M) in Payroll Register | F12: Department gross payroll — used in Dept Summary and Dashboard
A13: YTD via SUMIFS | B13: YTD | C13: SUMIFS(Prior!E$4:E$23, Prior!A$4:A$23, EmpID) + SUMIFS(Register!M$4:M$23, Register!A$4:A$23, EmpID) | D13: Accurate YTD: sums verified Prior YTD sheet (PP01-PP10) + current period Register. NOT a simple multiply. | E13: Employee ID, Prior YTD sheet, Payroll Register | F13: True YTD gross per employee
... A15: IFERROR Guard | B15: Error Handling | C15: IFERROR(INDEX(...), 0) | D15: Wraps all lookup formulas. Returns 0 if employee ID not found. Prevents error cascade across payroll row. | E15: Any formula susceptible to lookup errors | F15: Clean zero output — keeps totals accurate
A17: Prepared by: Muhammad Zeenat Ullah | CA Finalist (ICAP) · QBO ProAdvisor · Excel Expert | zeenatullah.bookkeeper@gmail.com | WA: +44 7577 845321
A18: Portfolio Sample — All employee names, SSNs, and company data are entirely fictitious and created solely to demonstrate financial formula expertise.
