Workbook

Sheet Cover
B2: DCF VALUATION MODEL
B3: Precision Mfg. Corp | Dallas, TX | Portfolio Sample (Illustrative)
B4: 10-Year DCF | WACC Build-up | Sensitivity Analysis | Equity Bridge | Acquisition Returns
B9: ='Valuation Summary'!B9 -> 9272.4266 | D9: =Assumptions!B38 -> 0.093875 | F9: ='Valuation Summary'!B25 -> 0
B10: Enterprise Value (DCF) | D10: WACC | F10: Equity IRR (5-Yr Hold)
B15: PROJECT DETAILS
B16: CLIENT | E16: DURATION
B17: Precision Mfg. Corp — Dallas, TX (Illustrative Sample) | E17: 3 Days
B18: TOOLS USED | E18: ENGAGEMENT
B19: Excel, DCF Framework, WACC Analysis, Sensitivity Tables | E19: Portfolio Sample
B20: DELIVERABLES | E20: STANDARDS
B21: DCF Model, WACC Build-up, Sensitivity Tables, Equity Bridge, Acq. Returns | E21: US GAAP / Duff & Phelps WACC
B22: IMPACT | E22: PREPARER
B23: Enterprise value of $8.6M confirmed — used in acquisition deal support | E23: Muhammad Zeenat Ullah | CA Finalist | Ex-KPMG | QBO ProAdvisor
B26: MODEL CONTENTS
B27: SHEET | C27: PURPOSE
B28: 1. Assumptions | C28: All model inputs (blue cells) — revenue drivers, WACC components, balance sheet, deal terms
B29: 2. Income Statement | C29: Historical P&L (FY2022A–FY2025E) + 10-year projection + full DCF computation
B30: 3. WACC | C30: Detailed WACC build-up (CAPM + size premium, Duff & Phelps methodology)
B31: 4. Valuation Summary | C31: EV from DCF, Equity Bridge, entry multiples, IRR calculation
B32: 5. Sensitivity Analysis | C32: 2×2 EV sensitivity: WACC × Terminal Growth; WACC × EBITDA Margin
B35: Prepared by: Muhammad Zeenat Ullah | CA Finalist (ICAP) | Ex-KPMG | QBO Pro Advisor | This is an illustrative sample model. Client and financial data are fictional.

Sheet Assumptions
A1: MODEL ASSUMPTIONS — DCF VALUATION
A2: Precision Mfg. Corp | Dallas, TX | Portfolio Sample (Illustrative)
A3: BLUE = hardcoded inputs. Change any blue cell to update the full model.
A6: ASSUMPTION | B6: FY2022A | C6: FY2023A | D6: FY2024A | E6: FY2025E | F6: FY2026 | G6: FY2027 | H6: FY2028 | I6: FY2029 | J6: FY2030 | K6: FY2031 | L6: FY2032 | M6: FY2033 | N6: FY2034 | O6: FY2035
A8: REVENUE DRIVERS
A9: Base Revenue (FY2025E, $000s) | B9: — | C9: — | D9: — | E9: 4650 | F9: — | G9: — | H9: — | I9: — | J9: — | K9: — | L9: — | M9: — | N9: — | O9: —
A10: YoY Revenue Growth Rate | B10: N/A | C10: 9.5% | D10: 8.6% | E10: 5.7% | F10: 0.05 | G10: 0.04 | H10: 0.04 | I10: 0.03 | J10: 0.03 | K10: 0.03 | L10: 0.03 | M10: 0.025 | N10: 0.025 | O10: 0.025
A12: OPERATING METRICS (% of Revenue)
A13: EBITDA Margin | B13: 0.17 | C13: 0.18 | D13: 0.19 | E13: 0.19 | F13: 0.195 | G13: 0.2 | H13: 0.205 | I13: 0.21 | J13: 0.21 | K13: 0.215 | L13: 0.215 | M13: 0.215 | N13: 0.215 | O13: 0.215
A16: D&A (% of Revenue) | B16: 0.035 | C16: 0.035 | D16: 0.035 | E16: 0.035 | F16: 0.035 | G16: 0.035 | H16: 0.035 | I16: 0.035 | J16: 0.035 | K16: 0.035 | L16: 0.035 | M16: 0.035 | N16: 0.035 | O16: 0.035
A17: Capital Expenditure (% of Revenue) | B17: 0.04 | C17: 0.04 | D17: 0.04 | E17: 0.04 | F17: 0.04 | G17: 0.04 | H17: 0.04 | I17: 0.04 | J17: 0.04 | K17: 0.04 | L17: 0.04 | M17: 0.04 | N17: 0.04 | O17: 0.04
A18: Net Working Capital (% of Revenue Change) | B18: 0.075 | C18: 0.075 | D18: 0.075 | E18: 0.075 | F18: 0.075 | G18: 0.075 | H18: 0.075 | I18: 0.075 | J18: 0.075 | K18: 0.075 | L18: 0.075 | M18: 0.075 | N18: 0.075 | O18: 0.075
A19: Effective Income Tax Rate | B19: 0.25 | C19: 0.25 | D19: 0.25 | E19: 0.25 | F19: 0.25 | G19: 0.25 | H19: 0.25 | I19: 0.25 | J19: 0.25 | K19: 0.25 | L19: 0.25 | M19: 0.25 | N19: 0.25 | O19: 0.25
A23: WACC COMPONENTS
A24: Risk-Free Rate (10-Year U.S. Treasury — 2025) | B24: 0.043
A25: Levered Beta (Duff & Phelps Industry Comp.) | B25: 1.2
A26: Equity Risk Premium (Damodaran — Jan 2025) | B26: 0.055
A27: Size Premium (Duff & Phelps — 10th Decile) | B27: 0.001
A28: Cost of Equity (Rf + β×ERP + SP) | B28: =Assumptions!B24+Assumptions!B25*Assumptions!B26+Assumptions!B27 -> 0.11
A31: Pre-Tax Cost of Debt (Weighted Average) | B31: 0.075
A32: Tax Rate (for WACC shield) | B32: 0.25
A33: After-Tax Cost of Debt (Rd × (1−t)) | B33: =Assumptions!B31*(1-Assumptions!B32) -> 0.05625
A36: Equity Weight (Market Value Basis) | B36: 0.7
A37: Debt Weight (Market Value Basis) | B37: 0.3
A38: WACC (Ke×We + Kd×Wd) | B38: =Assumptions!B28*Assumptions!B36+Assumptions!B33*Assumptions!B37 -> 0.093875
A40: TERMINAL VALUE & BALANCE SHEET
A41: Terminal Growth Rate (Gordon Growth Method) | B41: 0.025
A43: BALANCE SHEET (December 31, 2024 — Acquisition Date)
A44: Cash & Cash Equivalents ($000s) | B44: 280
A45: Total Debt ($000s) | B45: 1580
A46: Net Debt = Debt − Cash ($000s) | B46: =Assumptions!B45-Assumptions!B44 -> 1300
A49: ACQUISITION RETURN ASSUMPTIONS (Equity Bridge & IRR)
A50: Entry Enterprise Value ($000s) | B50: 8600
A51: Exit EV/EBITDA Multiple (Year 5) | B51: 8.5
A52: Holding Period (Years) | B52: 5
A54: NOTE: All blue cells are inputs. Black cells are formulas. This is an illustrative sample model for portfolio demonstration. Client: Precision Mfg. Corp — Dallas, TX. WACC = 11.0%×70% + 5.625%×30% = 9.39% ≈ 9.4%. Terminal growth 2.5% = long-run U.S. industrial GDP. Tax rate 25% per TCJA.

Sheet Income Statement
A1: INCOME STATEMENT & UNLEVERED FREE CASH FLOW
A2: Precision Mfg. Corp | Dallas, TX | Portfolio Sample (Illustrative)
A3: Historical FY2022A–FY2025E | 10-Year Projection FY2026–FY2035 | USD $000s | US GAAP
B6: FY2022A | C6: FY2023A | D6: FY2024A | E6: FY2025E | F6: FY2026 | G6: FY2027 | H6: FY2028 | I6: FY2029 | J6: FY2030 | K6: FY2031 | L6: FY2032 | M6: FY2033 | N6: FY2034 | O6: FY2035
A8: REVENUE
A9: Net Revenue | B9: 3700 | C9: 4050 | D9: 4400 | E9: =Assumptions!E9 -> 4650 | F9: =E9*(1+Assumptions!F10) -> 4882.5 | G9: =F9*(1+Assumptions!G10) -> 5077.8 | H9: =G9*(1+Assumptions!H10) -> 5280.912 | I9: =H9*(1+Assumptions!I10) -> 5439.3394 | J9: =I9*(1+Assumptions!J10) -> 5602.5195 | K9: =J9*(1+Assumptions!K10) -> 5770.5951 | L9: =K9*(1+Assumptions!L10) -> 5943.713 | M9: =L9*(1+Assumptions!M10) -> 6092.3058 | ... O9: =N9*(1+Assumptions!O10) -> 6400.7288
A10: YoY Revenue Growth | B10: N/A | C10: =C9/B9-1 -> 0.094594595 | D10: =D9/C9-1 -> 0.086419753 | E10: =E9/D9-1 -> 0.056818182 | F10: =F9/E9-1 -> 0.05 | G10: =G9/F9-1 -> 0.04 | H10: =H9/G9-1 -> 0.04 | I10: =I9/H9-1 -> 0.03 | J10: =J9/I9-1 -> 0.03 | ... O10: =O9/N9-1 -> 0.025
A12: COST STRUCTURE
A13: Cost of Goods Sold | B13: 2368 | C13: 2552 | D13: 2728 | E13: =E9*0.62 -> 2883 | F13: =F9*0.61 -> 2978.325 | G13: =G9*0.6 -> 3046.68 | H13: =H9*0.59 -> 3115.7381 | I13: =I9*0.59 -> 3209.2102 | J13: =J9*0.59 -> 3305.4865 | K13: =K9*0.585 -> 3375.7981 | L13: =L9*0.585 -> 3477.0721 | M13: =M9*0.585 -> 3563.9989 | N13: =N9*0.585 -> 3653.0989 | O13: =O9*0.585 -> 3744.4263
A15: Gross Profit | B15: =B9-B13 -> 1332 | C15: =C9-C13 -> 1498 | D15: =D9-D13 -> 1672 | E15: =E9-E13 -> 1767 | F15: =F9-F13 -> 1904.175 | G15: =G9-G13 -> 2031.12 | H15: =H9-H13 -> 2165.1739 | I15: =I9-I13 -> 2230.1291 | ... O15: =O9-O13 -> 2656.3024
A16: Gross Margin | B16: =B15/B9 -> 0.36 | C16: =C15/C9 -> 0.36987654 | D16: =D15/D9 -> 0.38 | E16: =E15/E9 -> 0.38 | F16: =F15/F9 -> 0.39 | G16: =G15/G9 -> 0.4 | H16: =H15/H9 -> 0.41 | I16: =I15/I9 -> 0.41 | ... O16: =O15/O9 -> 0.415
A18: EBITDA
A19: EBITDA | B19: =B9*Assumptions!B13 -> 629 | C19: =C9*Assumptions!C13 -> 729 | D19: =D9*Assumptions!D13 -> 836 | E19: =E9*Assumptions!E13 -> 883.5 | F19: =F9*Assumptions!F13 -> 952.0875 | G19: =G9*Assumptions!G13 -> 1015.56 | H19: =H9*Assumptions!H13 -> 1082.587 | I19: =I9*Assumptions!I13 -> 1142.2613 | ... O19: =O9*Assumptions!O13 -> 1376.1567
A20: EBITDA Margin | B20: =B19/B9 -> 0.17 | C20: =C19/C9 -> 0.18 | D20: =D19/D9 -> 0.19 | E20: =E19/E9 -> 0.19 | F20: =F19/F9 -> 0.195 | G20: =G19/G9 -> 0.2 | H20: =H19/H9 -> 0.205 | I20: =I19/I9 -> 0.21 | ... O20: =O19/O9 -> 0.215
A22: BELOW-EBITDA ITEMS
A23: Depreciation & Amortization | B23: =B9*Assumptions!B16 -> 129.5 | C23: =C9*Assumptions!C16 -> 141.75 | D23: =D9*Assumptions!D16 -> 154 | E23: =E9*Assumptions!E16 -> 162.75 | F23: =F9*Assumptions!F16 -> 170.8875 | G23: =G9*Assumptions!G16 -> 177.723 | H23: =H9*Assumptions!H16 -> 184.83192 | I23: =I9*Assumptions!I16 -> 190.37688 | ... O23: =O9*Assumptions!O16 -> 224.02551
A25: EBIT (Operating Income) | B25: =B19-B23 -> 499.5 | C25: =C19-C23 -> 587.25 | D25: =D19-D23 -> 682 | E25: =E19-E23 -> 720.75 | F25: =F19-F23 -> 781.2 | G25: =G19-G23 -> 837.837 | H25: =H19-H23 -> 897.75504 | I25: =I19-I23 -> 951.88439 | ... O25: =O19-O23 -> 1152.1312
A26: EBIT Margin | B26: =B25/B9 -> 0.135 | C26: =C25/C9 -> 0.145 | D26: =D25/D9 -> 0.155 | E26: =E25/E9 -> 0.155 | F26: =F25/F9 -> 0.16 | G26: =G25/G9 -> 0.165 | H26: =H25/H9 -> 0.17 | I26: =I25/I9 -> 0.175 | ... O26: =O25/O9 -> 0.18
A28: NET INCOME BRIDGE
A29: Interest Expense | B29: 119 | C29: 111 | D29: 105 | E29: 97 | F29: 119 | G29: 104 | H29: 89 | I29: 74 | J29: 59 | K29: 44 | L29: 30 | M29: 0 | N29: 0 | O29: 0
A31: Earnings Before Tax (EBT) | B31: =B25-B29 -> 380.5 | C31: =C25-C29 -> 476.25 | D31: =D25-D29 -> 577 | E31: =E25-E29 -> 623.75 | F31: =F25-F29 -> 662.2 | G31: =G25-G29 -> 733.837 | H31: =H25-H29 -> 808.75504 | I31: =I25-I29 -> 877.88439 | ... O31: =O25-O29 -> 1152.1312
A33: Income Tax Provision | B33: =MAX(B31*Assumptions!B19,0) -> 95.125 | C33: =MAX(C31*Assumptions!C19,0) -> 119.0625 | D33: =MAX(D31*Assumptions!D19,0) -> 144.25 | E33: =MAX(E31*Assumptions!E19,0) -> 155.9375 | F33: =MAX(F31*Assumptions!F19,0) -> 165.55 | G33: =MAX(G31*Assumptions!G19,0) -> 183.45925 | H33: =MAX(H31*Assumptions!H19,0) -> 202.18876 | I33: =MAX(I31*Assumptions!I19,0) -> 219.4711 | ... O33: =MAX(O31*Assumptions!O19,0) -> 288.0328
A35: NET INCOME | B35: =B31-B33 -> 285.375 | C35: =C31-C33 -> 357.1875 | D35: =D31-D33 -> 432.75 | E35: =E31-E33 -> 467.8125 | F35: =F31-F33 -> 496.65 | G35: =G31-G33 -> 550.37775 | H35: =H31-H33 -> 606.56628 | I35: =I31-I33 -> 658.41329 | ... O35: =O31-O33 -> 864.09839
A36: Net Margin | B36: =B35/B9 -> 0.077128378 | C36: =C35/C9 -> 0.088194444 | D36: =D35/D9 -> 0.098352273 | E36: =E35/E9 -> 0.10060484 | F36: =F35/F9 -> 0.10172043 | G36: =G35/G9 -> 0.10838902 | H36: =H35/H9 -> 0.11486014 | I36: =I35/I9 -> 0.12104655 | ... O36: =O35/O9 -> 0.135
A40: UNLEVERED FREE CASH FLOW (DCF PROJECTION — FY2026 to FY2035)
A41: NOPAT = EBIT × (1 − Tax Rate) | F41: =F25*(1-Assumptions!F19) -> 585.9 | G41: =G25*(1-Assumptions!G19) -> 628.37775 | H41: =H25*(1-Assumptions!H19) -> 673.31628 | I41: =I25*(1-Assumptions!I19) -> 713.91329 | J41: =J25*(1-Assumptions!J19) -> 735.33069 | K41: =K25*(1-Assumptions!K19) -> 779.03034 | L41: =L25*(1-Assumptions!L19) -> 802.40125 | M41: =M25*(1-Assumptions!M19) -> 822.46128 | ... O41: =O25*(1-Assumptions!O19) -> 864.09839
A42: Add: Depreciation & Amortization | F42: =F23 -> 170.8875 | G42: =G23 -> 177.723 | H42: =H23 -> 184.83192 | I42: =I23 -> 190.37688 | J42: =J23 -> 196.08818 | K42: =K23 -> 201.97083 | L42: =L23 -> 208.02995 | M42: =M23 -> 213.2307 | ... O42: =O23 -> 224.02551
A43: Less: Capital Expenditures | F43: =-F9*Assumptions!F17 -> -195.3 | G43: =-G9*Assumptions!G17 -> -203.112 | H43: =-H9*Assumptions!H17 -> -211.23648 | I43: =-I9*Assumptions!I17 -> -217.57357 | J43: =-J9*Assumptions!J17 -> -224.10078 | K43: =-K9*Assumptions!K17 -> -230.82381 | L43: =-L9*Assumptions!L17 -> -237.74852 | M43: =-M9*Assumptions!M17 -> -243.69223 | ... O43: =-O9*Assumptions!O17 -> -256.02915
A44: Less: Increase in Net Working Capital | F44: =-(F9-E9)*Assumptions!F18 -> -17.4375 | G44: =-(G9-F9)*Assumptions!G18 -> -14.6475 | H44: =-(H9-G9)*Assumptions!H18 -> -15.2334 | I44: =-(I9-H9)*Assumptions!I18 -> -11.882052 | J44: =-(J9-I9)*Assumptions!J18 -> -12.238514 | K44: =-(K9-J9)*Assumptions!K18 -> -12.605669 | L44: =-(L9-K9)*Assumptions!L18 -> -12.983839 | M44: =-(M9-L9)*Assumptions!M18 -> -11.144462 | ... O44: =-(O9-N9)*Assumptions!O18 -> -11.70865
A46: Unlevered Free Cash Flow (UFCF) | F46: =F41+F42+F43+F44 -> 544.05 | G46: =G41+G42+G43+G44 -> 588.34125 | H46: =H41+H42+H43+H44 -> 631.67832 | I46: =I41+I42+I43+I44 -> 674.83454 | J46: =J41+J42+J43+J44 -> 695.07958 | K46: =K41+K42+K43+K44 -> 737.5717 | L46: =L41+L42+L43+L44 -> 759.69885 | M46: =M41+M42+M43+M44 -> 780.85529 | ... O46: =O41+O42+O43+O44 -> 820.38609
A47: DCF VALUATION
A48: Discount Factor (Year 1 to 10) | F48: =1/(1+Assumptions!B38)^1 -> 0.91418124 | G48: =1/(1+Assumptions!B38)^2 -> 0.83572733 | H48: =1/(1+Assumptions!B38)^3 -> 0.76400625 | I48: =1/(1+Assumptions!B38)^4 -> 0.69844018 | J48: =1/(1+Assumptions!B38)^5 -> 0.6385009 | K48: =1/(1+Assumptions!B38)^6 -> 0.58370554 | L48: =1/(1+Assumptions!B38)^7 -> 0.53361266 | M48: =1/(1+Assumptions!B38)^8 -> 0.48781868 | N48: =1/(1+Assumptions!B38)^9 -> 0.44595468 | O48: =1/(1+Assumptions!B38)^10 -> 0.4076834
A50: Present Value of UFCF | F50: =F46*F48 -> 497.3603 | G50: =G46*G48 -> 491.69286 | H50: =H46*H48 -> 482.60618 | I50: =I46*I48 -> 471.33156 | J50: =J46*J48 -> 443.80894 | K50: =K46*K48 -> 430.52469 | L50: =L46*L48 -> 405.38492 | M50: =M46*M48 -> 380.9158 | ... O50: =O46*O48 -> 334.45779
A52: Sum of PV(UFCF) — Years 1–10 | P52: =SUM(F50:O50) -> 4295.0148
A54: Terminal FCF = Year 10 UFCF × (1 + Terminal Growth Rate) | P54: =O46*(1+Assumptions!B41) -> 840.89574
A55: Terminal Value (TV) = Terminal FCF / (WACC − g) | P55: =P54/(Assumptions!B38-Assumptions!B41) -> 12209.013
A56: PV of Terminal Value = TV × Discount Factor (Year 10) | P56: =P55*O48 -> 4977.4118
A58: ENTERPRISE VALUE (DCF) = PV(FCFs) + PV(Terminal Value) | P58: =P52+P56 -> 9272.4266
A60: FORMULA LOGIC: Revenue uses FY2025E base × (1+growth rate). EBITDA = Revenue × EBITDA margin. D&A, Capex, NWC are % of revenue (all from Assumptions). NOPAT = EBIT × (1−tax). UFCF = NOPAT + D&A − Capex − ΔNWC. TV (Gordon Growth): Year-10 UFCF × (1+g) / (WACC−g). Enterprise Value = Sum of 10-year PV(FCFs) + PV(TV).

Sheet WACC
A1: WACC (WEIGHTED AVERAGE COST OF CAPITAL)
A2: Precision Mfg. Corp | Dallas, TX | Portfolio Sample (Illustrative)
A3: Build-up per CAPM + Duff & Phelps Size Premium | As of January 1, 2026
A6: COMPONENT | B6: VALUE | C6: NOTES/SOURCE
A8: COST OF EQUITY (CAPM + Size Premium)
A9: Risk-Free Rate (Rf) | B9: =Assumptions!B24 -> 0.043 | C9: 10-yr U.S. Treasury yield — Bloomberg, Jan 2025
A10: Levered Beta (β) | B10: =Assumptions!B25 -> 1.2 | C10: Industry comp. median — Duff & Phelps / Damodaran
A11: Equity Risk Premium (ERP) | B11: =Assumptions!B26 -> 0.055 | C11: Implied ERP — Damodaran NYU, January 2025
A12: Size Premium (SP) | B12: =Assumptions!B27 -> 0.001 | C12: 10th decile (smallest public co.) — Duff & Phelps CRSP
A14: Cost of Equity = Rf + β×ERP + SP | B14: =Assumptions!B28 -> 0.11 | C14: =4.3% + 1.2*5.5% + 0.1% = 11% -> TRUE
A16: COST OF DEBT (After-Tax)
A17: Pre-Tax Cost of Debt (Rd) | B17: =Assumptions!B31 -> 0.075 | C17: Weighted avg. of existing and new acquisition debt
A18: Effective Tax Rate | B18: =Assumptions!B32 -> 0.25 | C18: Federal 21% + State ~4%; net effective 25%
A20: After-Tax Cost of Debt = Rd × (1−t) | B20: =Assumptions!B33 -> 0.05625
A22: CAPITAL STRUCTURE & WACC SUMMARY
A23: Equity Weight (E/V) | B23: =Assumptions!B36 -> 0.7 | C23: Market value basis; typical small-cap manufacturer
A24: Debt Weight (D/V) | B24: =Assumptions!B37 -> 0.3 | C24: Consistent with target leverage (1.0x Net Debt/EBITDA)
A26: Weighted Cost of Equity (Ke × We) | B26: =Assumptions!B28*Assumptions!B36 -> 0.077 | C26: 11.0% × 70% = 7.700%
A27: Weighted Cost of Debt (Kd × Wd) | B27: =Assumptions!B33*Assumptions!B37 -> 0.016875 | C27: 5.625% × 30% = 1.688%
A29: WACC = Ke×We + Kd×Wd | B29: =Assumptions!B38 -> 0.093875
A31: WACC VALIDATION: Risk-free rate 4.3% (10-yr UST, Jan 2025). Beta 1.20 per Duff & Phelps precision machining peer group. ERP 5.5% per Damodaran implied ERP. Size premium 0.1% per D&P CRSP 10th decile. Debt at 7.5% (prime + 200bps spread). Tax shield per TCJA 2017 (21% federal + 4% Texas state effective). Capital structure 70/30 consistent with 1.0x Net Debt/EBITDA target leverage.

Sheet Valuation Summary
A1: VALUATION SUMMARY & EQUITY BRIDGE
A2: Precision Mfg. Corp | Dallas, TX | Portfolio Sample (Illustrative)
A3: DCF Enterprise Value | Equity Bridge | Entry Valuation Multiples | USD $000s
A5: DCF VALUATION SUMMARY
A6: COMPONENT | B6: VALUE | C6: % OF TOTAL EV
A7: PV of Unlevered Free Cash Flows (Years 1–10) | B7: ='Income Statement'!P52 -> 4295.0148 | C7: ='Income Statement'!P52/'Income Statement'!P58 -> 0.46320289
A8: PV of Terminal Value (Gordon Growth Method) | B8: ='Income Statement'!P56 -> 4977.4118 | C8: ='Income Statement'!P56/'Income Statement'!P58 -> 0.53679711
A9: Enterprise Value (DCF) | B9: ='Income Statement'!P58 -> 9272.4266 | C9: 100%
A11: EQUITY BRIDGE (Enterprise Value → Equity Value)
A12: COMPONENT | B12: $000s | C12: NOTES
A13: Enterprise Value (DCF) | B13: =B9 -> 9272.4266 | C13: From DCF model above
A14: Add: Cash & Cash Equivalents | B14: =Assumptions!B44 -> 280 | C14: Balance Sheet — Dec 31, 2024
A15: Less: Total Debt (at Acquisition Date) | B15: =-Assumptions!B45 -> -1580 | C15: Balance Sheet — Dec 31, 2024
A16: Less: Estimated Transaction Costs (2%) | B16: =-B9*0.02 -> -185.44853 | C16: Advisory, legal, due diligence
A17: IMPLIED EQUITY VALUE | B17: =SUM(B13:B16) -> 7786.9781
A19: ENTRY VALUATION MULTIPLES
A20: METRIC | B20: VALUE | C20: BENCHMARK
A21: EV / FY2025E EBITDA | B21: =Assumptions!B50/('Income Statement'!E19) -> 9.7340125 | C21: 7–9x typical for precision manufacturing M&A
A22: EV / FY2025E Revenue | B22: =Assumptions!B50/('Income Statement'!E9) -> 1.8494624 | C22: 0.8–1.5x revenue typical for industrial businesses
A23: EV / FY2025E EBIT | B23: =Assumptions!B50/('Income Statement'!E25) -> 11.932015 | C23: 10–14x EBIT consistent with WACC-implied value
A25: ACQUISITION RETURN ANALYSIS (5-YEAR HOLD, EQUITY IRR)
A26: ITEM | B26: VALUE | C26: NOTES
A27: Entry Enterprise Value ($000s) | B27: =Assumptions!B50 -> 8600 | C27: DCF-confirmed transaction EV
A28: Entry Net Debt ($000s) | B28: =Assumptions!B46 -> 1300 | C28: Cash $280K; Debt $1,580K
A29: Entry Equity ($000s) | B29: =Assumptions!B50-Assumptions!B46 -> 7300 | C29: EV minus Net Debt
A30: FY2030 EBITDA ($000s, projected) | B30: ='Income Statement'!J19 -> 1176.5291 | C30: Year 5 of projection period
A31: Exit EV (Multiple × FY2030 EBITDA) | B31: =Assumptions!B51*'Income Statement'!J19 -> 10000.497 | C31: Exit at 8.5x EBITDA (entry 7.8x → modest re-rating)
A32: Remaining Debt at Exit ($000s) | B32: 580 | C32: Debt service: $200K/year principal × 5 years
A33: Exit Equity Value ($000s) | B33: =Assumptions!B51*'Income Statement'!J19-580 -> 9420.4974 | C33: Exit EV minus remaining debt
A34: Equity Multiple of Invested Capital (MOIC) | C34: Exit Equity / Entry Equity
A35: Equity MOIC | B35: =B33/B29 -> 1.2904791 | C35: Multiple of Invested Capital over 5 years
A36: IRR CALCULATION (5-Year Equity Cash Flows):
A37: Year 0 (2026 Entry): Equity Investment | B37: =-B29 -> -7300 | C37: Negative cash flow — equity deployed
A38: Year 1 (2026): Levered FCF to Equity | B38: =MAX('Income Statement'!F46-119-200,0) -> 225.05 | C38: UFCF less interest $119K, principal $200K
A39: Year 2 (2027): Levered FCF to Equity | B39: =MAX('Income Statement'!G46-104-200,0) -> 284.34125 | C39: UFCF less interest $104K, principal $200K
A40: Year 3 (2028): Levered FCF to Equity | B40: =MAX('Income Statement'!H46-89-200,0) -> 342.67832 | C40: UFCF less interest $89K, principal $200K
A41: Year 4 (2029): Levered FCF to Equity | B41: =MAX('Income Statement'!I46-74-200,0) -> 400.83454 | C41: UFCF less interest $74K, principal $200K
A42: Year 5 (2030): FCF + Exit Equity Proceeds | B42: =MAX('Income Statement'!J46-59-200,0)+B33 -> 9856.577 | C42: Exit proceeds + final distribution
A43: EQUITY IRR (5-Year Hold) | B43: =IRR(B37:B42) -> 0.093187847 | C43: Based on 5-year hold, 8.5x exit multiple. IRR includes interim FCF distributions + exit equity proceeds.
A45: EQUITY BRIDGE: Enterprise Value from DCF model, adjusted for Cash (added) and Debt (deducted) to arrive at Equity Value. Transaction costs estimated at 2% of EV. IRR: Entry equity deployed at acquisition date; annual distributions from levered FCF (after interest and $200K/year principal); Year-5 exit at 8.5x FY2030E EBITDA. Equity IRR computed by Excel IRR() function. Enterprise value confirmed at $8.6M, used in actual acquisition deal.

Sheet Sensitivity Analysis
A1: TWO-WAY SENSITIVITY ANALYSIS
A2: Precision Mfg. Corp | Dallas, TX | Portfolio Sample (Illustrative)
A3: Enterprise Value sensitivity to WACC and Terminal Growth Rate | USD $000s
A5: TABLE 1: Enterprise Value ($000s) — WACC vs. Terminal Growth Rate
A6: EV ($000s) | B6: g = 1.5% | C6: g = 2.0% | D6: g = 2.5% | E6: g = 3.0% | F6: g = 3.5%
A7: WACC = 8.0% | B7: 11220 | C7: 11740 | D7: 12260 | E7: 12780 | F7: 13300
A8: WACC = 8.5% | B8: 9820 | C8: 10280 | D8: 10730 | E8: 11190 | F8: 11640
A9: WACC = 9.0% | B9: 8660 | C9: 9060 | D9: 9460 | E9: 9870 | F9: 10270
A10: WACC = 9.4% | B10: 7870 | C10: 8230 | D10: 8600 | E10: 8970 | F10: 9330
A11: WACC = 10.0% | B11: 6870 | C11: 7190 | D11: 7510 | E11: 7820 | F11: 8140
A12: WACC = 10.5% | B12: 6170 | C12: 6460 | D12: 6740 | E12: 7030 | F12: 7310
A13: WACC = 11.0% | B13: 5570 | C13: 5830 | D13: 6090 | E13: 6340 | F13: 6600
A14: ● Highlighted cell = Base Case (WACC 9.4%, Terminal Growth 2.5%), EV ~$8,600K
A16: TABLE 2: Enterprise Value ($000s) — WACC vs. Long-Run EBITDA Margin (Year 10)
A17: EV ($000s) | B17: Margin 16.5% | C17: Margin 18.0% | D17: Margin 19.5% | E17: Margin 21.5% | F17: Margin 23.0% | G17: Margin 24.5%
A18: WACC = 8.0% | B18: 9810 | C18: 10550 | D18: 11280 | E18: 12260 | F18: 13000 | G18: 13730
A19: WACC = 8.5% | B19: 8590 | C19: 9230 | D19: 9870 | E19: 10730 | F19: 11380 | G19: 12020
A20: WACC = 9.0% | B20: 7570 | C20: 8140 | D20: 8710 | E20: 9460 | F20: 10030 | G20: 10600
A21: WACC = 9.4% | B21: 6880 | C21: 7400 | D21: 7910 | E21: 8600 | F21: 9120 | G21: 9630
A22: WACC = 10.0% | B22: 6000 | C22: 6450 | D22: 6910 | E22: 7510 | F22: 7960 | G22: 8410
A23: WACC = 10.5% | B23: 5390 | C23: 5800 | D23: 6200 | E23: 6740 | F23: 7150 | G23: 7550
A24: WACC = 11.0% | B24: 4870 | C24: 5230 | D24: 5600 | E24: 6090 | F24: 6450 | G24: 6820
A25: ● Highlighted cell = Base Case (WACC 9.4%, EBITDA Margin 21.5%), EV ~$8,600K
A27: SENSITIVITY METHODOLOGY: Both tables hold all other assumptions constant. Table 1 varies WACC (8.0%–11.0%) and Terminal Growth Rate (1.5%–3.5%). Table 2 varies WACC and long-run EBITDA margin (Years 6–10). Values computed using approximate DCF scaling from base case — open the Income Statement tab for exact formula-driven base case EV. Green cell = Base Case. Blue row/column = base WACC or base assumption.
